Workbook

Sheet Model Cover
A1: Luxewall
A2: Paint manufacturing Company
A4: By Fasih

Sheet Assumptions
A1: Start Year | B1: 2026
D2: 2026 | E2: 2027 | F2: 2028 | G2: 2029 | H2: 2030
A4: Macroeconomics
A5: Inflation Rate - Local | D5: 0.1 | E5: 0.09 | F5: 0.08 | G5: 0.07 | H5: 0.065
A6: Inflation Rate - Foreign | D6: 0.03 | E6: 0.028 | F6: 0.026 | G6: 0.025 | H6: 0.025
A7: USD/PKR Exchange Rate | D7: 285 | E7: 295 | F7: 305 | G7: 315 | H7: 325
A8: 6M KIBOR | D8: 0.13 | E8: 0.125 | F8: 0.12 | G8: 0.115 | H8: 0.11
A9: PKR depreciation | B9: 0.06
A10: Products & Sales
B11: Unit (Drummi) | C11: 1st Yr Sales Volume | D11: 1st Yr Sales Price (PKR) | E11: 1st Yr Sales Price (USD) | H11: Unit ( Gallon) | I11: =C11 -> 1st Yr Sales Volume | J11: =D11 -> 1st Yr Sales Price (PKR) | K11: =E11 -> 1st Yr Sales Price (USD) | N11: Unit (Quarter) | O11: =I11 -> 1st Yr Sales Volume | P11: =J11 -> 1st Yr Sales Price (PKR) | Q11: =K11 -> 1st Yr Sales Price (USD)
A12: Royal Matt Emulsion paint | B12: 16L (Drummi) | C12: 25000 | D12: 16953 | E12: =D12/$D$7 -> 59.484211 | G12: =A12 -> Royal Matt Emulsion paint | H12: 4L (Gallon) | I12: 30000 | J12: 4392 | K12: =J12/$D$7 -> 15.410526 | M12: =G12 -> Royal Matt Emulsion paint | N12: 1L (Quarter) | O12: 15000 | P12: 1141 | Q12: =P12/$D$7 -> 4.0035088
A13: Anti-bacterial Interior paint | B13: 16L (Drummi) | C13: 18000 | D13: 27840 | E13: =D13/$D$7 -> 97.684211 | G13: =A13 -> Anti-bacterial Interior paint | H13: 4L (Gallon) | I13: 23000 | J13: 6960 | K13: =J13/$D$7 -> 24.421053 | M13: =G13 -> Anti-bacterial Interior paint | N13: 1L (Quarter) | O13: 13000 | P13: 1740 | Q13: =P13/$D$7 -> 6.1052632
A14: Silk emulsion | B14: 16L (Drummi) | C14: 23000 | D14: 18445 | E14: =D14/$D$7 -> 64.719298 | G14: =A14 -> Silk emulsion | H14: 4L (Gallon) | I14: 27000 | J14: 4785 | K14: =J14/$D$7 -> 16.789474 | M14: =G14 -> Silk emulsion | N14: 1L (Quarter) | O14: 17000 | P14: 1196 | Q14: =P14/$D$7 -> 4.1964912
A15: Weather resistent exterior paint | B15: 16L (Drummi) | C15: 30000 | D15: 13168 | E15: =D15/$D$7 -> 46.203509 | G15: =A15 -> Weather resistent exterior paint | H15: 4L (Gallon) | I15: 35000 | J15: 3430 | K15: =J15/$D$7 -> 12.035088 | M15: =G15 -> Weather resistent exterior paint | N15: 1L (Quarter) | O15: 25000 | P15: 930 | Q15: =P15/$D$7 -> 3.2631579
A16: Super primer | B16: 16L (Drummi) | C16: 35000 | D16: 5165 | E16: =D16/$D$7 -> 18.122807 | G16: =A16 -> Super primer | H16: 4L (Gallon) | I16: 40000 | J16: 1369 | K16: =J16/$D$7 -> 4.8035088 | M16: =G16 -> Super primer | N16: 1L (Quarter) | O16: 30000 | P16: 342 | Q16: =P16/$D$7 -> 1.2
A17: Synthetic Enamel | B17: 16L(Drummi) | C17: 40000 | D17: 15968 | E17: =D17/$D$7 -> 56.02807 | G17: =A17 -> Synthetic Enamel | H17: 4L (Gallon) | I17: 45000 | J17: 3992 | K17: =J17/$D$7 -> 14.007018 | M17: =G17 -> Synthetic Enamel | N17: 1L (Quarter) | O17: 35000 | P17: 998 | Q17: =P17/$D$7 -> 3.5017544
A19: Sales Growth Rates
C20: =+D2 -> 2026 | D20: =+E2 -> 2027 | E20: =+F2 -> 2028 | F20: =+G2 -> 2029 | G20: =+H2 -> 2030
A21: Sales Volume Growth | C21: 0 | D21: 0.9 | E21: 0.8 | F21: 0.6 | G21: 0.4
A22: Sales Price Growth (Local) | C22: 0 | D22: 0.1 | E22: 0.09 | F22: 0.08 | G22: 0.07
A23: Sales Price Growth (Export) | C23: 0 | D23: 0.03 | E23: 0.03 | F23: 0.025 | G23: 0.035
A24: Export Share | C24: 0 | D24: 0.2 | E24: 0.25 | F24: 0.25 | G24: 0.3
A26: Taxes
A27: Sales Tax Rate | C27: 0.18
A28: Income Tax Rate | C28: 0.29
A30: Costs & Expenses Assumptions
A32: DIRECT COSTS (INPUTS)
A33: RAW MATERIAL BREAKDOWN Drummi | I33: RAW MATERIAL BREAKDOWN Gallon | Q33: RAW MATERIAL BREAKDOWN Litre
A34: 1. Royal Matt Emulsion paint | B34: units | C34: 2026 PKR per drummi | D34: 2027 | E34: 2028 | F34: 2029 | G34: 2030 | I34: 1. Royal Matt Emulsion paint | J34: units | K34: 2026 PKR per gallon | L34: 2027 | M34: 2028 | N34: 2029 | O34: 2030 | Q34: 1. Royal Matt Emulsion paint | R34: units | S34: 2026 PKR per Litre | T34: 2027 | U34: 2028 | V34: 2029 | W34: 2030
A35: Water | B35: 7.2 | C35: 288 | D35: =C35*(1+E$5) -> 313.92 | E35: =D35*(1+F$5) -> 339.0336 | F35: =E35*(1+G$5) -> 362.76595 | G35: =F35*(1+H$5) -> 386.34574 | I35: Water | J35: =$B35/4 -> 1.8 | K35: =C35/4 -> 72 | L35: =D35/4 -> 78.48 | M35: =E35/4 -> 84.7584 | N35: =F35/4 -> 90.691488 | O35: =G35/4 -> 96.586435 | Q35: Water | R35: =B35/16 -> 0.45 | S35: =C35/16 -> 18 | T35: =D35/16 -> 19.62 | U35: =E35/16 -> 21.1896 | V35: =F35/16 -> 22.672872 | W35: =G35/16 -> 24.146609
A36: Calcium Carbonate | B36: 4.8 | C36: 168 | D36: =C36*(1+E$5) -> 183.12 | E36: =D36*(1+F$5) -> 197.7696 | F36: =E36*(1+G$5) -> 211.61347 | G36: =F36*(1+H$5) -> 225.36835 | I36: Calcium Carbonate | J36: =$B36/4 -> 1.2 | K36: =C36/4 -> 42 | L36: =D36/4 -> 45.78 | M36: =E36/4 -> 49.4424 | N36: =F36/4 -> 52.903368 | O36: =G36/4 -> 56.342087 | Q36: Calcium Carbonate | R36: =B36/16 -> 0.3 | S36: =C36/16 -> 10.5 | T36: =D36/16 -> 11.445 | U36: =E36/16 -> 12.3606 | V36: =F36/16 -> 13.225842 | W36: =G36/16 -> 14.085522
A37: Titanium Dioxide (imported) | B37: 1.9 | C37: 2280 | D37: =C37*(1+E$6+$B$9) -> 2480.64 | E37: =D37*(1+F$6+$B$9) -> 2693.975 | F37: =E37*(1+G$6+$B$9) -> 2922.9629 | G37: =F37*(1+H$6+$B$9) -> 3171.4148 | I37: Titanium Dioxide (imported) | J37: =$B37/4 -> 0.475 | K37: =C37/4 -> 570 | L37: =D37/4 -> 620.16 | M37: =E37/4 -> 673.49376 | N37: =F37/4 -> 730.74073 | O37: =G37/4 -> 792.85369 | Q37: Titanium Dioxide (imported) | R37: =B37/16 -> 0.11875 | S37: =C37/16 -> 142.5 | T37: =D37/16 -> 155.04 | U37: =E37/16 -> 168.37344 | V37: =F37/16 -> 182.68518 | W37: =G37/16 -> 198.21342
A38: Acrylic Binder | B38: 1.4 | C38: 910 | D38: =C38*(1+E$5) -> 991.9 | E38: =D38*(1+F$5) -> 1071.252 | F38: =E38*(1+G$5) -> 1146.2396 | G38: =F38*(1+H$5) -> 1220.7452 | I38: Acrylic Binder | J38: =$B38/4 -> 0.35 | K38: =C38/4 -> 227.5 | L38: =D38/4 -> 247.975 | M38: =E38/4 -> 267.813 | N38: =F38/4 -> 286.55991 | O38: =G38/4 -> 305.1863 | Q38: Acrylic Binder | R38: =B38/16 -> 0.0875 | S38: =C38/16 -> 56.875 | T38: =D38/16 -> 61.99375 | U38: =E38/16 -> 66.95325 | V38: =F38/16 -> 71.639978 | W38: =G38/16 -> 76.296576
A39: Other Additives | B39: 0.15 | C39: 150 | D39: =C39*(1+E$5) -> 163.5 | E39: =D39*(1+F$5) -> 176.58 | F39: =E39*(1+G$5) -> 188.9406 | G39: =F39*(1+H$5) -> 201.22174 | I39: Other Additives | J39: =$B39/4 -> 0.0375 | K39: =C39/4 -> 37.5 | L39: =D39/4 -> 40.875 | M39: =E39/4 -> 44.145 | N39: =F39/4 -> 47.23515 | O39: =G39/4 -> 50.305435 | Q39: Other Additives | R39: =B39/16 -> 0.009375 | S39: =C39/16 -> 9.375 | T39: =D39/16 -> 10.21875 | U39: =E39/16 -> 11.03625 | V39: =F39/16 -> 11.808787 | W39: =G39/16 -> 12.576359
A40: Color pigments (Imported) | B40: 0.08 | C40: 80 | D40: =C40*(1+E$6+$B$9) -> 87.04 | E40: =D40*(1+F$6+$B$9) -> 94.52544 | F40: =E40*(1+G$6+$B$9) -> 102.5601 | G40: =F40*(1+H$6+$B$9) -> 111.27771 | I40: Color pigments (Imported) | J40: =$B40/4 -> 0.02 | K40: =C40/4 -> 20 | L40: =D40/4 -> 21.76 | M40: =E40/4 -> 23.63136 | N40: =F40/4 -> 25.640026 | O40: =G40/4 -> 27.819428 | Q40: Color pigments (Imported) | R40: =B40/16 -> 0.005 | S40: =C40/16 -> 5 | T40: =D40/16 -> 5.44 | U40: =E40/16 -> 5.90784 | V40: =F40/16 -> 6.4100064 | W40: =G40/16 -> 6.9548569
A41: Total Material Cost | C41: =SUM(C35:C40) -> 3876 | D41: =SUM(D35:D40) -> 4220.12 | E41: =SUM(E35:E40) -> 4573.1357 | F41: =SUM(F35:F40) -> 4935.0827 | G41: =SUM(G35:G40) -> 5316.3735 | I41: Total Material Cost | K41: =C41/4 -> 969 | L41: =D41/4 -> 1055.03 | M41: =E41/4 -> 1143.2839 | N41: =F41/4 -> 1233.7707 | O41: =G41/4 -> 1329.0934 | Q41: Total Material Cost | S41: =SUM(S35:S40) -> 242.25 | T41: =SUM(T35:T40) -> 263.7575 | U41: =SUM(U35:U40) -> 285.82098 | V41: =SUM(V35:V40) -> 308.44267 | W41: =SUM(W35:W40) -> 332.27335
A43: 2. Anti-bacterial Interior paint | B43: =B34 -> units | C43: =C34 -> 2026 PKR per drummi | D43: =D34 -> 2027 | E43: =E34 -> 2028 | F43: =F34 -> 2029 | G43: =G34 -> 2030 | I43: 2. Anti-bacterial Interior paint | J43: =J34 -> units | K43: =K34 -> 2026 PKR per gallon | L43: =L34 -> 2027 | M43: =M34 -> 2028 | N43: =N34 -> 2029 | O43: =O34 -> 2030 | Q43: 2. Anti-bacterial Interior paint | R43: =R34 -> units | S43: =S34 -> 2026 PKR per Litre | T43: =T34 -> 2027 | U43: =U34 -> 2028 | V43: =V34 -> 2029 | W43: =W34 -> 2030
A44: Water | B44: 6.7 | C44: 268 | D44: =C44*(1+E$5) -> 292.12 | E44: =D44*(1+F$5) -> 315.4896 | F44: =E44*(1+G$5) -> 337.57387 | G44: =F44*(1+H$5) -> 359.51617 | I44: Water | J44: =$B44/4 -> 1.675 | K44: =C44/4 -> 67 | L44: =D44/4 -> 73.03 | M44: =E44/4 -> 78.8724 | N44: =F44/4 -> 84.393468 | O44: =G44/4 -> 89.879043 | Q44: Water | R44: =B44/16 -> 0.41875 | S44: =C44/16 -> 16.75 | T44: =D44/16 -> 18.2575 | U44: =E44/16 -> 19.7181 | V44: =F44/16 -> 21.098367 | W44: =G44/16 -> 22.469761
A45: Calcium Carbonate | B45: 4.2 | C45: 147 | D45: =C45*(1+E$5) -> 160.23 | E45: =D45*(1+F$5) -> 173.0484 | F45: =E45*(1+G$5) -> 185.16179 | G45: =F45*(1+H$5) -> 197.1973 | I45: Calcium Carbonate | J45: =$B45/4 -> 1.05 | K45: =C45/4 -> 36.75 | L45: =D45/4 -> 40.0575 | M45: =E45/4 -> 43.2621 | N45: =F45/4 -> 46.290447 | O45: =G45/4 -> 49.299326 | Q45: Calcium Carbonate | R45: =B45/16 -> 0.2625 | S45: =C45/16 -> 9.1875 | T45: =D45/16 -> 10.014375 | U45: =E45/16 -> 10.815525 | V45: =F45/16 -> 11.572612 | W45: =G45/16 -> 12.324832
A46: Titanium Dioxide (imported) | B46: 2.2 | C46: 2640 | D46: =C46*(1+E$6+$B$9) -> 2872.32 | E46: =D46*(1+F$6+$B$9) -> 3119.3395 | F46: =E46*(1+G$6+$B$9) -> 3384.4834 | G46: =F46*(1+H$6+$B$9) -> 3672.1645 | I46: Titanium Dioxide (imported) | J46: =$B46/4 -> 0.55 | K46: =C46/4 -> 660 | L46: =D46/4 -> 718.08 | M46: =E46/4 -> 779.83488 | N46: =F46/4 -> 846.12084 | O46: =G46/4 -> 918.04112 | Q46: Titanium Dioxide (imported) | R46: =B46/16 -> 0.1375 | S46: =C46/16 -> 165 | T46: =D46/16 -> 179.52 | U46: =E46/16 -> 194.95872 | V46: =F46/16 -> 211.53021 | W46: =G46/16 -> 229.51028
A47: Acrylic Binder | B47: 1.8 | C47: 1170 | D47: =C47*(1+E$5) -> 1275.3 | E47: =D47*(1+F$5) -> 1377.324 | F47: =E47*(1+G$5) -> 1473.7367 | G47: =F47*(1+H$5) -> 1569.5296 | I47: Acrylic Binder | J47: =$B47/4 -> 0.45 | K47: =C47/4 -> 292.5 | L47: =D47/4 -> 318.825 | M47: =E47/4 -> 344.331 | N47: =F47/4 -> 368.43417 | O47: =G47/4 -> 392.38239 | Q47: Acrylic Binder | R47: =B47/16 -> 0.1125 | S47: =C47/16 -> 73.125 | T47: =D47/16 -> 79.70625 | U47: =E47/16 -> 86.08275 | V47: =F47/16 -> 92.108542 | W47: =G47/16 -> 98.095598
A48: Anti-bacterial Additive (imported) | B48: 0.08 | C48: 200 | D48: =C48*(1+E$6+$B$9) -> 217.6 | E48: =D48*(1+F$6+$B$9) -> 236.3136 | F48: =E48*(1+G$6+$B$9) -> 256.40026 | G48: =F48*(1+H$6+$B$9) -> 278.19428 | I48: Anti-bacterial Additive (imported) | J48: =$B48/4 -> 0.02 | K48: =C48/4 -> 50 | L48: =D48/4 -> 54.4 | M48: =E48/4 -> 59.0784 | N48: =F48/4 -> 64.100064 | O48: =G48/4 -> 69.548569 | Q48: Anti-bacterial Additive (imported) | R48: =B48/16 -> 0.005 | S48: =C48/16 -> 12.5 | T48: =D48/16 -> 13.6 | U48: =E48/16 -> 14.7696 | V48: =F48/16 -> 16.025016 | W48: =G48/16 -> 17.387142
A49: Other Additives | B49: 0.13 | C49: 130 | D49: =C49*(1+E$5) -> 141.7 | E49: =D49*(1+F$5) -> 153.036 | F49: =E49*(1+G$5) -> 163.74852 | G49: =F49*(1+H$5) -> 174.39217 | I49: Other Additives | J49: =$B49/4 -> 0.0325 | K49: =C49/4 -> 32.5 | L49: =D49/4 -> 35.425 | M49: =E49/4 -> 38.259 | N49: =F49/4 -> 40.93713 | O49: =G49/4 -> 43.598043 | Q49: Other Additives | R49: =B49/16 -> 0.008125 | S49: =C49/16 -> 8.125 | T49: =D49/16 -> 8.85625 | U49: =E49/16 -> 9.56475 | V49: =F49/16 -> 10.234283 | W49: =G49/16 -> 10.899511
A50: Color pigments (imported) | B50: 0.08 | C50: 80 | D50: =C50*(1+E$6+$B$9) -> 87.04 | E50: =D50*(1+F$6+$B$9) -> 94.52544 | F50: =E50*(1+G$6+$B$9) -> 102.5601 | G50: =F50*(1+H$6+$B$9) -> 111.27771 | I50: Color pigments (imported) | J50: =$B50/4 -> 0.02 | K50: =C50/4 -> 20 | L50: =D50/4 -> 21.76 | M50: =E50/4 -> 23.63136 | N50: =F50/4 -> 25.640026 | O50: =G50/4 -> 27.819428 | Q50: Color pigments (imported) | R50: =B50/16 -> 0.005 | S50: =C50/16 -> 5 | T50: =D50/16 -> 5.44 | U50: =E50/16 -> 5.90784 | V50: =F50/16 -> 6.4100064 | W50: =G50/16 -> 6.9548569
A51: =A41 -> Total Material Cost | C51: =SUM(C44:C50) -> 4635 | D51: =SUM(D44:D50) -> 5046.31 | E51: =SUM(E44:E50) -> 5469.0766 | F51: =SUM(F44:F50) -> 5903.6646 | G51: =SUM(G44:G50) -> 6362.2717 | I51: =I41 -> Total Material Cost | K51: =C51/4 -> 1158.75 | L51: =D51/4 -> 1261.5775 | M51: =E51/4 -> 1367.2691 | N51: =F51/4 -> 1475.9161 | O51: =G51/4 -> 1590.5679 | Q51: =Q41 -> Total Material Cost | S51: =SUM(S44:S50) -> 289.6875 | T51: =SUM(T44:T50) -> 315.39438 | U51: =SUM(U44:U50) -> 341.81729 | V51: =SUM(V44:V50) -> 368.97904 | W51: =SUM(W44:W50) -> 397.64198
A53: 3.Silk emulsion | B53: =B43 -> units | C53: =C43 -> 2026 PKR per drummi | D53: =D43 -> 2027 | E53: =E43 -> 2028 | F53: =F43 -> 2029 | G53: =G43 -> 2030 | I53: 3.Silk emulsion | J53: =J43 -> units | K53: =K43 -> 2026 PKR per gallon | L53: =L43 -> 2027 | M53: =M43 -> 2028 | N53: =N43 -> 2029 | O53: =O43 -> 2030 | Q53: 3.Silk emulsion | R53: =R43 -> units | S53: =S43 -> 2026 PKR per Litre | T53: =T43 -> 2027 | U53: =U43 -> 2028 | V53: =V43 -> 2029 | W53: =W43 -> 2030
A54: Water | B54: 6.1 | C54: 244 | D54: =C54*(1+E$5) -> 265.96 | E54: =D54*(1+F$5) -> 287.2368 | F54: =E54*(1+G$5) -> 307.34338 | G54: =F54*(1+H$5) -> 327.3207 | I54: Water | J54: =B54/4 -> 1.525 | K54: =C54/4 -> 61 | L54: =D54/4 -> 66.49 | M54: =E54/4 -> 71.8092 | N54: =F54/4 -> 76.835844 | O54: =G54/4 -> 81.830174 | Q54: Water | R54: =B54/16 -> 0.38125 | S54: =K54/4 -> 15.25 | T54: =L54/4 -> 16.6225 | U54: =M54/4 -> 17.9523 | V54: =N54/4 -> 19.208961 | W54: =O54/4 -> 20.457543
A55: Calcium Carbonate | B55: 3.2 | C55: 168 | D55: =C55*(1+E$5) -> 183.12 | E55: =D55*(1+F$5) -> 197.7696 | F55: =E55*(1+G$5) -> 211.61347 | G55: =F55*(1+H$5) -> 225.36835 | I55: Calcium Carbonate | J55: =B55/4 -> 0.8 | K55: =C55/4 -> 42 | L55: =D55/4 -> 45.78 | M55: =E55/4 -> 49.4424 | N55: =F55/4 -> 52.903368 | O55: =G55/4 -> 56.342087 | Q55: Calcium Carbonate | R55: =B55/16 -> 0.2 | S55: =K55/4 -> 10.5 | T55: =L55/4 -> 11.445 | U55: =M55/4 -> 12.3606 | V55: =N55/4 -> 13.225842 | W55: =O55/4 -> 14.085522
A56: Titanium Dioxide (imported) | B56: 2.6 | C56: 3120 | D56: =C56*(1+E$6+$B$9) -> 3394.56 | E56: =D56*(1+F$6+$B$9) -> 3686.4922 | F56: =E56*(1+G$6+$B$9) -> 3999.844 | G56: =F56*(1+H$6+$B$9) -> 4339.8307 | I56: Titanium Dioxide (imported) | J56: =B56/4 -> 0.65 | K56: =C56/4 -> 780 | L56: =D56/4 -> 848.64 | M56: =E56/4 -> 921.62304 | N56: =F56/4 -> 999.961 | O56: =G56/4 -> 1084.9577 | Q56: Titanium Dioxide (imported) | R56: =B56/16 -> 0.1625 | S56: =K56/4 -> 195 | T56: =L56/4 -> 212.16 | U56: =M56/4 -> 230.40576 | V56: =N56/4 -> 249.99025 | W56: =O56/4 -> 271.23942
A57: Color pigments (imported) | B57: 0.1 | C57: 100 | D57: =C57*(1+E$5+$B$9) -> 115 | E57: =D57*(1+F$5+$B$9) -> 131.1 | F57: =E57*(1+G$5+$B$9) -> 148.143 | G57: =F57*(1+H$5+$B$9) -> 166.66088 | I57: Color pigments (imported) | J57: =B57/4 -> 0.025 | K57: =C57/4 -> 25 | L57: =D57/4 -> 28.75 | M57: =E57/4 -> 32.775 | N57: =F57/4 -> 37.03575 | O57: =G57/4 -> 41.665219 | Q57: Color pigments (imported) | R57: =B57/16 -> 0.00625 | S57: =K57/4 -> 6.25 | T57: =L57/4 -> 7.1875 | U57: =M57/4 -> 8.19375 | V57: =N57/4 -> 9.2589375 | W57: =O57/4 -> 10.416305
A58: flow and leveling additives (imported) | B58: 0.18 | C58: 216 | D58: =C58*(1+E$6+$B$9) -> 235.008 | E58: =D58*(1+F$6+$B$9) -> 255.21869 | F58: =E58*(1+G$6+$B$9) -> 276.91228 | G58: =F58*(1+H$6+$B$9) -> 300.44982 | I58: flow and leveling additives (imported) | J58: =B58/4 -> 0.045 | K58: =C58/4 -> 54 | L58: =D58/4 -> 58.752 | M58: =E58/4 -> 63.804672 | N58: =F58/4 -> 69.228069 | O58: =G58/4 -> 75.112455 | Q58: flow and leveling additives (imported) | R58: =B58/16 -> 0.01125 | S58: =K58/4 -> 13.5 | T58: =L58/4 -> 14.688 | U58: =M58/4 -> 15.951168 | V58: =N58/4 -> 17.307017 | W58: =O58/4 -> 18.778114
A59: high grade acrylic binder (imported) | B59: 2.4 | C59: 1560 | D59: =C59*(1+E$6+$B$9) -> 1697.28 | E59: =D59*(1+F$6+$B$9) -> 1843.2461 | F59: =E59*(1+G$6+$B$9) -> 1999.922 | G59: =F59*(1+H$6+$B$9) -> 2169.9154 | I59: high grade acrylic binder (imported) | J59: =B59/4 -> 0.6 | K59: =C59/4 -> 390 | L59: =D59/4 -> 424.32 | M59: =E59/4 -> 460.81152 | N59: =F59/4 -> 499.9805 | O59: =G59/4 -> 542.47884 | Q59: high grade acrylic binder (imported) | R59: =B59/16 -> 0.15 | S59: =K59/4 -> 97.5 | T59: =L59/4 -> 106.08 | U59: =M59/4 -> 115.20288 | V59: =N59/4 -> 124.99512 | W59: =O59/4 -> 135.61971
A60: =A51 -> Total Material Cost | C60: =SUM(C54:C59) -> 5408 | D60: =SUM(D54:D59) -> 5890.928 | E60: =SUM(E54:E59) -> 6401.0633 | F60: =SUM(F54:F59) -> 6943.7781 | G60: =SUM(G54:G59) -> 7529.5458 | I60: =I51 -> Total Material Cost | K60: =SUM(K54:K59) -> 1352 | L60: =SUM(L54:L59) -> 1472.732 | M60: =SUM(M54:M59) -> 1600.2658 | N60: =SUM(N54:N59) -> 1735.9445 | O60: =SUM(O54:O59) -> 1882.3865 | Q60: =Q51 -> Total Material Cost | S60: =SUM(S54:S59) -> 338 | T60: =SUM(T54:T59) -> 368.183 | U60: =SUM(U54:U59) -> 400.06646 | V60: =SUM(V54:V59) -> 433.98613 | W60: =SUM(W54:W59) -> 470.59661
A62: 4.Weather resistent exterior paint | B62: =B53 -> units | C62: =C53 -> 2026 PKR per drummi | D62: =D53 -> 2027 | E62: =E53 -> 2028 | F62: =F53 -> 2029 | G62: =G53 -> 2030 | I62: 4.Weather resistent exterior paint | J62: =J53 -> units | K62: =K53 -> 2026 PKR per gallon | L62: =L53 -> 2027 | M62: =M53 -> 2028 | N62: =N53 -> 2029 | O62: =O53 -> 2030 | Q62: 4.Weather resistent exterior paint | R62: =R53 -> units | S62: =S53 -> 2026 PKR per Litre | T62: =T53 -> 2027 | U62: =U53 -> 2028 | V62: =V53 -> 2029 | W62: =W53 -> 2030
A63: Water | B63: 6.1 | C63: 244 | D63: =C63*(1+E$5) -> 265.96 | E63: =D63*(1+F$5) -> 287.2368 | F63: =E63*(1+G$5) -> 307.34338 | G63: =F63*(1+H$5) -> 327.3207 | I63: Water | J63: =B63/4 -> 1.525 | K63: =C63/4 -> 61 | L63: =D63/4 -> 66.49 | M63: =E63/4 -> 71.8092 | N63: =F63/4 -> 76.835844 | O63: =G63/4 -> 81.830174 | Q63: Water | R63: =J63/4 -> 0.38125 | S63: =K63/4 -> 15.25 | T63: =L63/4 -> 16.6225 | U63: =M63/4 -> 17.9523 | V63: =N63/4 -> 19.208961 | W63: =O63/4 -> 20.457543
A64: Calcium Carbonate | B64: 3.2 | C64: 112 | D64: =C64*(1+E$5) -> 122.08 | E64: =D64*(1+F$5) -> 131.8464 | F64: =E64*(1+G$5) -> 141.07565 | G64: =F64*(1+H$5) -> 150.24557 | I64: Calcium Carbonate | J64: =B64/4 -> 0.8 | K64: =C64/4 -> 28 | L64: =D64/4 -> 30.52 | M64: =E64/4 -> 32.9616 | N64: =F64/4 -> 35.268912 | O64: =G64/4 -> 37.561391 | Q64: Calcium Carbonate | R64: =J64/4 -> 0.2 | S64: =K64/4 -> 7 | T64: =L64/4 -> 7.63 | U64: =M64/4 -> 8.2404 | V64: =N64/4 -> 8.817228 | W64: =O64/4 -> 9.3903478
A65: Titanium Dioxide (Imported) | B65: 2.6 | C65: 3120 | D65: =C65*(1+E$6+$B$9) -> 3394.56 | E65: =D65*(1+F$6+$B$9) -> 3686.4922 | F65: =E65*(1+G$6+$B$9) -> 3999.844 | G65: =F65*(1+H$6+$B$9) -> 4339.8307 | I65: Titanium Dioxide (Imported) | J65: =B65/4 -> 0.65 | K65: =C65/4 -> 780 | L65: =D65/4 -> 848.64 | M65: =E65/4 -> 921.62304 | N65: =F65/4 -> 999.961 | O65: =G65/4 -> 1084.9577 | Q65: Titanium Dioxide (Imported) | R65: =J65/4 -> 0.1625 | S65: =K65/4 -> 195 | T65: =L65/4 -> 212.16 | U65: =M65/4 -> 230.40576 | V65: =N65/4 -> 249.99025 | W65: =O65/4 -> 271.23942
A66: Color pigments (imported) | B66: 0.1 | C66: 100 | D66: =C66*(1+E$6+$B$9) -> 108.8 | E66: =D66*(1+F$6+$B$9) -> 118.1568 | F66: =E66*(1+G$6+$B$9) -> 128.20013 | G66: =F66*(1+H$6+$B$9) -> 139.09714 | I66: Color pigments (imported) | J66: =B66/4 -> 0.025 | K66: =C66/4 -> 25 | L66: =D66/4 -> 27.2 | M66: =E66/4 -> 29.5392 | N66: =F66/4 -> 32.050032 | O66: =G66/4 -> 34.774285 | Q66: Color pigments (imported) | R66: =J66/4 -> 0.00625 | S66: =K66/4 -> 6.25 | T66: =L66/4 -> 6.8 | U66: =M66/4 -> 7.3848 | V66: =N66/4 -> 8.012508 | W66: =O66/4 -> 8.6935712
A67: UV/Weather additive (imported) | B67: 0.16 | C67: 160 | D67: =C67*(1+E$6+$B$9) -> 174.08 | E67: =D67*(1+F$6+$B$9) -> 189.05088 | F67: =E67*(1+G$6+$B$9) -> 205.1202 | G67: =F67*(1+H$6+$B$9) -> 222.55542 | I67: UV/Weather additive (imported) | J67: =B67/4 -> 0.04 | K67: =C67/4 -> 40 | L67: =D67/4 -> 43.52 | M67: =E67/4 -> 47.26272 | N67: =F67/4 -> 51.280051 | O67: =G67/4 -> 55.638856 | Q67: UV/Weather additive (imported) | R67: =J67/4 -> 0.01 | S67: =K67/4 -> 10 | T67: =L67/4 -> 10.88 | U67: =M67/4 -> 11.81568 | V67: =N67/4 -> 12.820013 | W67: =O67/4 -> 13.909714
A68: Styrene Acrylic Binder (imported) | B68: 2.2 | C68: 1540 | D68: =C68*(1+E$6+$B$9) -> 1675.52 | E68: =D68*(1+F$6+$B$9) -> 1819.6147 | F68: =E68*(1+G$6+$B$9) -> 1974.282 | G68: =F68*(1+H$6+$B$9) -> 2142.0959 | I68: Styrene Acrylic Binder (imported) | J68: =B68/4 -> 0.55 | K68: =C68/4 -> 385 | L68: =D68/4 -> 418.88 | M68: =E68/4 -> 454.90368 | N68: =F68/4 -> 493.57049 | O68: =G68/4 -> 535.52398 | Q68: Styrene Acrylic Binder (imported) | R68: =J68/4 -> 0.1375 | S68: =K68/4 -> 96.25 | T68: =L68/4 -> 104.72 | U68: =M68/4 -> 113.72592 | V68: =N68/4 -> 123.39262 | W68: =O68/4 -> 133.881
A69: =A60 -> Total Material Cost | C69: =SUM(C63:C68) -> 5276 | D69: =SUM(D63:D68) -> 5741 | E69: =SUM(E63:E68) -> 6232.3978 | F69: =SUM(F63:F68) -> 6755.8653 | G69: =SUM(G63:G68) -> 7321.1455 | I69: =I60 -> Total Material Cost | K69: =SUM(K63:K68) -> 1319 | L69: =SUM(L63:L68) -> 1435.25 | M69: =SUM(M63:M68) -> 1558.0994 | N69: =SUM(N63:N68) -> 1688.9663 | O69: =SUM(O63:O68) -> 1830.2864 | Q69: =Q60 -> Total Material Cost | S69: =SUM(S63:S68) -> 329.75 | T69: =SUM(T63:T68) -> 358.8125 | U69: =SUM(U63:U68) -> 389.52486 | V69: =SUM(V63:V68) -> 422.24158 | W69: =SUM(W63:W68) -> 457.57159
A71: 5.Super primer | B71: =B62 -> units | C71: =C62 -> 2026 PKR per drummi | D71: =D62 -> 2027 | E71: =E62 -> 2028 | F71: =F62 -> 2029 | G71: =G62 -> 2030 | I71: 5.Super primer | J71: =J62 -> units | K71: =K62 -> 2026 PKR per gallon | L71: =L62 -> 2027 | M71: =M62 -> 2028 | N71: =N62 -> 2029 | O71: =O62 -> 2030 | Q71: 5.Super primer | R71: =R62 -> units | S71: =S62 -> 2026 PKR per Litre | T71: =T62 -> 2027 | U71: =U62 -> 2028 | V71: =V62 -> 2029 | W71: =W62 -> 2030
A72: Water | B72: 8 | C72: 320 | D72: =C72*(1+E$5) -> 348.8 | E72: =D72*(1+F$5) -> 376.704 | F72: =E72*(1+G$5) -> 403.07328 | G72: =F72*(1+H$5) -> 429.27304 | I72: Water | J72: =B72/4 -> 2 | K72: =C72/4 -> 80 | L72: =D72/4 -> 87.2 | M72: =E72/4 -> 94.176 | N72: =F72/4 -> 100.76832 | O72: =G72/4 -> 107.31826 | Q72: Water | R72: =J72/4 -> 0.5 | S72: =K72/4 -> 20 | T72: =L72/4 -> 21.8 | U72: =M72/4 -> 23.544 | V72: =N72/4 -> 25.19208 | W72: =O72/4 -> 26.829565
A73: Calcium Carbonate | B73: 5.6 | C73: 196 | D73: =C73*(1+E$5) -> 213.64 | E73: =D73*(1+F$5) -> 230.7312 | F73: =E73*(1+G$5) -> 246.88238 | G73: =F73*(1+H$5) -> 262.92974 | I73: Calcium Carbonate | J73: =B73/4 -> 1.4 | K73: =C73/4 -> 49 | L73: =D73/4 -> 53.41 | M73: =E73/4 -> 57.6828 | N73: =F73/4 -> 61.720596 | O73: =G73/4 -> 65.732435 | Q73: Calcium Carbonate | R73: =J73/4 -> 0.35 | S73: =K73/4 -> 12.25 | T73: =L73/4 -> 13.3525 | U73: =M73/4 -> 14.4207 | V73: =N73/4 -> 15.430149 | W73: =O73/4 -> 16.433109
A74: Titanium Dioxide (imported) | B74: 1.3 | C74: 1560 | D74: =C74*(1+E$6+$B$9) -> 1697.28 | E74: =D74*(1+F$6+$B$9) -> 1843.2461 | F74: =E74*(1+G$6+$B$9) -> 1999.922 | G74: =F74*(1+H$6+$B$9) -> 2169.9154 | I74: Titanium Dioxide (imported) | J74: =B74/4 -> 0.325 | K74: =C74/4 -> 390 | L74: =D74/4 -> 424.32 | M74: =E74/4 -> 460.81152 | N74: =F74/4 -> 499.9805 | O74: =G74/4 -> 542.47884 | Q74: Titanium Dioxide (imported) | R74: =J74/4 -> 0.08125 | S74: =K74/4 -> 97.5 | T74: =L74/4 -> 106.08 | U74: =M74/4 -> 115.20288 | V74: =N74/4 -> 124.99512 | W74: =O74/4 -> 135.61971
A75: Acrylic Binder | B75: 1.1 | C75: 715 | D75: =C75*(1+E$5) -> 779.35 | E75: =D75*(1+F$5) -> 841.698 | F75: =E75*(1+G$5) -> 900.61686 | G75: =F75*(1+H$5) -> 959.15696 | I75: Acrylic Binder | J75: =B75/4 -> 0.275 | K75: =C75/4 -> 178.75 | L75: =D75/4 -> 194.8375 | M75: =E75/4 -> 210.4245 | N75: =F75/4 -> 225.15421 | O75: =G75/4 -> 239.78924 | Q75: Acrylic Binder | R75: =J75/4 -> 0.06875 | S75: =K75/4 -> 44.6875 | T75: =L75/4 -> 48.709375 | U75: =M75/4 -> 52.606125 | V75: =N75/4 -> 56.288554 | W75: =O75/4 -> 59.94731
A76: Other Additives | B76: 0.12 | C76: 120 | D76: =C76*(1+E$5) -> 130.8 | E76: =D76*(1+F$5) -> 141.264 | F76: =E76*(1+G$5) -> 151.15248 | G76: =F76*(1+H$5) -> 160.97739 | I76: Other Additives | J76: =B76/4 -> 0.03 | K76: =C76/4 -> 30 | L76: =D76/4 -> 32.7 | M76: =E76/4 -> 35.316 | N76: =F76/4 -> 37.78812 | O76: =G76/4 -> 40.244348 | Q76: Other Additives | R76: =J76/4 -> 0.0075 | S76: =K76/4 -> 7.5 | T76: =L76/4 -> 8.175 | U76: =M76/4 -> 8.829 | V76: =N76/4 -> 9.44703 | W76: =O76/4 -> 10.061087
A77: =A85 -> Total Material Cost | C77: =SUM(C72:C76) -> 2911 | D77: =SUM(D72:D76) -> 3169.87 | E77: =SUM(E72:E76) -> 3433.6433 | F77: =SUM(F72:F76) -> 3701.647 | G77: =SUM(G72:G76) -> 3982.2525 | I77: =I85 -> Total Material Cost | K77: =SUM(K72:K76) -> 727.75 | L77: =SUM(L72:L76) -> 792.4675 | M77: =SUM(M72:M76) -> 858.41082 | N77: =SUM(N72:N76) -> 925.41175 | O77: =SUM(O72:O76) -> 995.56312 | Q77: =Q85 -> Total Material Cost | S77: =SUM(S72:S76) -> 181.9375 | T77: =SUM(T72:T76) -> 198.11687 | U77: =SUM(U72:U76) -> 214.6027 | V77: =SUM(V72:V76) -> 231.35294 | W77: =SUM(W72:W76) -> 248.89078
A79: 6.Synthetic Enamel | B79: =B71 -> units | C79: =C71 -> 2026 PKR per drummi | D79: =D71 -> 2027 | E79: =E71 -> 2028 | F79: =F71 -> 2029 | G79: =G71 -> 2030 | I79: 6.Synthetic Enamel | J79: =J71 -> units | K79: =K71 -> 2026 PKR per gallon | L79: =L71 -> 2027 | M79: =M71 -> 2028 | N79: =N71 -> 2029 | O79: =O71 -> 2030 | Q79: 6.Synthetic Enamel | R79: =R71 -> units | S79: =S71 -> 2026 PKR per Litre | T79: =T71 -> 2027 | U79: =U71 -> 2028 | V79: =V71 -> 2029 | W79: =W71 -> 2030
A80: Titanium Dioxide (imported) | B80: 2.3 | C80: 2760 | D80: =C80*(1+E$6+$B$9) -> 3002.88 | E80: =D80*(1+F$6+$B$9) -> 3261.1277 | F80: =E80*(1+G$6+$B$9) -> 3538.3235 | G80: =F80*(1+H$6+$B$9) -> 3839.081 | I80: Titanium Dioxide (imported) | J80: =B80/4 -> 0.575 | K80: =C80/4 -> 690 | L80: =D80/4 -> 750.72 | M80: =E80/4 -> 815.28192 | N80: =F80/4 -> 884.58088 | O80: =N80*(1+P$6+$B$9) -> 937.65574 | Q80: Titanium Dioxide (imported) | R80: =J80/4 -> 0.14375 | S80: =K80/4 -> 172.5 | T80: =L80/4 -> 187.68 | U80: =M80/4 -> 203.82048 | V80: =N80/4 -> 221.14522 | W80: =V80*(1+X$6+$B$9) -> 234.41393
A81: Other Additives | B81: 0.2 | C81: 200 | D81: =C81*(1+$D$5) -> 220 | E81: =D81*(1+$D$5) -> 242 | F81: =E81*(1+$D$5) -> 266.2 | G81: =F81*(1+$D$5) -> 292.82 | I81: Other Additives | J81: =B81/4 -> 0.05 | K81: =C81/4 -> 50 | L81: =D81/4 -> 55 | M81: =E81/4 -> 60.5 | N81: =F81/4 -> 66.55 | O81: =N81*(1+$D$5) -> 73.205 | Q81: Other Additives | R81: =J81/4 -> 0.0125 | S81: =K81/4 -> 12.5 | T81: =L81/4 -> 13.75 | U81: =M81/4 -> 15.125 | V81: =N81/4 -> 16.6375 | W81: =V81*(1+$D$5) -> 18.30125
A82: Color pigments (imported) | B82: 0.15 | C82: 150 | D82: =C82*(1+E$6+$B$9) -> 163.2 | E82: =D82*(1+F$6+$B$9) -> 177.2352 | F82: =E82*(1+G$6+$B$9) -> 192.30019 | G82: =F82*(1+H$6+$B$9) -> 208.64571 | I82: Color pigments (imported) | J82: =B82/4 -> 0.0375 | K82: =C82/4 -> 37.5 | L82: =D82/4 -> 40.8 | M82: =E82/4 -> 44.3088 | N82: =F82/4 -> 48.075048 | O82: =N82*(1+P$6+$B$9) -> 50.959551 | Q82: Color pigments (imported) | R82: =J82/4 -> 0.009375 | S82: =K82/4 -> 9.375 | T82: =L82/4 -> 10.2 | U82: =M82/4 -> 11.0772 | V82: =N82/4 -> 12.018762 | W82: =V82*(1+X$6+$B$9) -> 12.739888
A83: Solvent ( Mineral Turpentine/Xylene) (imported) | B83: 5.6 | C83: 1680 | D83: =C83*(1+E$6+$B$9) -> 1827.84 | E83: =D83*(1+F$6+$B$9) -> 1985.0342 | F83: =E83*(1+G$6+$B$9) -> 2153.7622 | G83: =F83*(1+H$6+$B$9) -> 2336.8319 | I83: Solvent ( Mineral Turpentine/Xylene) (imported) | J83: =B83/4 -> 1.4 | K83: =C83/4 -> 420 | L83: =D83/4 -> 456.96 | M83: =E83/4 -> 496.25856 | N83: =F83/4 -> 538.44054 | O83: =N83*(1+P$6+$B$9) -> 570.74697 | Q83: Solvent ( Mineral Turpentine/Xylene) (imported) | R83: =J83/4 -> 0.35 | S83: =K83/4 -> 105 | T83: =L83/4 -> 114.24 | U83: =M83/4 -> 124.06464 | V83: =N83/4 -> 134.61013 | W83: =V83*(1+X$6+$B$9) -> 142.68674
A84: Alkyd resin (imported) | B84: 4.8 | C84: 2880 | D84: =C84*(1+E$6+$B$9) -> 3133.44 | E84: =D84*(1+F$6+$B$9) -> 3402.9158 | F84: =E84*(1+G$6+$B$9) -> 3692.1637 | G84: =F84*(1+H$6+$B$9) -> 4005.9976 | I84: Alkyd resin (imported) | J84: =B84/4 -> 1.2 | K84: =C84/4 -> 720 | L84: =D84/4 -> 783.36 | M84: =E84/4 -> 850.72896 | N84: =F84/4 -> 923.04092 | O84: =N84*(1+P$6+$B$9) -> 978.42338 | Q84: Alkyd resin (imported) | R84: =J84/4 -> 0.3 | S84: =K84/4 -> 180 | T84: =L84/4 -> 195.84 | U84: =M84/4 -> 212.68224 | V84: =N84/4 -> 230.76023 | W84: =V84*(1+X$6+$B$9) -> 244.60584
A85: =A69 -> Total Material Cost | C85: =SUM(C80:C84) -> 7670 | D85: =SUM(D80:D84) -> 8347.36 | E85: =SUM(E80:E84) -> 9068.313 | F85: =SUM(F80:F84) -> 9842.7496 | G85: =SUM(G80:G84) -> 10683.376 | I85: =I69 -> Total Material Cost | K85: =SUM(K80:K84) -> 1917.5 | L85: =SUM(L80:L84) -> 2086.84 | M85: =SUM(M80:M84) -> 2267.0782 | N85: =SUM(N80:N84) -> 2460.6874 | O85: =SUM(O80:O84) -> 2610.9906 | Q85: =Q69 -> Total Material Cost | S85: =SUM(S80:S84) -> 479.375 | T85: =SUM(T80:T84) -> 521.71 | U85: =SUM(U80:U84) -> 566.76956 | V85: =SUM(V80:V84) -> 615.17185 | W85: =SUM(W80:W84) -> 652.74766
A88: Labor Cost
A90: DL Utilization per Product | B90: Manhours (Drummi) | C90: Manhours (gallon) | D90: Manhours (litre)
A91: =A12 -> Royal Matt Emulsion paint | B91: 0.5 | C91: =B91/4 -> 0.125 | D91: =B91/16 -> 0.03125
A92: =A13 -> Anti-bacterial Interior paint | B92: 0.9 | C92: =B92/4 -> 0.225 | D92: =B92/16 -> 0.05625
A93: =A14 -> Silk emulsion | B93: 0.6 | C93: =B93/4 -> 0.15 | D93: =B93/16 -> 0.0375
A94: =A15 -> Weather resistent exterior paint | B94: 0.7 | C94: =B94/4 -> 0.175 | D94: =B94/16 -> 0.04375
A95: =A16 -> Super primer | B95: 0.4 | C95: =B95/4 -> 0.1 | D95: =B95/16 -> 0.025
A96: =A17 -> Synthetic Enamel | B96: 0.8 | C96: =B96/4 -> 0.2 | D96: =B96/16 -> 0.05
A98: Manhour Cost | B98: =D2 -> 2026 | C98: =E2 -> 2027 | D98: =F2 -> 2028 | E98: =G2 -> 2029 | F98: =H2 -> 2030
A99: Cost per Hour (PKR) | B99: 250 | C99: =B99*(1+E$5) -> 272.5 | D99: =C99*(1+F$5) -> 294.3 | E99: =D99*(1+G$5) -> 314.901 | F99: =E99*(1+H$5) -> 335.36957
A101: Packaging and labeling cost per product PKR Drummi | B101: =D2 -> 2026 | C101: =E2 -> 2027 | D101: =F2 -> 2028 | E101: =G2 -> 2029 | F101: =H2 -> 2030 | H101: Packaging and labeling cost per product PKR gallon | I101: =B101 -> 2026 | J101: =C101 -> 2027 | K101: =D101 -> 2028 | L101: =E101 -> 2029 | M101: =F101 -> 2030 | O101: Packaging and labeling cost per product PKR Litre | P101: =I101 -> 2026 | Q101: =J101 -> 2027 | R101: =K101 -> 2028 | S101: =L101 -> 2029 | T101: =M101 -> 2030
A102: =A91 -> Royal Matt Emulsion paint | B102: 400 | C102: =B102*(1+E$5) -> 436 | D102: =C102*(1+F$5) -> 470.88 | E102: =D102*(1+G$5) -> 503.8416 | F102: =E102*(1+H$5) -> 536.5913 | H102: =A102 -> Royal Matt Emulsion paint | I102: 350 | J102: =I102*(1+E$5) -> 381.5 | K102: =J102*(1+F$5) -> 412.02 | L102: =K102*(1+G$5) -> 440.8614 | M102: =L102*(1+H$5) -> 469.51739 | O102: =H102 -> Royal Matt Emulsion paint | P102: 88 | Q102: =P102*(1+E$5) -> 95.92 | R102: =Q102*(1+F$5) -> 103.5936 | S102: =R102*(1+G$5) -> 110.84515 | T102: =S102*(1+H$5) -> 118.05009
A103: =A92 -> Anti-bacterial Interior paint | B103: 420 | C103: =B103*(1+E$5) -> 457.8 | D103: =C103*(1+F$5) -> 494.424 | E103: =D103*(1+G$5) -> 529.03368 | F103: =E103*(1+H$5) -> 563.42087 | H103: =A103 -> Anti-bacterial Interior paint | I103: 368 | J103: =I103*(1+E$5) -> 401.12 | K103: =J103*(1+F$5) -> 433.2096 | L103: =K103*(1+G$5) -> 463.53427 | M103: =L103*(1+H$5) -> 493.664 | O103: =H103 -> Anti-bacterial Interior paint | P103: 92 | Q103: =P103*(1+E$5) -> 100.28 | R103: =Q103*(1+F$5) -> 108.3024 | S103: =R103*(1+G$5) -> 115.88357 | T103: =S103*(1+H$5) -> 123.416
A104: =A93 -> Silk emulsion | B104: 450 | C104: =B104*(1+E$5) -> 490.5 | D104: =C104*(1+F$5) -> 529.74 | E104: =D104*(1+G$5) -> 566.8218 | F104: =E104*(1+H$5) -> 603.66522 | H104: =A104 -> Silk emulsion | I104: 394 | J104: =I104*(1+E$5) -> 429.46 | K104: =J104*(1+F$5) -> 463.8168 | L104: =K104*(1+G$5) -> 496.28398 | M104: =L104*(1+H$5) -> 528.54243 | O104: =H104 -> Silk emulsion | P104: 98 | Q104: =P104*(1+E$5) -> 106.82 | R104: =Q104*(1+F$5) -> 115.3656 | S104: =R104*(1+G$5) -> 123.44119 | T104: =S104*(1+H$5) -> 131.46487
A105: =A94 -> Weather resistent exterior paint | B105: 480 | C105: =B105*(1+E$5) -> 523.2 | D105: =C105*(1+F$5) -> 565.056 | E105: =D105*(1+G$5) -> 604.60992 | F105: =E105*(1+H$5) -> 643.90956 | H105: =A105 -> Weather resistent exterior paint | I105: 420 | J105: =I105*(1+E$5) -> 457.8 | K105: =J105*(1+F$5) -> 494.424 | L105: =K105*(1+G$5) -> 529.03368 | M105: =L105*(1+H$5) -> 563.42087 | O105: =H105 -> Weather resistent exterior paint | P105: 105 | Q105: =P105*(1+E$5) -> 114.45 | R105: =Q105*(1+F$5) -> 123.606 | S105: =R105*(1+G$5) -> 132.25842 | T105: =S105*(1+H$5) -> 140.85522
A106: =A95 -> Super primer | B106: 380 | C106: =B106*(1+E$5) -> 414.2 | D106: =C106*(1+F$5) -> 447.336 | E106: =D106*(1+G$5) -> 478.64952 | F106: =E106*(1+H$5) -> 509.76174 | H106: =A106 -> Super primer | I106: 333 | J106: =I106*(1+E$5) -> 362.97 | K106: =J106*(1+F$5) -> 392.0076 | L106: =K106*(1+G$5) -> 419.44813 | M106: =L106*(1+H$5) -> 446.71226 | O106: =H106 -> Super primer | P106: 83 | Q106: =P106*(1+E$5) -> 90.47 | R106: =Q106*(1+F$5) -> 97.7076 | S106: =R106*(1+G$5) -> 104.54713 | T106: =S106*(1+H$5) -> 111.3427
A107: =A96 -> Synthetic Enamel | B107: 500 | C107: =B107*(1+E$5) -> 545 | D107: =C107*(1+F$5) -> 588.6 | E107: =D107*(1+G$5) -> 629.802 | F107: =E107*(1+H$5) -> 670.73913 | H107: =A107 -> Synthetic Enamel | I107: 438 | J107: =I107*(1+E$5) -> 477.42 | K107: =J107*(1+F$5) -> 515.6136 | L107: =K107*(1+G$5) -> 551.70655 | M107: =L107*(1+H$5) -> 587.56748 | O107: =H107 -> Synthetic Enamel | P107: 109 | Q107: =P107*(1+E$5) -> 118.81 | R107: =Q107*(1+F$5) -> 128.3148 | S107: =R107*(1+G$5) -> 137.29684 | T107: =S107*(1+H$5) -> 146.22113
A108: =A97
A109: Admin Costs | B109: (%age)
C110: =D2 -> 2026 | D110: =E2 -> 2027 | E110: =F2 -> 2028 | F110: =G2 -> 2029 | G110: =H2 -> 2030
A111: Utilities | B111: (% of COS) | C111: 0.05 | D111: 0.04 | E111: 0.03 | F111: 0.02 | G111: 0.02
A112: Salaries (Indirect Labor) | B112: (% of COS) | C112: 0.14 | D112: 0.12 | E112: 0.1 | F112: 0.08 | G112: 0.07
A113: Misc. Admin Expenses | B113: (% of COS) | C113: 0.07 | D113: 0.06 | E113: 0.05 | F113: 0.04 | G113: 0.04
A115: Selling Costs | B115: (%age)
C116: =D2 -> 2026 | D116: =E2 -> 2027 | E116: =F2 -> 2028 | F116: =G2 -> 2029 | G116: =H2 -> 2030
...

Sheet Sales
A1: Sales
A2: Drummi | I2: Gallon | P2: Litre
A3: Sales Volume Drummi | B3: (NO) | I3: Sales Volume Gallon | J3: =B3 -> (NO) | P3: Sales Vol Litre
A4: Total sales | C4: =Assumptions!D2 -> 2026 | D4: =Assumptions!E2 -> 2027 | E4: =Assumptions!F2 -> 2028 | F4: =Assumptions!G2 -> 2029 | G4: =Assumptions!H2 -> 2030 | I4: =A4 -> Total sales | J4: =C4 -> 2026 | K4: =D4 -> 2027 | L4: =E4 -> 2028 | M4: =F4 -> 2029 | N4: =G4 -> 2030 | P4: =I4 -> Total sales | Q4: =J4 -> 2026 | R4: =K4 -> 2027 | S4: =L4 -> 2028 | T4: =M4 -> 2029 | U4: =N4 -> 2030
A5: =Assumptions!A12 -> Royal Matt Emulsion paint | C5: =Assumptions!C12 -> 25000 | D5: =C5*(1+Assumptions!D$21) -> 47500 | E5: =D5*(1+Assumptions!E$21) -> 85500 | F5: =E5*(1+Assumptions!F$21) -> 136800 | G5: =F5*(1+Assumptions!G$21) -> 191520 | I5: =A5 -> Royal Matt Emulsion paint | J5: =Assumptions!I12 -> 30000 | K5: =J5*(1+Assumptions!D$21) -> 57000 | L5: =K5*(1+Assumptions!E$21) -> 102600 | M5: =L5*(1+Assumptions!F$21) -> 164160 | N5: =M5*(1+Assumptions!G$21) -> 229824 | P5: =I5 -> Royal Matt Emulsion paint | Q5: =Assumptions!O12 -> 15000 | R5: =Q5*(1+Assumptions!D$21) -> 28500 | S5: =R5*(1+Assumptions!E$21) -> 51300 | T5: =S5*(1+Assumptions!F$21) -> 82080 | U5: =T5*(1+Assumptions!G$21) -> 114912
A6: =Assumptions!A13 -> Anti-bacterial Interior paint | C6: =Assumptions!C13 -> 18000 | D6: =C6*(1+Assumptions!D$21) -> 34200 | E6: =D6*(1+Assumptions!E$21) -> 61560 | F6: =E6*(1+Assumptions!F$21) -> 98496 | G6: =F6*(1+Assumptions!G$21) -> 137894.4 | I6: =A6 -> Anti-bacterial Interior paint | J6: =Assumptions!I13 -> 23000 | K6: =J6*(1+Assumptions!D$21) -> 43700 | L6: =K6*(1+Assumptions!E$21) -> 78660 | M6: =L6*(1+Assumptions!F$21) -> 125856 | N6: =M6*(1+Assumptions!G$21) -> 176198.4 | P6: =I6 -> Anti-bacterial Interior paint | Q6: =Assumptions!O13 -> 13000 | R6: =Q6*(1+Assumptions!D$21) -> 24700 | S6: =R6*(1+Assumptions!E$21) -> 44460 | T6: =S6*(1+Assumptions!F$21) -> 71136 | U6: =T6*(1+Assumptions!G$21) -> 99590.4
A7: =Assumptions!A14 -> Silk emulsion | C7: =Assumptions!C14 -> 23000 | D7: =C7*(1+Assumptions!D$21) -> 43700 | E7: =D7*(1+Assumptions!E$21) -> 78660 | F7: =E7*(1+Assumptions!F$21) -> 125856 | G7: =F7*(1+Assumptions!G$21) -> 176198.4 | I7: =A7 -> Silk emulsion | J7: =Assumptions!I14 -> 27000 | K7: =J7*(1+Assumptions!D$21) -> 51300 | L7: =K7*(1+Assumptions!E$21) -> 92340 | M7: =L7*(1+Assumptions!F$21) -> 147744 | N7: =M7*(1+Assumptions!G$21) -> 206841.6 | P7: =I7 -> Silk emulsion | Q7: =Assumptions!O14 -> 17000 | R7: =Q7*(1+Assumptions!D$21) -> 32300 | S7: =R7*(1+Assumptions!E$21) -> 58140 | T7: =S7*(1+Assumptions!F$21) -> 93024 | U7: =T7*(1+Assumptions!G$21) -> 130233.6
A8: =Assumptions!A15 -> Weather resistent exterior paint | C8: =Assumptions!C15 -> 30000 | D8: =C8*(1+Assumptions!D$21) -> 57000 | E8: =D8*(1+Assumptions!E$21) -> 102600 | F8: =E8*(1+Assumptions!F$21) -> 164160 | G8: =F8*(1+Assumptions!G$21) -> 229824 | I8: =A8 -> Weather resistent exterior paint | J8: =Assumptions!I15 -> 35000 | K8: =J8*(1+Assumptions!D$21) -> 66500 | L8: =K8*(1+Assumptions!E$21) -> 119700 | M8: =L8*(1+Assumptions!F$21) -> 191520 | N8: =M8*(1+Assumptions!G$21) -> 268128 | P8: =I8 -> Weather resistent exterior paint | Q8: =Assumptions!O15 -> 25000 | R8: =Q8*(1+Assumptions!D$21) -> 47500 | S8: =R8*(1+Assumptions!E$21) -> 85500 | T8: =S8*(1+Assumptions!F$21) -> 136800 | U8: =T8*(1+Assumptions!G$21) -> 191520
A9: =Assumptions!A16 -> Super primer | C9: =Assumptions!C16 -> 35000 | D9: =C9*(1+Assumptions!D$21) -> 66500 | E9: =D9*(1+Assumptions!E$21) -> 119700 | F9: =E9*(1+Assumptions!F$21) -> 191520 | G9: =F9*(1+Assumptions!G$21) -> 268128 | I9: =A9 -> Super primer | J9: =Assumptions!I16 -> 40000 | K9: =J9*(1+Assumptions!D$21) -> 76000 | L9: =K9*(1+Assumptions!E$21) -> 136800 | M9: =L9*(1+Assumptions!F$21) -> 218880 | N9: =M9*(1+Assumptions!G$21) -> 306432 | P9: =I9 -> Super primer | Q9: =Assumptions!O16 -> 30000 | R9: =Q9*(1+Assumptions!D$21) -> 57000 | S9: =R9*(1+Assumptions!E$21) -> 102600 | T9: =S9*(1+Assumptions!F$21) -> 164160 | U9: =T9*(1+Assumptions!G$21) -> 229824
A10: =Assumptions!A17 -> Synthetic Enamel | C10: =Assumptions!C17 -> 40000 | D10: =C10*(1+Assumptions!D$21) -> 76000 | E10: =D10*(1+Assumptions!E$21) -> 136800 | F10: =E10*(1+Assumptions!F$21) -> 218880 | G10: =F10*(1+Assumptions!G$21) -> 306432 | I10: =A10 -> Synthetic Enamel | J10: =Assumptions!I17 -> 45000 | K10: =J10*(1+Assumptions!D$21) -> 85500 | L10: =K10*(1+Assumptions!E$21) -> 153900 | M10: =L10*(1+Assumptions!F$21) -> 246240 | N10: =M10*(1+Assumptions!G$21) -> 344736 | P10: =I10 -> Synthetic Enamel | Q10: =Assumptions!O17 -> 35000 | R10: =Q10*(1+Assumptions!D$21) -> 66500 | S10: =R10*(1+Assumptions!E$21) -> 119700 | T10: =S10*(1+Assumptions!F$21) -> 191520 | U10: =T10*(1+Assumptions!G$21) -> 268128
P11: =I11
A12: Export Sales | C12: =C4 -> 2026 | D12: =D4 -> 2027 | E12: =E4 -> 2028 | F12: =F4 -> 2029 | G12: =G4 -> 2030 | I12: =A12 -> Export Sales | J12: =C12 -> 2026 | K12: =D12 -> 2027 | L12: =E12 -> 2028 | M12: =F12 -> 2029 | N12: =G12 -> 2030 | P12: =I12 -> Export Sales | Q12: =Q4 -> 2026 | R12: =R4 -> 2027 | S12: =S4 -> 2028 | T12: =T4 -> 2029 | U12: =U4 -> 2030
A13: =A5 -> Royal Matt Emulsion paint | C13: =C5*Assumptions!C$24 -> 0 | D13: =D5*Assumptions!D$24 -> 9500 | E13: =E5*Assumptions!E$24 -> 21375 | F13: =F5*Assumptions!F$24 -> 34200 | G13: =G5*Assumptions!G$24 -> 57456 | I13: =A13 -> Royal Matt Emulsion paint | J13: =0 -> 0 | K13: =K5*Assumptions!D$24 -> 11400 | L13: =L5*Assumptions!E$24 -> 25650 | M13: =M5*Assumptions!F$24 -> 41040 | N13: =N5*Assumptions!G$24 -> 68947.2 | P13: =I13 -> Royal Matt Emulsion paint | Q13: =0 -> 0 | R13: =R5*Assumptions!D$24 -> 5700 | S13: =S5*Assumptions!E$24 -> 12825 | T13: =T5*Assumptions!F$24 -> 20520 | U13: =U5*Assumptions!G$24 -> 34473.6
A14: =A6 -> Anti-bacterial Interior paint | C14: =C6*Assumptions!C$24 -> 0 | D14: =D6*Assumptions!D$24 -> 6840 | E14: =E6*Assumptions!E$24 -> 15390 | F14: =F6*Assumptions!F$24 -> 24624 | G14: =G6*Assumptions!G$24 -> 41368.32 | I14: =A14 -> Anti-bacterial Interior paint | J14: =0 -> 0 | K14: =K6*Assumptions!D$24 -> 8740 | L14: =L6*Assumptions!E$24 -> 19665 | M14: =M6*Assumptions!F$24 -> 31464 | N14: =N6*Assumptions!G$24 -> 52859.52 | P14: =I14 -> Anti-bacterial Interior paint | Q14: =0 -> 0 | R14: =R6*Assumptions!D$24 -> 4940 | S14: =S6*Assumptions!E$24 -> 11115 | T14: =T6*Assumptions!F$24 -> 17784 | U14: =U6*Assumptions!G$24 -> 29877.12
A15: =A7 -> Silk emulsion | C15: =C7*Assumptions!C$24 -> 0 | D15: =D7*Assumptions!D$24 -> 8740 | E15: =E7*Assumptions!E$24 -> 19665 | F15: =F7*Assumptions!F$24 -> 31464 | G15: =G7*Assumptions!G$24 -> 52859.52 | I15: =A15 -> Silk emulsion | J15: =0 -> 0 | K15: =K7*Assumptions!D$24 -> 10260 | L15: =L7*Assumptions!E$24 -> 23085 | M15: =M7*Assumptions!F$24 -> 36936 | N15: =N7*Assumptions!G$24 -> 62052.48 | P15: =I15 -> Silk emulsion | Q15: =0 -> 0 | R15: =R7*Assumptions!D$24 -> 6460 | S15: =S7*Assumptions!E$24 -> 14535 | T15: =T7*Assumptions!F$24 -> 23256 | U15: =U7*Assumptions!G$24 -> 39070.08
A16: =A8 -> Weather resistent exterior paint | C16: =C8*Assumptions!C$24 -> 0 | D16: =D8*Assumptions!D$24 -> 11400 | E16: =E8*Assumptions!E$24 -> 25650 | F16: =F8*Assumptions!F$24 -> 41040 | G16: =G8*Assumptions!G$24 -> 68947.2 | I16: =A16 -> Weather resistent exterior paint | J16: =0 -> 0 | K16: =K8*Assumptions!D$24 -> 13300 | L16: =L8*Assumptions!E$24 -> 29925 | M16: =M8*Assumptions!F$24 -> 47880 | N16: =N8*Assumptions!G$24 -> 80438.4 | P16: =I16 -> Weather resistent exterior paint | Q16: =0 -> 0 | R16: =R8*Assumptions!D$24 -> 9500 | S16: =S8*Assumptions!E$24 -> 21375 | T16: =T8*Assumptions!F$24 -> 34200 | U16: =U8*Assumptions!G$24 -> 57456
A17: =A9 -> Super primer | C17: =C9*Assumptions!C$24 -> 0 | D17: =D9*Assumptions!D$24 -> 13300 | E17: =E9*Assumptions!E$24 -> 29925 | F17: =F9*Assumptions!F$24 -> 47880 | G17: =G9*Assumptions!G$24 -> 80438.4 | I17: =A17 -> Super primer | J17: =0 -> 0 | K17: =K9*Assumptions!D$24 -> 15200 | L17: =L9*Assumptions!E$24 -> 34200 | M17: =M9*Assumptions!F$24 -> 54720 | N17: =N9*Assumptions!G$24 -> 91929.6 | P17: =I17 -> Super primer | Q17: =0 -> 0 | R17: =R9*Assumptions!D$24 -> 11400 | S17: =S9*Assumptions!E$24 -> 25650 | T17: =T9*Assumptions!F$24 -> 41040 | U17: =U9*Assumptions!G$24 -> 68947.2
A18: =A10 -> Synthetic Enamel | C18: =C10*Assumptions!C$24 -> 0 | D18: =D10*Assumptions!D$24 -> 15200 | E18: =E10*Assumptions!E$24 -> 34200 | F18: =F10*Assumptions!F$24 -> 54720 | G18: =G10*Assumptions!G$24 -> 91929.6 | I18: =A18 -> Synthetic Enamel | J18: =0 -> 0 | K18: =K10*Assumptions!D$24 -> 17100 | L18: =L10*Assumptions!E$24 -> 38475 | M18: =M10*Assumptions!F$24 -> 61560 | N18: =N10*Assumptions!G$24 -> 103420.8 | P18: =I18 -> Synthetic Enamel | Q18: =0 -> 0 | R18: =R10*Assumptions!D$24 -> 13300 | S18: =S10*Assumptions!E$24 -> 29925 | T18: =T10*Assumptions!F$24 -> 47880 | U18: =U10*Assumptions!G$24 -> 80438.4
A19: =A11 | P19: =I19
A20: Local sales | C20: =C12 -> 2026 | D20: =D12 -> 2027 | E20: =E12 -> 2028 | F20: =F12 -> 2029 | G20: =G12 -> 2030 | I20: =A20 -> Local sales | J20: =C20 -> 2026 | K20: =D20 -> 2027 | L20: =E20 -> 2028 | M20: =F20 -> 2029 | N20: =G20 -> 2030 | P20: =I20 -> Local sales | Q20: =Q12 -> 2026 | R20: =R12 -> 2027 | S20: =S12 -> 2028 | T20: =T12 -> 2029 | U20: =U12 -> 2030
A21: =A13 -> Royal Matt Emulsion paint | C21: =C5 -> 25000 | D21: =D5-D13 -> 38000 | E21: =E5-E13 -> 64125 | F21: =F5-F13 -> 102600 | G21: =G5-G13 -> 134064 | I21: =A21 -> Royal Matt Emulsion paint | J21: =J5 -> 30000 | K21: =K5-K13 -> 45600 | L21: =L5-L13 -> 76950 | M21: =M5-M13 -> 123120 | N21: =N5-N13 -> 160876.8 | P21: =I21 -> Royal Matt Emulsion paint | Q21: =Q5-Q13 -> 15000 | R21: =R5-R13 -> 22800 | S21: =S5-S13 -> 38475 | T21: =T5-T13 -> 61560 | U21: =U5-U13 -> 80438.4
A22: =A14 -> Anti-bacterial Interior paint | C22: =C6 -> 18000 | D22: =D6-D14 -> 27360 | E22: =E6-E14 -> 46170 | F22: =F6-F14 -> 73872 | G22: =G6-G14 -> 96526.08 | I22: =A22 -> Anti-bacterial Interior paint | J22: =J6 -> 23000 | K22: =K6-K14 -> 34960 | L22: =L6-L14 -> 58995 | M22: =M6-M14 -> 94392 | N22: =N6-N14 -> 123338.88 | P22: =I22 -> Anti-bacterial Interior paint | Q22: =Q6-Q14 -> 13000 | R22: =R6-R14 -> 19760 | S22: =S6-S14 -> 33345 | T22: =T6-T14 -> 53352 | U22: =U6-U14 -> 69713.28
A23: =A15 -> Silk emulsion | C23: =C7 -> 23000 | D23: =D7-D15 -> 34960 | E23: =E7-E15 -> 58995 | F23: =F7-F15 -> 94392 | G23: =G7-G15 -> 123338.88 | I23: =A23 -> Silk emulsion | J23: =J7 -> 27000 | K23: =K7-K15 -> 41040 | L23: =L7-L15 -> 69255 | M23: =M7-M15 -> 110808 | N23: =N7-N15 -> 144789.12 | P23: =I23 -> Silk emulsion | Q23: =Q7-Q15 -> 17000 | R23: =R7-R15 -> 25840 | S23: =S7-S15 -> 43605 | T23: =T7-T15 -> 69768 | U23: =U7-U15 -> 91163.52
A24: =A16 -> Weather resistent exterior paint | C24: =C8 -> 30000 | D24: =D8-D16 -> 45600 | E24: =E8-E16 -> 76950 | F24: =F8-F16 -> 123120 | G24: =G8-G16 -> 160876.8 | I24: =A24 -> Weather resistent exterior paint | J24: =J8 -> 35000 | K24: =K8-K16 -> 53200 | L24: =L8-L16 -> 89775 | M24: =M8-M16 -> 143640 | N24: =N8-N16 -> 187689.6 | P24: =I24 -> Weather resistent exterior paint | Q24: =Q8-Q16 -> 25000 | R24: =R8-R16 -> 38000 | S24: =S8-S16 -> 64125 | T24: =T8-T16 -> 102600 | U24: =U8-U16 -> 134064
A25: =A17 -> Super primer | C25: =C9 -> 35000 | D25: =D9-D17 -> 53200 | E25: =E9-E17 -> 89775 | F25: =F9-F17 -> 143640 | G25: =G9-G17 -> 187689.6 | I25: =A25 -> Super primer | J25: =J9 -> 40000 | K25: =K9-K17 -> 60800 | L25: =L9-L17 -> 102600 | M25: =M9-M17 -> 164160 | N25: =N9-N17 -> 214502.4 | P25: =I25 -> Super primer | Q25: =Q9-Q17 -> 30000 | R25: =R9-R17 -> 45600 | S25: =S9-S17 -> 76950 | T25: =T9-T17 -> 123120 | U25: =U9-U17 -> 160876.8
A26: =A18 -> Synthetic Enamel | C26: =C10 -> 40000 | D26: =D10-D18 -> 60800 | E26: =E10-E18 -> 102600 | F26: =F10-F18 -> 164160 | G26: =G10-G18 -> 214502.4 | I26: =A26 -> Synthetic Enamel | J26: =J10 -> 45000 | K26: =K10-K18 -> 68400 | L26: =L10-L18 -> 115425 | M26: =M10-M18 -> 184680 | N26: =N10-N18 -> 241315.2 | P26: =I26 -> Synthetic Enamel | Q26: =Q10-Q18 -> 35000 | R26: =R10-R18 -> 53200 | S26: =S10-S18 -> 89775 | T26: =T10-T18 -> 143640 | U26: =U10-U18 -> 187689.6
P27: =I27
A28: Sales Price | I28: =A28 -> Sales Price | P28: =I28 -> Sales Price
P29: =I29
A30: Export Sales | C30: =C20 -> 2026 | D30: =D20 -> 2027 | E30: =E20 -> 2028 | F30: =F20 -> 2029 | G30: =G20 -> 2030 | I30: =A30 -> Export Sales | J30: =C30 -> 2026 | K30: =D30 -> 2027 | L30: =E30 -> 2028 | M30: =F30 -> 2029 | N30: =G30 -> 2030 | P30: =I30 -> Export Sales | Q30: =Q20 -> 2026 | R30: =R20 -> 2027 | S30: =S20 -> 2028 | T30: =T20 -> 2029 | U30: =U20 -> 2030
A31: =A21 -> Royal Matt Emulsion paint | C31: =Assumptions!E12 -> 59.484211 | D31: =C31*(1+Assumptions!D$23) -> 61.268737 | E31: =D31*(1+Assumptions!E$23) -> 63.106799 | F31: =E31*(1+Assumptions!F$23) -> 64.684469 | G31: =F31*(1+Assumptions!G$23) -> 66.948425 | I31: =A31 -> Royal Matt Emulsion paint | J31: =Assumptions!K12 -> 15.410526 | K31: =J31*(1+Assumptions!D$23) -> 15.872842 | L31: =K31*(1+Assumptions!E$23) -> 16.349027 | M31: =L31*(1+Assumptions!F$23) -> 16.757753 | N31: =M31*(1+Assumptions!G$23) -> 17.344274 | P31: =I31 -> Royal Matt Emulsion paint | Q31: =Assumptions!Q12 -> 4.0035088 | R31: =Q31*(1+Assumptions!D$23) -> 4.123614 | S31: =R31*(1+Assumptions!E$23) -> 4.2473225 | T31: =S31*(1+Assumptions!F$23) -> 4.3535055 | U31: =T31*(1+Assumptions!G$23) -> 4.5058782
A32: =A22 -> Anti-bacterial Interior paint | C32: =Assumptions!E13 -> 97.684211 | D32: =C32*(1+Assumptions!D$23) -> 100.61474 | E32: =D32*(1+Assumptions!E$23) -> 103.63318 | F32: =E32*(1+Assumptions!F$23) -> 106.22401 | G32: =F32*(1+Assumptions!G$23) -> 109.94185 | I32: =A32 -> Anti-bacterial Interior paint | J32: =Assumptions!K13 -> 24.421053 | K32: =J32*(1+Assumptions!D$23) -> 25.153684 | L32: =K32*(1+Assumptions!E$23) -> 25.908295 | M32: =L32*(1+Assumptions!F$23) -> 26.556002 | N32: =M32*(1+Assumptions!G$23) -> 27.485462 | P32: =I32 -> Anti-bacterial Interior paint | Q32: =Assumptions!Q13 -> 6.1052632 | R32: =Q32*(1+Assumptions!D$23) -> 6.2884211 | S32: =R32*(1+Assumptions!E$23) -> 6.4770737 | T32: =S32*(1+Assumptions!F$23) -> 6.6390005 | U32: =T32*(1+Assumptions!G$23) -> 6.8713655
A33: =A23 -> Silk emulsion | C33: =Assumptions!E14 -> 64.719298 | D33: =C33*(1+Assumptions!D$23) -> 66.660877 | E33: =D33*(1+Assumptions!E$23) -> 68.660704 | F33: =E33*(1+Assumptions!F$23) -> 70.377221 | G33: =F33*(1+Assumptions!G$23) -> 72.840424 | I33: =A33 -> Silk emulsion | J33: =Assumptions!K14 -> 16.789474 | K33: =J33*(1+Assumptions!D$23) -> 17.293158 | L33: =K33*(1+Assumptions!E$23) -> 17.811953 | M33: =L33*(1+Assumptions!F$23) -> 18.257251 | N33: =M33*(1+Assumptions!G$23) -> 18.896255 | P33: =I33 -> Silk emulsion | Q33: =Assumptions!Q14 -> 4.1964912 | R33: =Q33*(1+Assumptions!D$23) -> 4.322386 | S33: =R33*(1+Assumptions!E$23) -> 4.4520575 | T33: =S33*(1+Assumptions!F$23) -> 4.563359 | U33: =T33*(1+Assumptions!G$23) -> 4.7230765
A34: =A24 -> Weather resistent exterior paint | C34: =Assumptions!E15 -> 46.203509 | D34: =C34*(1+Assumptions!D$23) -> 47.589614 | E34: =D34*(1+Assumptions!E$23) -> 49.017302 | F34: =E34*(1+Assumptions!F$23) -> 50.242735 | G34: =F34*(1+Assumptions!G$23) -> 52.001231 | I34: =A34 -> Weather resistent exterior paint | J34: =Assumptions!K15 -> 12.035088 | K34: =J34*(1+Assumptions!D$23) -> 12.39614 | L34: =K34*(1+Assumptions!E$23) -> 12.768025 | M34: =L34*(1+Assumptions!F$23) -> 13.087225 | N34: =M34*(1+Assumptions!G$23) -> 13.545278 | P34: =I34 -> Weather resistent exterior paint | Q34: =Assumptions!Q15 -> 3.2631579 | R34: =Q34*(1+Assumptions!D$23) -> 3.3610526 | S34: =R34*(1+Assumptions!E$23) -> 3.4618842 | T34: =S34*(1+Assumptions!F$23) -> 3.5484313 | U34: =T34*(1+Assumptions!G$23) -> 3.6726264
A35: =A25 -> Super primer | C35: =Assumptions!E16 -> 18.122807 | D35: =C35*(1+Assumptions!D$23) -> 18.666491 | E35: =D35*(1+Assumptions!E$23) -> 19.226486 | F35: =E35*(1+Assumptions!F$23) -> 19.707148 | G35: =F35*(1+Assumptions!G$23) -> 20.396898 | I35: =A35 -> Super primer | J35: =Assumptions!K16 -> 4.8035088 | K35: =J35*(1+Assumptions!D$23) -> 4.947614 | L35: =K35*(1+Assumptions!E$23) -> 5.0960425 | M35: =L35*(1+Assumptions!F$23) -> 5.2234435 | N35: =M35*(1+Assumptions!G$23) -> 5.406264 | P35: =I35 -> Super primer | Q35: =Assumptions!Q16 -> 1.2 | R35: =Q35*(1+Assumptions!D$23) -> 1.236 | S35: =R35*(1+Assumptions!E$23) -> 1.27308 | T35: =S35*(1+Assumptions!F$23) -> 1.304907 | U35: =T35*(1+Assumptions!G$23) -> 1.3505787
A36: =A26 -> Synthetic Enamel | C36: =Assumptions!E17 -> 56.02807 | D36: =C36*(1+Assumptions!D$23) -> 57.708912 | E36: =D36*(1+Assumptions!E$23) -> 59.44018 | F36: =E36*(1+Assumptions!F$23) -> 60.926184 | G36: =F36*(1+Assumptions!G$23) -> 63.058601 | I36: =A36 -> Synthetic Enamel | J36: =Assumptions!K17 -> 14.007018 | K36: =J36*(1+Assumptions!D$23) -> 14.427228 | L36: =K36*(1+Assumptions!E$23) -> 14.860045 | M36: =L36*(1+Assumptions!F$23) -> 15.231546 | N36: =M36*(1+Assumptions!G$23) -> 15.76465 | P36: =I36 -> Synthetic Enamel | Q36: =Assumptions!Q17 -> 3.5017544 | R36: =Q36*(1+Assumptions!D$23) -> 3.606807 | S36: =R36*(1+Assumptions!E$23) -> 3.7150112 | T36: =S36*(1+Assumptions!F$23) -> 3.8078865 | U36: =T36*(1+Assumptions!G$23) -> 3.9411625
P37: =I37
A38: Local Sales | C38: =C30 -> 2026 | D38: =D30 -> 2027 | E38: =E30 -> 2028 | F38: =F30 -> 2029 | G38: =G30 -> 2030 | I38: =A38 -> Local Sales | J38: =C38 -> 2026 | K38: =D38 -> 2027 | L38: =E38 -> 2028 | M38: =F38 -> 2029 | N38: =G38 -> 2030 | P38: =I38 -> Local Sales | Q38: =Q30 -> 2026 | R38: =R30 -> 2027 | S38: =S30 -> 2028 | T38: =T30 -> 2029 | U38: =U30 -> 2030
A39: =A31 -> Royal Matt Emulsion paint | C39: =Assumptions!D12 -> 16953 | D39: =C39*(1+Assumptions!D$22) -> 18648.3 | E39: =D39*(1+Assumptions!E$22) -> 20326.647 | F39: =E39*(1+Assumptions!F$22) -> 21952.779 | G39: =F39*(1+Assumptions!G$22) -> 23489.473 | I39: =A39 -> Royal Matt Emulsion paint | J39: =Assumptions!J12 -> 4392 | K39: =J39*( 1+Assumptions!D$22) -> 4831.2 | L39: =K39*(1+Assumptions!E$22) -> 5266.008 | M39: =L39*(1+Assumptions!F$22) -> 5687.2886 | N39: =M39*(1+Assumptions!G$22) -> 6085.3988 | P39: =I39 -> Royal Matt Emulsion paint | Q39: =Assumptions!P12 -> 1141 | R39: =Q39*(1+Assumptions!D$22) -> 1255.1 | S39: =R39*(1+Assumptions!E$22) -> 1368.059 | T39: =S39*(1+Assumptions!F$22) -> 1477.5037 | U39: =T39*(1+Assumptions!G$22) -> 1580.929
A40: =A32 -> Anti-bacterial Interior paint | C40: =Assumptions!D13 -> 27840 | D40: =C40*(1+Assumptions!D$22) -> 30624 | E40: =D40*(1+Assumptions!E$22) -> 33380.16 | F40: =E40*(1+Assumptions!F$22) -> 36050.573 | G40: =F40*(1+Assumptions!G$22) -> 38574.113 | I40: =A40 -> Anti-bacterial Interior paint | J40: =Assumptions!J13 -> 6960 | K40: =J40*(1+Assumptions!D$22) -> 7656 | L40: =K40*(1+Assumptions!E$22) -> 8345.04 | M40: =L40*(1+Assumptions!F$22) -> 9012.6432 | N40: =M40*(1+Assumptions!G$22) -> 9643.5282 | P40: =I40 -> Anti-bacterial Interior paint | Q40: =Assumptions!P13 -> 1740 | R40: =Q40*(1+Assumptions!D$22) -> 1914 | S40: =R40*(1+Assumptions!E$22) -> 2086.26 | T40: =S40*(1+Assumptions!F$22) -> 2253.1608 | U40: =T40*(1+Assumptions!G$22) -> 2410.8821
A41: =A33 -> Silk emulsion | C41: =Assumptions!D14 -> 18445 | D41: =C41*(1+Assumptions!D$22) -> 20289.5 | E41: =D41*(1+Assumptions!E$22) -> 22115.555 | F41: =E41*(1+Assumptions!F$22) -> 23884.799 | G41: =F41*(1+Assumptions!G$22) -> 25556.735 | I41: =A41 -> Silk emulsion | J41: =Assumptions!J14 -> 4785 | K41: =J41*(1+Assumptions!D$22) -> 5263.5 | L41: =K41*(1+Assumptions!E$22) -> 5737.215 | M41: =L41*(1+Assumptions!F$22) -> 6196.1922 | N41: =M41*(1+Assumptions!G$22) -> 6629.9257 | P41: =I41 -> Silk emulsion | Q41: =Assumptions!P14 -> 1196 | R41: =Q41*(1+Assumptions!D$22) -> 1315.6 | S41: =R41*(1+Assumptions!E$22) -> 1434.004 | T41: =S41*(1+Assumptions!F$22) -> 1548.7243 | U41: =T41*(1+Assumptions!G$22) -> 1657.135
A42: =A34 -> Weather resistent exterior paint | C42: =Assumptions!D15 -> 13168 | D42: =C42*(1+Assumptions!D$22) -> 14484.8 | E42: =D42*(1+Assumptions!E$22) -> 15788.432 | F42: =E42*(1+Assumptions!F$22) -> 17051.507 | G42: =F42*(1+Assumptions!G$22) -> 18245.112 | I42: =A42 -> Weather resistent exterior paint | J42: =Assumptions!J15 -> 3430 | K42: =J42*(1+Assumptions!D$22) -> 3773 | L42: =K42*(1+Assumptions!E$22) -> 4112.57 | M42: =L42*(1+Assumptions!F$22) -> 4441.5756 | N42: =M42*(1+Assumptions!G$22) -> 4752.4859 | P42: =I42 -> Weather resistent exterior paint | Q42: =Assumptions!P15 -> 930 | R42: =Q42*(1+Assumptions!D$22) -> 1023 | S42: =R42*(1+Assumptions!E$22) -> 1115.07 | T42: =S42*(1+Assumptions!F$22) -> 1204.2756 | U42: =T42*(1+Assumptions!G$22) -> 1288.5749
A43: =A35 -> Super primer | C43: =Assumptions!D16 -> 5165 | D43: =C43*(1+Assumptions!D$22) -> 5681.5 | E43: =D43*(1+Assumptions!E$22) -> 6192.835 | F43: =E43*(1+Assumptions!F$22) -> 6688.2618 | G43: =F43*(1+Assumptions!G$22) -> 7156.4401 | I43: =A43 -> Super primer | J43: =Assumptions!J16 -> 1369 | K43: =J43*(1+Assumptions!D$22) -> 1505.9 | L43: =K43*(1+Assumptions!E$22) -> 1641.431 | M43: =L43*(1+Assumptions!F$22) -> 1772.7455 | N43: =M43*(1+Assumptions!G$22) -> 1896.8377 | P43: =I43 -> Super primer | Q43: =Assumptions!P16 -> 342 | R43: =Q43*(1+Assumptions!D$22) -> 376.2 | S43: =R43*(1+Assumptions!E$22) -> 410.058 | T43: =S43*(1+Assumptions!F$22) -> 442.86264 | U43: =T43*(1+Assumptions!G$22) -> 473.86302
A44: =A36 -> Synthetic Enamel | C44: =Assumptions!D17 -> 15968 | D44: =C44*(1+Assumptions!D$22) -> 17564.8 | E44: =D44*(1+Assumptions!E$22) -> 19145.632 | F44: =E44*(1+Assumptions!F$22) -> 20677.283 | G44: =F44*(1+Assumptions!G$22) -> 22124.692 | I44: =A44 -> Synthetic Enamel | J44: =Assumptions!J17 -> 3992 | K44: =J44*(1+Assumptions!D$22) -> 4391.2 | L44: =K44*(1+Assumptions!E$22) -> 4786.408 | M44: =L44*(1+Assumptions!F$22) -> 5169.3206 | N44: =M44*(1+Assumptions!G$22) -> 5531.1731 | P44: =I44 -> Synthetic Enamel | Q44: =Assumptions!P17 -> 998 | R44: =Q44*(1+Assumptions!D$22) -> 1097.8 | S44: =R44*(1+Assumptions!E$22) -> 1196.602 | T44: =S44*(1+Assumptions!F$22) -> 1292.3302 | U44: =T44*(1+Assumptions!G$22) -> 1382.7933
P45: =I45
A46: Export Revenue PKR Mn | C46: =C38 -> 2026 | D46: =D38 -> 2027 | E46: =E38 -> 2028 | F46: =F38 -> 2029 | G46: =G38 -> 2030 | I46: =A46 -> Export Revenue PKR Mn | J46: =C46 -> 2026 | K46: =D46 -> 2027 | L46: =E46 -> 2028 | M46: =F46 -> 2029 | N46: =G46 -> 2030 | P46: =I46 -> Export Revenue PKR Mn | Q46: =Q38 -> 2026 | R46: =R38 -> 2027 | S46: =S38 -> 2028 | T46: =T38 -> 2029 | U46: =U38 -> 2030
A47: =A39 -> Royal Matt Emulsion paint | C47: =C31*C13/1000000 -> 0 | D47: =D31*D13/1000000 -> 0.582053 | E47: =E31*E13/1000000 -> 1.3489078 | F47: =F31*F13/1000000 -> 2.2122088 | G47: =G31*G13/1000000 -> 3.8465887 | I47: =A47 -> Royal Matt Emulsion paint | J47: =J31*J13/1000000 -> 0 | K47: =K31*K13/1000000 -> 0.1809504 | L47: =L31*L13/1000000 -> 0.41935255 | M47: =M31*M13/1000000 -> 0.68773819 | N47: =N31*N13/1000000 -> 1.1958392 | P47: =I47 -> Royal Matt Emulsion paint | Q47: =0 -> 0 | R47: =R31*R13/1000000 -> 0.0235046 | S47: =S31*S13/1000000 -> 0.05447191 | T47: =T31*T13/1000000 -> 0.089333933 | U47: =U31*U13/1000000 -> 0.15533384
A48: =A40 -> Anti-bacterial Interior paint | C48: =C32*C14/1000000 -> 0 | D48: =D32*D14/1000000 -> 0.6882048 | E48: =E32*E14/1000000 -> 1.5949146 | F48: =F32*F14/1000000 -> 2.61566 | G48: =G32*G14/1000000 -> 4.5481096 | I48: =A48 -> Anti-bacterial Interior paint | J48: =J32*J14/1000000 -> 0 | K48: =K32*K14/1000000 -> 0.2198432 | L48: =L32*L14/1000000 -> 0.50948662 | M48: =M32*M14/1000000 -> 0.83555805 | N48: =N32*N14/1000000 -> 1.4528683 | P48: =I48 -> Anti-bacterial Interior paint | Q48: =0 -> 0 | R48: =R32*R14/1000000 -> 0.0310648 | S48: =S32*S14/1000000 -> 0.071992674 | T48: =T32*T14/1000000 -> 0.11806799 | U48: =U32*U14/1000000 -> 0.20529661
A49: =A41 -> Silk emulsion | C49: =C33*C15/1000000 -> 0 | D49: =D33*D15/1000000 -> 0.58261607 | E49: =E33*E15/1000000 -> 1.3502127 | F49: =F33*F15/1000000 -> 2.2143489 | G49: =G33*G15/1000000 -> 3.8503098 | I49: =A49 -> Silk emulsion | J49: =J33*J15/1000000 -> 0 | K49: =K33*K15/1000000 -> 0.1774278 | L49: =L33*L15/1000000 -> 0.41118893 | M49: =M33*M15/1000000 -> 0.67434984 | N49: =N33*N15/1000000 -> 1.1725595 | P49: =I49 -> Silk emulsion | Q49: =0 -> 0 | R49: =R33*R15/1000000 -> 0.027922613 | S49: =S33*S15/1000000 -> 0.064710656 | T49: =T33*T15/1000000 -> 0.10612548 | U49: =U33*U15/1000000 -> 0.18453098
A50: =A42 -> Weather resistent exterior paint | C50: =C34*C16/1000000 -> 0 | D50: =D34*D16/1000000 -> 0.5425216 | E50: =E34*E16/1000000 -> 1.2572938 | F50: =F34*F16/1000000 -> 2.0619618 | G50: =G34*G16/1000000 -> 3.5853393 | I50: =A50 -> Weather resistent exterior paint | J50: =J34*J16/1000000 -> 0 | K50: =K34*K16/1000000 -> 0.16486867 | L50: =L34*L16/1000000 -> 0.38208314 | M50: =M34*M16/1000000 -> 0.62661634 | N50: =N34*N16/1000000 -> 1.0895605 | P50: =I50 -> Weather resistent exterior paint | Q50: =0 -> 0 | R50: =R34*R16/1000000 -> 0.03193 | S50: =S34*S16/1000000 -> 0.073997775 | T50: =T34*T16/1000000 -> 0.12135635 | U50: =U34*U16/1000000 -> 0.21101442
A51: =A43 -> Super primer | C51: =C35*C17/1000000 -> 0 | D51: =D35*D17/1000000 -> 0.24826433 | E51: =E35*E17/1000000 -> 0.57535259 | F51: =F35*F17/1000000 -> 0.94357825 | G51: =G35*G17/1000000 -> 1.6406939 | I51: =A51 -> Super primer | J51: =J35*J17/1000000 -> 0 | K51: =K35*K17/1000000 -> 0.075203733 | L51: =L35*L17/1000000 -> 0.17428465 | M51: =M35*M17/1000000 -> 0.28582683 | N51: =N35*N17/1000000 -> 0.49699569 | P51: =I51 -> Super primer | Q51: =0 -> 0 | R51: =R35*R17/1000000 -> 0.0140904 | S51: =S35*S17/1000000 -> 0.032654502 | T51: =T35*T17/1000000 -> 0.053553383 | U51: =U35*U17/1000000 -> 0.093118623
A52: =A44 -> Synthetic Enamel | C52: =C36*C18/1000000 -> 0 | D52: =D36*D18/1000000 -> 0.87717547 | E52: =E36*E18/1000000 -> 2.0328541 | F52: =F36*F18/1000000 -> 3.3338808 | G52: =G36*G18/1000000 -> 5.7969519 | I52: =A52 -> Synthetic Enamel | J52: =J36*J18/1000000 -> 0 | K52: =K36*K18/1000000 -> 0.2467056 | L52: =L36*L18/1000000 -> 0.57174023 | M52: =M36*M18/1000000 -> 0.93765397 | N52: =N36*N18/1000000 -> 1.6303927 | P52: =I52 -> Synthetic Enamel | Q52: =0 -> 0 | R52: =R36*R18/1000000 -> 0.047970533 | S52: =S36*S18/1000000 -> 0.11117171 | T52: =T36*T18/1000000 -> 0.18232161 | U52: =U36*U18/1000000 -> 0.31702081
P53: =I53
A54: Local Revenue PKR Mn | C54: =C46 -> 2026 | D54: =D46 -> 2027 | E54: =E46 -> 2028 | F54: =F46 -> 2029 | G54: =G46 -> 2030 | I54: =A54 -> Local Revenue PKR Mn | J54: =C54 -> 2026 | K54: =D54 -> 2027 | L54: =E54 -> 2028 | M54: =F54 -> 2029 | N54: =G54 -> 2030 | P54: =I54 -> Local Revenue PKR Mn | Q54: =Q46 -> 2026 | R54: =R46 -> 2027 | S54: =S46 -> 2028 | T54: =T46 -> 2029 | U54: =U46 -> 2030
A55: =A47 -> Royal Matt Emulsion paint | C55: =C39*C21/1000000 -> 423.825 | D55: =D39*D21/1000000 -> 708.6354 | E55: =E39*E21/1000000 -> 1303.4462 | F55: =F39*F21/1000000 -> 2252.3551 | G55: =G39*G21/1000000 -> 3149.0927 | I55: =A55 -> Royal Matt Emulsion paint | J55: =J21*J39/1000000 -> 131.76 | K55: =K21*K39/1000000 -> 220.30272 | L55: =L21*L39/1000000 -> 405.21932 | M55: =M21*M39/1000000 -> 700.21898 | N55: =N21*N39/1000000 -> 978.99949 | P55: =I55 -> Royal Matt Emulsion paint | Q55: =Q39*Q21/1000000 -> 17.115 | R55: =R39*R21/1000000 -> 28.61628 | S55: =S39*S21/1000000 -> 52.63607 | T55: =T39*T21/1000000 -> 90.955129 | U55: =U39*U21/1000000 -> 127.1674
A56: =A48 -> Anti-bacterial Interior paint | C56: =C40*C22/1000000 -> 501.12 | D56: =D40*D22/1000000 -> 837.87264 | E56: =E40*E22/1000000 -> 1541.162 | F56: =F40*F22/1000000 -> 2663.1279 | G56: =G40*G22/1000000 -> 3723.4079 | I56: =A56 -> Anti-bacterial Interior paint | J56: =J22*J40/1000000 -> 160.08 | K56: =K22*K40/1000000 -> 267.65376 | L56: =L22*L40/1000000 -> 492.31563 | M56: =M22*M40/1000000 -> 850.72142 | N56: =N22*N40/1000000 -> 1189.422 | P56: =I56 -> Anti-bacterial Interior paint | Q56: =Q40*Q22/1000000 -> 22.62 | R56: =R40*R22/1000000 -> 37.82064 | S56: =S40*S22/1000000 -> 69.56634 | T56: =T40*T22/1000000 -> 120.21063 | U56: =U40*U22/1000000 -> 168.0705
A57: =A49 -> Silk emulsion | C57: =C41*C23/1000000 -> 424.235 | D57: =D41*D23/1000000 -> 709.32092 | E57: =E41*E23/1000000 -> 1304.7072 | F57: =F41*F23/1000000 -> 2254.534 | G57: =G41*G23/1000000 -> 3152.1391 | I57: =A57 -> Silk emulsion | J57: =J23*J41/1000000 -> 129.195 | K57: =K23*K41/1000000 -> 216.01404 | L57: =L23*L41/1000000 -> 397.33082 | M57: =M23*M41/1000000 -> 686.58767 | N57: =N23*N41/1000000 -> 959.9411 | P57: =I57 -> Silk emulsion | Q57: =Q41*Q23/1000000 -> 20.332 | R57: =R41*R23/1000000 -> 33.995104 | S57: =S41*S23/1000000 -> 62.529744 | T57: =T41*T23/1000000 -> 108.0514 | U57: =U41*U23/1000000 -> 151.07026
A58: =A50 -> Weather resistent exterior paint | C58: =C42*C24/1000000 -> 395.04 | D58: =D42*D24/1000000 -> 660.50688 | E58: =E42*E24/1000000 -> 1214.9198 | F58: =F42*F24/1000000 -> 2099.3815 | G58: =G42*G24/1000000 -> 2935.2152 | I58: =A58 -> Weather resistent exterior paint | J58: =J24*J42/1000000 -> 120.05 | K58: =K24*K42/1000000 -> 200.7236 | L58: =L24*L42/1000000 -> 369.20597 | M58: =M24*M42/1000000 -> 637.98792 | N58: =N24*N42/1000000 -> 891.99218 | P58: =I58 -> Weather resistent exterior paint | Q58: =Q42*Q24/1000000 -> 23.25 | R58: =R42*R24/1000000 -> 38.874 | S58: =S42*S24/1000000 -> 71.503864 | T58: =T42*T24/1000000 -> 123.55868 | U58: =U42*U24/1000000 -> 172.7515
A59: =A51 -> Super primer | C59: =C43*C25/1000000 -> 180.775 | D59: =D43*D25/1000000 -> 302.2558 | E59: =E43*E25/1000000 -> 555.96176 | F59: =F43*F25/1000000 -> 960.70192 | G59: =G43*G25/1000000 -> 1343.1894 | I59: =A59 -> Super primer | J59: =J25*J43/1000000 -> 54.76 | K59: =K25*K43/1000000 -> 91.55872 | L59: =L25*L43/1000000 -> 168.41082 | M59: =M25*M43/1000000 -> 291.0139 | N59: =N25*N43/1000000 -> 406.87623 | P59: =I59 -> Super primer | Q59: =Q43*Q25/1000000 -> 10.26 | R59: =R43*R25/1000000 -> 17.15472 | S59: =S43*S25/1000000 -> 31.553963 | T59: =T43*T25/1000000 -> 54.525248 | U59: =U43*U25/1000000 -> 76.233567
A60: =A52 -> Synthetic Enamel | C60: =C44*C26/1000000 -> 638.72 | D60: =D44*D26/1000000 -> 1067.9398 | E60: =E44*E26/1000000 -> 1964.3418 | F60: =F44*F26/1000000 -> 3394.3827 | G60: =G44*G26/1000000 -> 4745.7996 | I60: =A60 -> Synthetic Enamel | J60: =J26*J44/1000000 -> 179.64 | K60: =K26*K44/1000000 -> 300.35808 | L60: =L26*L44/1000000 -> 552.47114 | M60: =M26*M44/1000000 -> 954.67014 | N60: =N26*N44/1000000 -> 1334.7561 | P60: =I60 -> Synthetic Enamel | Q60: =Q44*Q26/1000000 -> 34.93 | R60: =R44*R26/1000000 -> 58.40296 | S60: =S44*S26/1000000 -> 107.42494 | T60: =T44*T26/1000000 -> 185.6303 | U60: =U44*U26/1000000 -> 259.53592
P61: =I61
A62: Total Revenue | C62: =C54 -> 2026 | D62: =D54 -> 2027 | E62: =E54 -> 2028 | F62: =F54 -> 2029 | G62: =G54 -> 2030 | I62: =A62 -> Total Revenue | J62: =C62 -> 2026 | K62: =D62 -> 2027 | L62: =E62 -> 2028 | M62: =F62 -> 2029 | N62: =G62 -> 2030 | P62: =I62 -> Total Revenue | Q62: =Q54 -> 2026 | R62: =R54 -> 2027 | S62: =S54 -> 2028 | T62: =T54 -> 2029 | U62: =U54 -> 2030
A63: =A55 -> Royal Matt Emulsion paint | C63: =(C47*Assumptions!D$7)+C55 -> 423.825 | D63: =(D47*Assumptions!E$7)+D55 -> 880.34104 | E63: =(E47*Assumptions!F$7)+E55 -> 1714.8631 | F63: =(F47*Assumptions!G$7)+F55 -> 2949.2009 | G63: =(G47*Assumptions!H$7)+G55 -> 4399.2341 | I63: =A63 -> Royal Matt Emulsion paint | J63: =(Assumptions!D$7*J47)+J55 -> 131.76 | K63: =(Assumptions!E$7*K47)+K55 -> 273.68309 | L63: =(Assumptions!F$7*L47)+L55 -> 533.12184 | M63: =(Assumptions!G$7*M47)+M55 -> 916.85651 | N63: =(Assumptions!H$7*N47)+N55 -> 1367.6472 | P63: =I63 -> Royal Matt Emulsion paint | Q63: =(Q47*Assumptions!D$7)+Q55 -> 17.115 | R63: =(R47*Assumptions!E$7)+R55 -> 35.550137 | S63: =(S47*Assumptions!F$7)+S55 -> 69.250003 | T63: =(T47*Assumptions!G$7)+T55 -> 119.09532 | U63: =(U47*Assumptions!H$7)+U55 -> 177.6509
A64: =A56 -> Anti-bacterial Interior paint | C64: =(C48*Assumptions!D$7)+C56 -> 501.12 | D64: =(D48*Assumptions!E$7)+D56 -> 1040.8931 | E64: =(E48*Assumptions!F$7)+E56 -> 2027.6109 | F64: =(F48*Assumptions!G$7)+F56 -> 3487.0608 | G64: =(G48*Assumptions!H$7)+G56 -> 5201.5435 | I64: =A64 -> Anti-bacterial Interior paint | J64: =(Assumptions!D$7*J48)+J56 -> 160.08 | K64: =(Assumptions!E$7*K48)+K56 -> 332.5075 | L64: =(Assumptions!F$7*L48)+L56 -> 647.70905 | M64: =(Assumptions!G$7*M48)+M56 -> 1113.9222 | N64: =(Assumptions!H$7*N48)+N56 -> 1661.6042 | P64: =I64 -> Anti-bacterial Interior paint | Q64: =(Q48*Assumptions!D$7)+Q56 -> 22.62 | R64: =(R48*Assumptions!E$7)+R56 -> 46.984756 | S64: =(S48*Assumptions!F$7)+S56 -> 91.524105 | T64: =(T48*Assumptions!G$7)+T56 -> 157.40205 | U64: =(U48*Assumptions!H$7)+U56 -> 234.7919
A65: =A57 -> Silk emulsion | C65: =(C49*Assumptions!D$7)+C57 -> 424.235 | D65: =(D49*Assumptions!E$7)+D57 -> 881.19266 | E65: =(E49*Assumptions!F$7)+E57 -> 1716.5221 | F65: =(F49*Assumptions!G$7)+F57 -> 2952.0539 | G65: =(G49*Assumptions!H$7)+G57 -> 4403.4898 | I65: =A65 -> Silk emulsion | J65: =(Assumptions!D$7*J49)+J57 -> 129.195 | K65: =(Assumptions!E$7*K49)+K57 -> 268.35524 | L65: =(Assumptions!F$7*L49)+L57 -> 522.74345 | M65: =(Assumptions!G$7*M49)+M57 -> 899.00786 | N65: =(Assumptions!H$7*N49)+N57 -> 1341.0229 | P65: =I65 -> Silk emulsion | Q65: =(Q49*Assumptions!D$7)+Q57 -> 20.332 | R65: =(R49*Assumptions!E$7)+R57 -> 42.232275 | S65: =(S49*Assumptions!F$7)+S57 -> 82.266495 | T65: =(T49*Assumptions!G$7)+T57 -> 141.48092 | U65: =(U49*Assumptions!H$7)+U57 -> 211.04283
A66: =A58 -> Weather resistent exterior paint | C66: =(C50*Assumptions!D$7)+C58 -> 395.04 | D66: =(D50*Assumptions!E$7)+D58 -> 820.55075 | E66: =(E50*Assumptions!F$7)+E58 -> 1598.3945 | F66: =(F50*Assumptions!G$7)+F58 -> 2748.8995 | G66: =(G50*Assumptions!H$7)+G58 -> 4100.4505 | I66: =A66 -> Weather resistent exterior paint | J66: =(Assumptions!D$7*J50)+J58 -> 120.05 | K66: =(Assumptions!E$7*K50)+K58 -> 249.35986 | L66: =(Assumptions!F$7*L50)+L58 -> 485.74133 | M66: =(Assumptions!G$7*M50)+M58 -> 835.37207 | N66: =(Assumptions!H$7*N50)+N58 -> 1246.0993 | P66: =I66 -> Weather resistent exterior paint | Q66: =(Q50*Assumptions!D$7)+Q58 -> 23.25 | R66: =(R50*Assumptions!E$7)+R58 -> 48.29335 | S66: =(S50*Assumptions!F$7)+S58 -> 94.073185 | T66: =(T50*Assumptions!G$7)+T58 -> 161.78593 | U66: =(U50*Assumptions!H$7)+U58 -> 241.33119
A67: =A59 -> Super primer | C67: =(C51*Assumptions!D$7)+C59 -> 180.775 | D67: =(D51*Assumptions!E$7)+D59 -> 375.49378 | E67: =(E51*Assumptions!F$7)+E59 -> 731.4443 | F67: =(F51*Assumptions!G$7)+F59 -> 1257.9291 | G67: =(G51*Assumptions!H$7)+G59 -> 1876.4149 | I67: =A67 -> Super primer | J67: =(Assumptions!D$7*J51)+J59 -> 54.76 | K67: =(Assumptions!E$7*K51)+K59 -> 113.74382 | L67: =(Assumptions!F$7*L51)+L59 -> 221.56764 | M67: =(Assumptions!G$7*M51)+M59 -> 381.04935 | N67: =(Assumptions!H$7*N51)+N59 -> 568.39983 | P67: =I67 -> Super primer | Q67: =(Q51*Assumptions!D$7)+Q59 -> 10.26 | R67: =(R51*Assumptions!E$7)+R59 -> 21.311388 | S67: =(S51*Assumptions!F$7)+S59 -> 41.513586 | T67: =(T51*Assumptions!G$7)+T59 -> 71.394564 | U67: =(U51*Assumptions!H$7)+U59 -> 106.49712
A68: =A60 -> Synthetic Enamel | C68: =(C52*Assumptions!D$7)+C60 -> 638.72 | D68: =(D52*Assumptions!E$7)+D60 -> 1326.7066 | E68: =(E52*Assumptions!F$7)+E60 -> 2584.3624 | F68: =(F52*Assumptions!G$7)+F60 -> 4444.5552 | G68: =(G52*Assumptions!H$7)+G60 -> 6629.809 | I68: =A68 -> Synthetic Enamel | J68: =(Assumptions!D$7*J52)+J60 -> 179.64 | K68: =(Assumptions!E$7*K52)+K60 -> 373.13623 | L68: =(Assumptions!F$7*L52)+L60 -> 726.85191 | M68: =(Assumptions!G$7*M52)+M60 -> 1250.0311 | N68: =(Assumptions!H$7*N52)+N60 -> 1864.6338 | P68: =I68 -> Synthetic Enamel | Q68: =(Q52*Assumptions!D$7)+Q60 -> 34.93 | R68: =(R52*Assumptions!E$7)+R60 -> 72.554267 | S68: =(S52*Assumptions!F$7)+S60 -> 141.33232 | T68: =(T52*Assumptions!G$7)+T60 -> 243.06161 | U68: =(U52*Assumptions!H$7)+U60 -> 362.56768
P69: =I69
C70: =C62 -> 2026 | D70: =D62 -> 2027 | E70: =E62 -> 2028 | F70: =F62 -> 2029 | G70: =G62 -> 2030 | J70: =C70 -> 2026 | K70: =D70 -> 2027 | L70: =E70 -> 2028 | M70: =F70 -> 2029 | N70: =G70 -> 2030 | P70: =I70 | Q70: =Q62 -> 2026 | R70: =R62 -> 2027 | S70: =S62 -> 2028 | T70: =T62 -> 2029 | U70: =U62 -> 2030
A71: Total Export Sales | C71: =SUM(C47:C52)*Assumptions!D$7 -> 0 | D71: =SUM(D47:D52)*Assumptions!E$7 -> 1038.6464 | E71: =SUM(E47:E52)*Assumptions!F$7 -> 2488.6584 | F71: =SUM(F47:F52)*Assumptions!G$7 -> 4215.2162 | G71: =SUM(G47:G52)*Assumptions!H$7 -> 7562.0978 | I71: =A71 -> Total Export Sales | J71: =SUM(J47:J52)*Assumptions!D$7 -> 0 | K71: =SUM(K47:K52)*Assumptions!E$7 -> 314.17482 | L71: =SUM(L47:L52)*Assumptions!F$7 -> 752.78151 | M71: =SUM(M47:M52)*Assumptions!G$7 -> 1275.0391 | N71: =SUM(N47:N52)*Assumptions!H$7 -> 2287.4202 | P71: =I71 -> Total Export Sales | Q71: =SUM(Q47:Q52)*Assumptions!D$7 -> 0 | R71: =SUM(R47:R52)*Assumptions!E$7 -> 52.062469 | S71: =SUM(S47:S52)*Assumptions!F$7 -> 124.74476 | T71: =SUM(T47:T52)*Assumptions!G$7 -> 211.289 | U71: =SUM(U47:U52)*Assumptions!H$7 -> 379.05247
A72: Total Local sales | C72: =SUM(C55:C60) -> 2563.715 | D72: =SUM(D55:D60) -> 4286.5315 | E72: =SUM(E55:E60) -> 7884.5388 | F72: =SUM(F55:F60) -> 13624.483 | G72: =SUM(G55:G60) -> 19048.844 | I72: =A72 -> Total Local sales | J72: =SUM(J55:J60) -> 775.485 | K72: =SUM(K55:K60) -> 1296.6109 | L72: =SUM(L55:L60) -> 2384.9537 | M72: =SUM(M55:M60) -> 4121.2 | N72: =SUM(N55:N60) -> 5761.9871 | P72: =I72 -> Total Local sales | Q72: =SUM(Q55:Q60) -> 128.507 | R72: =SUM(R55:R60) -> 214.8637 | S72: =SUM(S55:S60) -> 395.21493 | T72: =SUM(T55:T60) -> 682.93139 | U72: =SUM(U55:U60) -> 954.82914
A73: Total Sales | C73: =SUM(C71:C72) -> 2563.715 | D73: =SUM(D71:D72) -> 5325.1779 | E73: =SUM(E71:E72) -> 10373.197 | F73: =SUM(F71:F72) -> 17839.699 | G73: =SUM(G71:G72) -> 26610.942 | I73: =A73 -> Total Sales | J73: =SUM(J71:J72) -> 775.485 | K73: =SUM(K71:K72) -> 1610.7857 | L73: =SUM(L71:L72) -> 3137.7352 | M73: =SUM(M71:M72) -> 5396.2391 | N73: =SUM(N71:N72) -> 8049.4073 | P73: =I73 -> Total Sales | Q73: =SUM(Q71:Q72) -> 128.507 | R73: =SUM(R71:R72) -> 266.92617 | S73: =SUM(S71:S72) -> 519.95969 | T73: =SUM(T71:T72) -> 894.22039 | U73: =SUM(U71:U72) -> 1333.8816
A76: Total Sales | C76: =J70 -> 2026 | D76: =K70 -> 2027 | E76: =L70 -> 2028 | F76: =M70 -> 2029 | G76: =N70 -> 2030
A77: Drummi | C77: =C73 -> 2563.715 | D77: =D73 -> 5325.1779 | E77: =E73 -> 10373.197 | F77: =F73 -> 17839.699 | G77: =G73 -> 26610.942
A78: Gallon | C78: =J73 -> 775.485 | D78: =K73 -> 1610.7857 | E78: =L73 -> 3137.7352 | F78: =M73 -> 5396.2391 | G78: =N73 -> 8049.4073
A79: Litre | C79: =Q73 -> 128.507 | D79: =R73 -> 266.92617 | E79: =S73 -> 519.95969 | F79: =T73 -> 894.22039 | G79: =U73 -> 1333.8816
C80: =SUM(C77:C79) -> 3467.707 | D80: =SUM(D77:D79) -> 7202.8898 | E80: =SUM(E77:E79) -> 14030.892 | F80: =SUM(F77:F79) -> 24130.159 | G80: =SUM(G77:G79) -> 35994.231

Sheet Cost
A1: Cost
A2: DRUMMI | H2: GALLON | O2: LITRE
A3: Direct Labor | H3: =A3 -> Direct Labor | O3: =H3 -> Direct Labor
O4: =H4
A5: DL cost per product (PKR) | B5: =Sales!C4 -> 2026 | C5: =Sales!D4 -> 2027 | D5: =Sales!E4 -> 2028 | E5: =Sales!F4 -> 2029 | F5: =Sales!G4 -> 2030 | H5: =A5 -> DL cost per product (PKR) | I5: =B5 -> 2026 | J5: =C5 -> 2027 | K5: =D5 -> 2028 | L5: =E5 -> 2029 | M5: =F5 -> 2030 | O5: =H5 -> DL cost per product (PKR) | P5: =I5 -> 2026 | Q5: =J5 -> 2027 | R5: =K5 -> 2028 | S5: =L5 -> 2029 | T5: =M5 -> 2030
A6: =Sales!A5 -> Royal Matt Emulsion paint | B6: =Assumptions!$B91*Assumptions!B$99 -> 125 | C6: =Assumptions!$B91*Assumptions!C$99 -> 136.25 | D6: =Assumptions!$B91*Assumptions!D$99 -> 147.15 | E6: =Assumptions!$B91*Assumptions!E$99 -> 157.4505 | F6: =Assumptions!$B91*Assumptions!F$99 -> 167.68478 | H6: =A6 -> Royal Matt Emulsion paint | I6: =Assumptions!$C91*Assumptions!B$99 -> 31.25 | J6: =Assumptions!$C91*Assumptions!C$99 -> 34.0625 | K6: =Assumptions!$C91*Assumptions!D$99 -> 36.7875 | L6: =Assumptions!$C91*Assumptions!E$99 -> 39.362625 | M6: =Assumptions!$C91*Assumptions!F$99 -> 41.921196 | O6: =H6 -> Royal Matt Emulsion paint | P6: =Assumptions!$D91*Assumptions!B$99 -> 7.8125 | Q6: =Assumptions!$D91*Assumptions!C$99 -> 8.515625 | R6: =Assumptions!$D91*Assumptions!D$99 -> 9.196875 | S6: =Assumptions!$D91*Assumptions!E$99 -> 9.8406563 | T6: =Assumptions!$D91*Assumptions!F$99 -> 10.480299
A7: =Sales!A6 -> Anti-bacterial Interior paint | B7: =Assumptions!$B92*Assumptions!B$99 -> 225 | C7: =Assumptions!$B92*Assumptions!C$99 -> 245.25 | D7: =Assumptions!$B92*Assumptions!D$99 -> 264.87 | E7: =Assumptions!$B92*Assumptions!E$99 -> 283.4109 | F7: =Assumptions!$B92*Assumptions!F$99 -> 301.83261 | H7: =A7 -> Anti-bacterial Interior paint | I7: =Assumptions!$C92*Assumptions!B$99 -> 56.25 | J7: =Assumptions!$C92*Assumptions!C$99 -> 61.3125 | K7: =Assumptions!$C92*Assumptions!D$99 -> 66.2175 | L7: =Assumptions!$C92*Assumptions!E$99 -> 70.852725 | M7: =Assumptions!$C92*Assumptions!F$99 -> 75.458152 | O7: =H7 -> Anti-bacterial Interior paint | P7: =Assumptions!$D92*Assumptions!B$99 -> 14.0625 | Q7: =Assumptions!$D92*Assumptions!C$99 -> 15.328125 | R7: =Assumptions!$D92*Assumptions!D$99 -> 16.554375 | S7: =Assumptions!$D92*Assumptions!E$99 -> 17.713181 | T7: =Assumptions!$D92*Assumptions!F$99 -> 18.864538
A8: =Sales!A7 -> Silk emulsion | B8: =Assumptions!$B93*Assumptions!B$99 -> 150 | C8: =Assumptions!$B93*Assumptions!C$99 -> 163.5 | D8: =Assumptions!$B93*Assumptions!D$99 -> 176.58 | E8: =Assumptions!$B93*Assumptions!E$99 -> 188.9406 | F8: =Assumptions!$B93*Assumptions!F$99 -> 201.22174 | H8: =A8 -> Silk emulsion | I8: =Assumptions!$C93*Assumptions!B$99 -> 37.5 | J8: =Assumptions!$C93*Assumptions!C$99 -> 40.875 | K8: =Assumptions!$C93*Assumptions!D$99 -> 44.145 | L8: =Assumptions!$C93*Assumptions!E$99 -> 47.23515 | M8: =Assumptions!$C93*Assumptions!F$99 -> 50.305435 | O8: =H8 -> Silk emulsion | P8: =Assumptions!$D93*Assumptions!B$99 -> 9.375 | Q8: =Assumptions!$D93*Assumptions!C$99 -> 10.21875 | R8: =Assumptions!$D93*Assumptions!D$99 -> 11.03625 | S8: =Assumptions!$D93*Assumptions!E$99 -> 11.808787 | T8: =Assumptions!$D93*Assumptions!F$99 -> 12.576359
A9: =Sales!A8 -> Weather resistent exterior paint | B9: =Assumptions!$B94*Assumptions!B$99 -> 175 | C9: =Assumptions!$B94*Assumptions!C$99 -> 190.75 | D9: =Assumptions!$B94*Assumptions!D$99 -> 206.01 | E9: =Assumptions!$B94*Assumptions!E$99 -> 220.4307 | F9: =Assumptions!$B94*Assumptions!F$99 -> 234.7587 | H9: =A9 -> Weather resistent exterior paint | I9: =Assumptions!$C94*Assumptions!B$99 -> 43.75 | J9: =Assumptions!$C94*Assumptions!C$99 -> 47.6875 | K9: =Assumptions!$C94*Assumptions!D$99 -> 51.5025 | L9: =Assumptions!$C94*Assumptions!E$99 -> 55.107675 | M9: =Assumptions!$C94*Assumptions!F$99 -> 58.689674 | O9: =H9 -> Weather resistent exterior paint | P9: =Assumptions!$D94*Assumptions!B$99 -> 10.9375 | Q9: =Assumptions!$D94*Assumptions!C$99 -> 11.921875 | R9: =Assumptions!$D94*Assumptions!D$99 -> 12.875625 | S9: =Assumptions!$D94*Assumptions!E$99 -> 13.776919 | T9: =Assumptions!$D94*Assumptions!F$99 -> 14.672418
A10: =Sales!A9 -> Super primer | B10: =Assumptions!$B95*Assumptions!B$99 -> 100 | C10: =Assumptions!$B95*Assumptions!C$99 -> 109 | D10: =Assumptions!$B95*Assumptions!D$99 -> 117.72 | E10: =Assumptions!$B95*Assumptions!E$99 -> 125.9604 | F10: =Assumptions!$B95*Assumptions!F$99 -> 134.14783 | H10: =A10 -> Super primer | I10: =Assumptions!$C95*Assumptions!B$99 -> 25 | J10: =Assumptions!$C95*Assumptions!C$99 -> 27.25 | K10: =Assumptions!$C95*Assumptions!D$99 -> 29.43 | L10: =Assumptions!$C95*Assumptions!E$99 -> 31.4901 | M10: =Assumptions!$C95*Assumptions!F$99 -> 33.536957 | O10: =H10 -> Super primer | P10: =Assumptions!$D95*Assumptions!B$99 -> 6.25 | Q10: =Assumptions!$D95*Assumptions!C$99 -> 6.8125 | R10: =Assumptions!$D95*Assumptions!D$99 -> 7.3575 | S10: =Assumptions!$D95*Assumptions!E$99 -> 7.872525 | T10: =Assumptions!$D95*Assumptions!F$99 -> 8.3842391
A11: =Sales!A10 -> Synthetic Enamel | B11: =Assumptions!$B96*Assumptions!B$99 -> 200 | C11: =Assumptions!$B96*Assumptions!C$99 -> 218 | D11: =Assumptions!$B96*Assumptions!D$99 -> 235.44 | E11: =Assumptions!$B96*Assumptions!E$99 -> 251.9208 | F11: =Assumptions!$B96*Assumptions!F$99 -> 268.29565 | H11: =A11 -> Synthetic Enamel | I11: =Assumptions!$C96*Assumptions!B$99 -> 50 | J11: =Assumptions!$C96*Assumptions!C$99 -> 54.5 | K11: =Assumptions!$C96*Assumptions!D$99 -> 58.86 | L11: =Assumptions!$C96*Assumptions!E$99 -> 62.9802 | M11: =Assumptions!$C96*Assumptions!F$99 -> 67.073913 | O11: =H11 -> Synthetic Enamel | P11: =Assumptions!$D96*Assumptions!B$99 -> 12.5 | Q11: =Assumptions!$D96*Assumptions!C$99 -> 13.625 | R11: =Assumptions!$D96*Assumptions!D$99 -> 14.715 | S11: =Assumptions!$D96*Assumptions!E$99 -> 15.74505 | T11: =Assumptions!$D96*Assumptions!F$99 -> 16.768478
O12: =H12
A13: DL cost PKR Mn | B13: =B5 -> 2026 | C13: =C5 -> 2027 | D13: =D5 -> 2028 | E13: =E5 -> 2029 | F13: =F5 -> 2030 | H13: =A13 -> DL cost PKR Mn | I13: =B13 -> 2026 | J13: =C13 -> 2027 | K13: =D13 -> 2028 | L13: =E13 -> 2029 | M13: =F13 -> 2030 | O13: =H13 -> DL cost PKR Mn | P13: =I13 -> 2026 | Q13: =J13 -> 2027 | R13: =K13 -> 2028 | S13: =L13 -> 2029 | T13: =M13 -> 2030
A14: =A6 -> Royal Matt Emulsion paint | B14: =B6*Sales!C5/1000000 -> 3.125 | C14: =C6*Sales!D5/1000000 -> 6.471875 | D14: =D6*Sales!E5/1000000 -> 12.581325 | E14: =E6*Sales!F5/1000000 -> 21.539228 | F14: =F6*Sales!G5/1000000 -> 32.11499 | H14: =A14 -> Royal Matt Emulsion paint | I14: =I6*Sales!J5/1000000 -> 0.9375 | J14: =J6*Sales!K5/1000000 -> 1.9415625 | K14: =K6*Sales!L5/1000000 -> 3.7743975 | L14: =L6*Sales!M5/1000000 -> 6.4617685 | M14: =M6*Sales!N5/1000000 -> 9.6344969 | O14: =H14 -> Royal Matt Emulsion paint | P14: =P6*Sales!Q5/1000000 -> 0.1171875 | Q14: =Q6*Sales!R5/1000000 -> 0.24269531 | R14: =R6*Sales!S5/1000000 -> 0.47179969 | S14: =S6*Sales!T5/1000000 -> 0.80772106 | T14: =T6*Sales!U5/1000000 -> 1.2043121
A15: =A7 -> Anti-bacterial Interior paint | B15: =B7*Sales!C6/1000000 -> 4.05 | C15: =C7*Sales!D6/1000000 -> 8.38755 | D15: =D7*Sales!E6/1000000 -> 16.305397 | E15: =E7*Sales!F6/1000000 -> 27.91484 | F15: =F7*Sales!G6/1000000 -> 41.621026 | H15: =A15 -> Anti-bacterial Interior paint | I15: =I7*Sales!J6/1000000 -> 1.29375 | J15: =J7*Sales!K6/1000000 -> 2.6793563 | K15: =K7*Sales!L6/1000000 -> 5.2086685 | L15: =L7*Sales!M6/1000000 -> 8.9172406 | M15: =M7*Sales!N6/1000000 -> 13.295606 | O15: =H15 -> Anti-bacterial Interior paint | P15: =P7*Sales!Q6/1000000 -> 0.1828125 | Q15: =Q7*Sales!R6/1000000 -> 0.37860469 | R15: =R7*Sales!S6/1000000 -> 0.73600751 | S15: =S7*Sales!T6/1000000 -> 1.2600449 | T15: =T7*Sales!U6/1000000 -> 1.8787269
A16: =A8 -> Silk emulsion | B16: =B8*Sales!C7/1000000 -> 3.45 | C16: =C8*Sales!D7/1000000 -> 7.14495 | D16: =D8*Sales!E7/1000000 -> 13.889783 | E16: =E8*Sales!F7/1000000 -> 23.779308 | F16: =F8*Sales!G7/1000000 -> 35.454948 | H16: =A16 -> Silk emulsion | I16: =I8*Sales!J7/1000000 -> 1.0125 | J16: =J8*Sales!K7/1000000 -> 2.0968875 | K16: =K8*Sales!L7/1000000 -> 4.0763493 | L16: =L8*Sales!M7/1000000 -> 6.97871 | M16: =M8*Sales!N7/1000000 -> 10.405257 | O16: =H16 -> Silk emulsion | P16: =P8*Sales!Q7/1000000 -> 0.159375 | Q16: =Q8*Sales!R7/1000000 -> 0.33006562 | R16: =R8*Sales!S7/1000000 -> 0.64164758 | S16: =S8*Sales!T7/1000000 -> 1.0985006 | T16: =T8*Sales!U7/1000000 -> 1.6378645
A17: =A9 -> Weather resistent exterior paint | B17: =B9*Sales!C8/1000000 -> 5.25 | C17: =C9*Sales!D8/1000000 -> 10.87275 | D17: =D9*Sales!E8/1000000 -> 21.136626 | E17: =E9*Sales!F8/1000000 -> 36.185904 | F17: =F9*Sales!G8/1000000 -> 53.953182 | H17: =A17 -> Weather resistent exterior paint | I17: =I9*Sales!J8/1000000 -> 1.53125 | J17: =J9*Sales!K8/1000000 -> 3.1712187 | K17: =K9*Sales!L8/1000000 -> 6.1648492 | L17: =L9*Sales!M8/1000000 -> 10.554222 | M17: =M9*Sales!N8/1000000 -> 15.736345 | O17: =H17 -> Weather resistent exterior paint | P17: =P9*Sales!Q8/1000000 -> 0.2734375 | Q17: =Q9*Sales!R8/1000000 -> 0.56628906 | R17: =R9*Sales!S8/1000000 -> 1.1008659 | S17: =S9*Sales!T8/1000000 -> 1.8846825 | T17: =T9*Sales!U8/1000000 -> 2.8100616
A18: =A10 -> Super primer | B18: =B10*Sales!C9/1000000 -> 3.5 | C18: =C10*Sales!D9/1000000 -> 7.2485 | D18: =D10*Sales!E9/1000000 -> 14.091084 | E18: =E10*Sales!F9/1000000 -> 24.123936 | F18: =F10*Sales!G9/1000000 -> 35.968788 | H18: =A18 -> Super primer | I18: =I10*Sales!J9/1000000 -> 1 | J18: =J10*Sales!K9/1000000 -> 2.071 | K18: =K10*Sales!L9/1000000 -> 4.026024 | L18: =L10*Sales!M9/1000000 -> 6.8925531 | M18: =M10*Sales!N9/1000000 -> 10.276797 | O18: =H18 -> Super primer | P18: =P10*Sales!Q9/1000000 -> 0.1875 | Q18: =Q10*Sales!R9/1000000 -> 0.3883125 | R18: =R10*Sales!S9/1000000 -> 0.7548795 | S18: =S10*Sales!T9/1000000 -> 1.2923537 | T18: =T10*Sales!U9/1000000 -> 1.9268994
A19: =A11 -> Synthetic Enamel | B19: =B11*Sales!C10/1000000 -> 8 | C19: =C11*Sales!D10/1000000 -> 16.568 | D19: =D11*Sales!E10/1000000 -> 32.208192 | E19: =E11*Sales!F10/1000000 -> 55.140425 | F19: =F11*Sales!G10/1000000 -> 82.214373 | H19: =A19 -> Synthetic Enamel | I19: =I11*Sales!J10/1000000 -> 2.25 | J19: =J11*Sales!K10/1000000 -> 4.65975 | K19: =K11*Sales!L10/1000000 -> 9.058554 | L19: =L11*Sales!M10/1000000 -> 15.508244 | M19: =M11*Sales!N10/1000000 -> 23.122792 | O19: =H19 -> Synthetic Enamel | P19: =P11*Sales!Q10/1000000 -> 0.4375 | Q19: =Q11*Sales!R10/1000000 -> 0.9060625 | R19: =R11*Sales!S10/1000000 -> 1.7613855 | S19: =S11*Sales!T10/1000000 -> 3.015492 | T19: =T11*Sales!U10/1000000 -> 4.4960985
A20: Total DL cost | B20: =SUM(B14:B19) -> 27.375 | C20: =SUM(C14:C19) -> 56.693625 | D20: =SUM(D14:D19) -> 110.21241 | E20: =SUM(E14:E19) -> 188.68364 | F20: =SUM(F14:F19) -> 281.32731 | H20: =A20 -> Total DL cost | I20: =SUM(I14:I19) -> 8.025 | J20: =SUM(J14:J19) -> 16.619775 | K20: =SUM(K14:K19) -> 32.308843 | L20: =SUM(L14:L19) -> 55.312739 | M20: =SUM(M14:M19) -> 82.471293 | O20: =H20 -> Total DL cost | P20: =SUM(P14:P19) -> 1.3578125 | Q20: =SUM(Q14:Q19) -> 2.8120297 | R20: =SUM(R14:R19) -> 5.4665857 | S20: =SUM(S14:S19) -> 9.3587947 | T20: =SUM(T14:T19) -> 13.953963
O21: =H21
A22: Raw Material Cost | H22: =A22 -> Raw Material Cost | O22: =H22 -> Raw Material Cost
O23: =H23
A24: Raw material Cost per product | B24: =B13 -> 2026 | C24: =C13 -> 2027 | D24: =D13 -> 2028 | E24: =E13 -> 2029 | F24: =F13 -> 2030 | H24: =A24 -> Raw material Cost per product | I24: =B24 -> 2026 | J24: =C24 -> 2027 | K24: =D24 -> 2028 | L24: =E24 -> 2029 | M24: =F24 -> 2030 | O24: =H24 -> Raw material Cost per product | P24: =I24 -> 2026 | Q24: =J24 -> 2027 | R24: =K24 -> 2028 | S24: =L24 -> 2029 | T24: =M24 -> 2030
A25: =A14 -> Royal Matt Emulsion paint | B25: =Assumptions!C41 -> 3876 | C25: =Assumptions!D41 -> 4220.12 | D25: =Assumptions!E41 -> 4573.1357 | E25: =Assumptions!F41 -> 4935.0827 | F25: =Assumptions!G41 -> 5316.3735 | H25: =A25 -> Royal Matt Emulsion paint | I25: =Assumptions!K$41 -> 969 | J25: =Assumptions!L$41 -> 1055.03 | K25: =Assumptions!M$41 -> 1143.2839 | L25: =Assumptions!N$41 -> 1233.7707 | M25: =Assumptions!O$41 -> 1329.0934 | O25: =H25 -> Royal Matt Emulsion paint | P25: =Assumptions!S41 -> 242.25 | Q25: =Assumptions!T41 -> 263.7575 | R25: =Assumptions!U41 -> 285.82098 | S25: =Assumptions!V41 -> 308.44267 | T25: =Assumptions!W41 -> 332.27335
A26: =A15 -> Anti-bacterial Interior paint | B26: =Assumptions!C51 -> 4635 | C26: =Assumptions!D51 -> 5046.31 | D26: =Assumptions!E51 -> 5469.0766 | E26: =Assumptions!F51 -> 5903.6646 | F26: =Assumptions!G51 -> 6362.2717 | H26: =A26 -> Anti-bacterial Interior paint | I26: =Assumptions!K$51 -> 1158.75 | J26: =Assumptions!L$51 -> 1261.5775 | K26: =Assumptions!M$51 -> 1367.2691 | L26: =Assumptions!N$51 -> 1475.9161 | M26: =Assumptions!O$51 -> 1590.5679 | O26: =H26 -> Anti-bacterial Interior paint | P26: =Assumptions!S51 -> 289.6875 | Q26: =Assumptions!T51 -> 315.39438 | R26: =Assumptions!U51 -> 341.81729 | S26: =Assumptions!V51 -> 368.97904 | T26: =Assumptions!W51 -> 397.64198
A27: =A16 -> Silk emulsion | B27: =Assumptions!C60 -> 5408 | C27: =Assumptions!D60 -> 5890.928 | D27: =Assumptions!E60 -> 6401.0633 | E27: =Assumptions!F60 -> 6943.7781 | F27: =Assumptions!G60 -> 7529.5458 | H27: =A27 -> Silk emulsion | I27: =Assumptions!K$60 -> 1352 | J27: =Assumptions!L$60 -> 1472.732 | K27: =Assumptions!M$60 -> 1600.2658 | L27: =Assumptions!N$60 -> 1735.9445 | M27: =Assumptions!O$60 -> 1882.3865 | O27: =H27 -> Silk emulsion | P27: =Assumptions!S60 -> 338 | Q27: =Assumptions!T60 -> 368.183 | R27: =Assumptions!U60 -> 400.06646 | S27: =Assumptions!V60 -> 433.98613 | T27: =Assumptions!W60 -> 470.59661
A28: =A17 -> Weather resistent exterior paint | B28: =Assumptions!C69 -> 5276 | C28: =Assumptions!D69 -> 5741 | D28: =Assumptions!E69 -> 6232.3978 | E28: =Assumptions!F69 -> 6755.8653 | F28: =Assumptions!G69 -> 7321.1455 | H28: =A28 -> Weather resistent exterior paint | I28: =Assumptions!K69 -> 1319 | J28: =Assumptions!L69 -> 1435.25 | K28: =Assumptions!M69 -> 1558.0994 | L28: =Assumptions!N69 -> 1688.9663 | M28: =Assumptions!O69 -> 1830.2864 | O28: =H28 -> Weather resistent exterior paint | P28: =Assumptions!S69 -> 329.75 | Q28: =Assumptions!T69 -> 358.8125 | R28: =Assumptions!U69 -> 389.52486 | S28: =Assumptions!V69 -> 422.24158 | T28: =Assumptions!W69 -> 457.57159
A29: =A18 -> Super primer | B29: =Assumptions!C77 -> 2911 | C29: =Assumptions!D77 -> 3169.87 | D29: =Assumptions!E77 -> 3433.6433 | E29: =Assumptions!F77 -> 3701.647 | F29: =Assumptions!G77 -> 3982.2525 | H29: =A29 -> Super primer | I29: =Assumptions!K$77 -> 727.75 | J29: =Assumptions!L$77 -> 792.4675 | K29: =Assumptions!M$77 -> 858.41082 | L29: =Assumptions!N$77 -> 925.41175 | M29: =Assumptions!O$77 -> 995.56312 | O29: =H29 -> Super primer | P29: =Assumptions!S77 -> 181.9375 | Q29: =Assumptions!T77 -> 198.11687 | R29: =Assumptions!U77 -> 214.6027 | S29: =Assumptions!V77 -> 231.35294 | T29: =Assumptions!W77 -> 248.89078
A30: =A19 -> Synthetic Enamel | B30: =Assumptions!C85 -> 7670 | C30: =Assumptions!D85 -> 8347.36 | D30: =Assumptions!E85 -> 9068.313 | E30: =Assumptions!F85 -> 9842.7496 | F30: =Assumptions!G85 -> 10683.376 | H30: =A30 -> Synthetic Enamel | I30: =Assumptions!K$85 -> 1917.5 | J30: =Assumptions!L$85 -> 2086.84 | K30: =Assumptions!M$85 -> 2267.0782 | L30: =Assumptions!N$85 -> 2460.6874 | M30: =Assumptions!O$85 -> 2610.9906 | O30: =H30 -> Synthetic Enamel | P30: =Assumptions!S85 -> 479.375 | Q30: =Assumptions!T85 -> 521.71 | R30: =Assumptions!U85 -> 566.76956 | S30: =Assumptions!V85 -> 615.17185 | T30: =Assumptions!W85 -> 652.74766
O31: =H31
A32: Total RM cost PKR Mn | B32: =B24 -> 2026 | C32: =C24 -> 2027 | D32: =D24 -> 2028 | E32: =E24 -> 2029 | F32: =F24 -> 2030 | H32: =A32 -> Total RM cost PKR Mn | I32: =B32 -> 2026 | J32: =C32 -> 2027 | K32: =D32 -> 2028 | L32: =E32 -> 2029 | M32: =F32 -> 2030 | O32: =H32 -> Total RM cost PKR Mn | P32: =I32 -> 2026 | Q32: =J32 -> 2027 | R32: =K32 -> 2028 | S32: =L32 -> 2029 | T32: =M32 -> 2030
A33: =A25 -> Royal Matt Emulsion paint | B33: =B25*Sales!C5/1000000 -> 96.9 | C33: =C25*Sales!D5/1000000 -> 200.4557 | D33: =D25*Sales!E5/1000000 -> 391.0031 | E33: =E25*Sales!F5/1000000 -> 675.11931 | F33: =F25*Sales!G5/1000000 -> 1018.1919 | H33: =A33 -> Royal Matt Emulsion paint | I33: =I25*Sales!J5/1000000 -> 29.07 | J33: =J25*Sales!K5/1000000 -> 60.13671 | K33: =K25*Sales!L5/1000000 -> 117.30093 | L33: =L25*Sales!M5/1000000 -> 202.53579 | M33: =M25*Sales!N5/1000000 -> 305.45756 | O33: =H33 -> Royal Matt Emulsion paint | P33: =P25*Sales!Q5/1000000 -> 3.63375 | Q33: =Q25*Sales!R5/1000000 -> 7.5170888 | R33: =R25*Sales!S5/1000000 -> 14.662616 | S33: =S25*Sales!T5/1000000 -> 25.316974 | T33: =T25*Sales!U5/1000000 -> 38.182195
A34: =A26 -> Anti-bacterial Interior paint | B34: =B26*Sales!C6/1000000 -> 83.43 | C34: =C26*Sales!D6/1000000 -> 172.5838 | D34: =D26*Sales!E6/1000000 -> 336.67635 | E34: =E26*Sales!F6/1000000 -> 581.48735 | F34: =F26*Sales!G6/1000000 -> 877.32163 | H34: =A34 -> Anti-bacterial Interior paint | I34: =I26*Sales!J6/1000000 -> 26.65125 | J34: =J26*Sales!K6/1000000 -> 55.130937 | K34: =K26*Sales!L6/1000000 -> 107.54939 | L34: =L26*Sales!M6/1000000 -> 185.7529 | M34: =M26*Sales!N6/1000000 -> 280.25552 | O34: =H34 -> Anti-bacterial Interior paint | P34: =P26*Sales!Q6/1000000 -> 3.7659375 | Q34: =Q26*Sales!R6/1000000 -> 7.7902411 | R34: =R26*Sales!S6/1000000 -> 15.197196 | S34: =S26*Sales!T6/1000000 -> 26.247693 | T34: =T26*Sales!U6/1000000 -> 39.601324
A35: =A27 -> Silk emulsion | B35: =B27*Sales!C7/1000000 -> 124.384 | C35: =C27*Sales!D7/1000000 -> 257.43355 | D35: =D27*Sales!E7/1000000 -> 503.50764 | E35: =E27*Sales!F7/1000000 -> 873.91614 | F35: =F27*Sales!G7/1000000 -> 1326.6939 | H35: =A35 -> Silk emulsion | I35: =I27*Sales!J7/1000000 -> 36.504 | J35: =J27*Sales!K7/1000000 -> 75.551152 | K35: =K27*Sales!L7/1000000 -> 147.76855 | L35: =L27*Sales!M7/1000000 -> 256.47539 | M35: =M27*Sales!N7/1000000 -> 389.35583 | O35: =H35 -> Silk emulsion | P35: =P27*Sales!Q7/1000000 -> 5.746 | Q35: =Q27*Sales!R7/1000000 -> 11.892311 | R35: =R27*Sales!S7/1000000 -> 23.259864 | S35: =S27*Sales!T7/1000000 -> 40.371126 | T35: =T27*Sales!U7/1000000 -> 61.287491
A36: =A28 -> Weather resistent exterior paint | B36: =B28*Sales!C8/1000000 -> 158.28 | C36: =C28*Sales!D8/1000000 -> 327.237 | D36: =D28*Sales!E8/1000000 -> 639.44401 | E36: =E28*Sales!F8/1000000 -> 1109.0429 | F36: =F28*Sales!G8/1000000 -> 1682.5749 | H36: =A36 -> Weather resistent exterior paint | I36: =I28*Sales!J8/1000000 -> 46.165 | J36: =J28*Sales!K8/1000000 -> 95.444125 | K36: =K28*Sales!L8/1000000 -> 186.5045 | L36: =L28*Sales!M8/1000000 -> 323.47083 | M36: =M28*Sales!N8/1000000 -> 490.75102 | O36: =H36 -> Weather resistent exterior paint | P36: =P28*Sales!Q8/1000000 -> 8.24375 | Q36: =Q28*Sales!R8/1000000 -> 17.043594 | R36: =R28*Sales!S8/1000000 -> 33.304376 | S36: =S28*Sales!T8/1000000 -> 57.762648 | T36: =T28*Sales!U8/1000000 -> 87.634112
A37: =A29 -> Super primer | B37: =B29*Sales!C9/1000000 -> 101.885 | C37: =C29*Sales!D9/1000000 -> 210.79636 | D37: =D29*Sales!E9/1000000 -> 411.0071 | E37: =E29*Sales!F9/1000000 -> 708.93943 | F37: =F29*Sales!G9/1000000 -> 1067.7534 | H37: =A37 -> Super primer | I37: =I29*Sales!J9/1000000 -> 29.11 | J37: =J29*Sales!K9/1000000 -> 60.22753 | K37: =K29*Sales!L9/1000000 -> 117.4306 | L37: =L29*Sales!M9/1000000 -> 202.55412 | M37: =M29*Sales!N9/1000000 -> 305.0724 | O37: =H37 -> Super primer | P37: =P29*Sales!Q9/1000000 -> 5.458125 | Q37: =Q29*Sales!R9/1000000 -> 11.292662 | R37: =R29*Sales!S9/1000000 -> 22.018238 | S37: =S29*Sales!T9/1000000 -> 37.978898 | T37: =T29*Sales!U9/1000000 -> 57.201075
A38: =A30 -> Synthetic Enamel | B38: =B30*Sales!C10/1000000 -> 306.8 | C38: =C30*Sales!D10/1000000 -> 634.39936 | D38: =D30*Sales!E10/1000000 -> 1240.5452 | E38: =E30*Sales!F10/1000000 -> 2154.381 | F38: =F30*Sales!G10/1000000 -> 3273.7284 | H38: =A38 -> Synthetic Enamel | I38: =I30*Sales!J10/1000000 -> 86.2875 | J38: =J30*Sales!K10/1000000 -> 178.42482 | K38: =K30*Sales!L10/1000000 -> 348.90334 | L38: =L30*Sales!M10/1000000 -> 605.91966 | M38: =M30*Sales!N10/1000000 -> 900.10247 | O38: =H38 -> Synthetic Enamel | P38: =P30*Sales!Q10/1000000 -> 16.778125 | Q38: =Q30*Sales!R10/1000000 -> 34.693715 | R38: =R30*Sales!S10/1000000 -> 67.842316 | S38: =S30*Sales!T10/1000000 -> 117.81771 | T38: =T30*Sales!U10/1000000 -> 175.01992
A39: Total RM cost PKR Mn | B39: =SUM(B33:B38) -> 871.679 | C39: =SUM(C33:C38) -> 1802.9058 | D39: =SUM(D33:D38) -> 3522.1834 | E39: =SUM(E33:E38) -> 6102.8861 | F39: =SUM(F33:F38) -> 9246.2641 | H39: =A39 -> Total RM cost PKR Mn | I39: =SUM(I33:I38) -> 253.78775 | J39: =SUM(J33:J38) -> 524.91527 | K39: =SUM(K33:K38) -> 1025.4573 | L39: =SUM(L33:L38) -> 1776.7087 | M39: =SUM(M33:M38) -> 2670.9948 | O39: =H39 -> Total RM cost PKR Mn | P39: =SUM(P33:P38) -> 43.625687 | Q39: =SUM(Q33:Q38) -> 90.229611 | R39: =SUM(R33:R38) -> 176.28461 | S39: =SUM(S33:S38) -> 305.49505 | T39: =SUM(T33:T38) -> 458.92612
O40: =H40
B41: =B24 -> 2026 | C41: =C24 -> 2027 | D41: =D24 -> 2028 | E41: =E24 -> 2029 | F41: =F24 -> 2030 | I41: =B41 -> 2026 | J41: =C41 -> 2027 | K41: =D41 -> 2028 | L41: =E41 -> 2029 | M41: =F41 -> 2030 | O41: =H41
O42: =H42
A43: Total COS | B43: =B39+B20 -> 899.054 | C43: =C39+C20 -> 1859.5994 | D43: =D39+D20 -> 3632.3958 | E43: =E39+E20 -> 6291.5697 | F43: =F39+F20 -> 9527.5914 | H43: =A43 -> Total COS | I43: =I39+I20 -> 261.81275 | J43: =J39+J20 -> 541.53505 | K43: =K39+K20 -> 1057.7662 | L43: =L39+L20 -> 1832.0214 | M43: =M39+M20 -> 2753.4661 | O43: =H43 -> Total COS | P43: =P39+P20 -> 44.9835 | Q43: =Q39+Q20 -> 93.041641 | R43: =R39+R20 -> 181.75119 | S43: =S39+S20 -> 314.85385 | T43: =T39+T20 -> 472.88008
O44: =H44
A45: Packaging and label Cost per product | B45: =B41 -> 2026 | C45: =C41 -> 2027 | D45: =D41 -> 2028 | E45: =E41 -> 2029 | F45: =F41 -> 2030 | H45: =A45 -> Packaging and label Cost per product | I45: =B45 -> 2026 | J45: =C45 -> 2027 | K45: =D45 -> 2028 | L45: =E45 -> 2029 | M45: =F45 -> 2030 | O45: =H45 -> Packaging and label Cost per product | P45: =I45 -> 2026 | Q45: =J45 -> 2027 | R45: =K45 -> 2028 | S45: =L45 -> 2029 | T45: =M45 -> 2030
A46: =A33 -> Royal Matt Emulsion paint | B46: =Assumptions!B102 -> 400 | C46: =Assumptions!C102 -> 436 | D46: =Assumptions!D102 -> 470.88 | E46: =Assumptions!E102 -> 503.8416 | F46: =Assumptions!F102 -> 536.5913 | H46: =A46 -> Royal Matt Emulsion paint | I46: =Assumptions!I102 -> 350 | J46: =Assumptions!J102 -> 381.5 | K46: =Assumptions!K102 -> 412.02 | L46: =Assumptions!L102 -> 440.8614 | M46: =Assumptions!M102 -> 469.51739 | O46: =H46 -> Royal Matt Emulsion paint | P46: =Assumptions!P102 -> 88 | Q46: =Assumptions!Q102 -> 95.92 | R46: =Assumptions!R102 -> 103.5936 | S46: =Assumptions!S102 -> 110.84515 | T46: =Assumptions!T102 -> 118.05009
A47: =A34 -> Anti-bacterial Interior paint | B47: =Assumptions!B103 -> 420 | C47: =Assumptions!C103 -> 457.8 | D47: =Assumptions!D103 -> 494.424 | E47: =Assumptions!E103 -> 529.03368 | F47: =Assumptions!F103 -> 563.42087 | H47: =A47 -> Anti-bacterial Interior paint | I47: =Assumptions!I103 -> 368 | J47: =Assumptions!J103 -> 401.12 | K47: =Assumptions!K103 -> 433.2096 | L47: =Assumptions!L103 -> 463.53427 | M47: =Assumptions!M103 -> 493.664 | O47: =H47 -> Anti-bacterial Interior paint | P47: =Assumptions!P103 -> 92 | Q47: =Assumptions!Q103 -> 100.28 | R47: =Assumptions!R103 -> 108.3024 | S47: =Assumptions!S103 -> 115.88357 | T47: =Assumptions!T103 -> 123.416
A48: =A35 -> Silk emulsion | B48: =Assumptions!B104 -> 450 | C48: =Assumptions!C104 -> 490.5 | D48: =Assumptions!D104 -> 529.74 | E48: =Assumptions!E104 -> 566.8218 | F48: =Assumptions!F104 -> 603.66522 | H48: =A48 -> Silk emulsion | I48: =Assumptions!I104 -> 394 | J48: =Assumptions!J104 -> 429.46 | K48: =Assumptions!K104 -> 463.8168 | L48: =Assumptions!L104 -> 496.28398 | M48: =Assumptions!M104 -> 528.54243 | O48: =H48 -> Silk emulsion | P48: =Assumptions!P104 -> 98 | Q48: =Assumptions!Q104 -> 106.82 | R48: =Assumptions!R104 -> 115.3656 | S48: =Assumptions!S104 -> 123.44119 | T48: =Assumptions!T104 -> 131.46487
A49: =A36 -> Weather resistent exterior paint | B49: =Assumptions!B105 -> 480 | C49: =Assumptions!C105 -> 523.2 | D49: =Assumptions!D105 -> 565.056 | E49: =Assumptions!E105 -> 604.60992 | F49: =Assumptions!F105 -> 643.90956 | H49: =A49 -> Weather resistent exterior paint | I49: =Assumptions!I105 -> 420 | J49: =Assumptions!J105 -> 457.8 | K49: =Assumptions!K105 -> 494.424 | L49: =Assumptions!L105 -> 529.03368 | M49: =Assumptions!M105 -> 563.42087 | O49: =H49 -> Weather resistent exterior paint | P49: =Assumptions!P105 -> 105 | Q49: =Assumptions!Q105 -> 114.45 | R49: =Assumptions!R105 -> 123.606 | S49: =Assumptions!S105 -> 132.25842 | T49: =Assumptions!T105 -> 140.85522
A50: =A37 -> Super primer | B50: =Assumptions!B106 -> 380 | C50: =Assumptions!C106 -> 414.2 | D50: =Assumptions!D106 -> 447.336 | E50: =Assumptions!E106 -> 478.64952 | F50: =Assumptions!F106 -> 509.76174 | H50: =A50 -> Super primer | I50: =Assumptions!I106 -> 333 | J50: =Assumptions!J106 -> 362.97 | K50: =Assumptions!K106 -> 392.0076 | L50: =Assumptions!L106 -> 419.44813 | M50: =Assumptions!M106 -> 446.71226 | O50: =H50 -> Super primer | P50: =Assumptions!P106 -> 83 | Q50: =Assumptions!Q106 -> 90.47 | R50: =Assumptions!R106 -> 97.7076 | S50: =Assumptions!S106 -> 104.54713 | T50: =Assumptions!T106 -> 111.3427
A51: =A38 -> Synthetic Enamel | B51: =Assumptions!B107 -> 500 | C51: =Assumptions!C107 -> 545 | D51: =Assumptions!D107 -> 588.6 | E51: =Assumptions!E107 -> 629.802 | F51: =Assumptions!F107 -> 670.73913 | H51: =A51 -> Synthetic Enamel | I51: =Assumptions!I107 -> 438 | J51: =Assumptions!J107 -> 477.42 | K51: =Assumptions!K107 -> 515.6136 | L51: =Assumptions!L107 -> 551.70655 | M51: =Assumptions!M107 -> 587.56748 | O51: =H51 -> Synthetic Enamel | P51: =Assumptions!P107 -> 109 | Q51: =Assumptions!Q107 -> 118.81 | R51: =Assumptions!R107 -> 128.3148 | S51: =Assumptions!S107 -> 137.29684 | T51: =Assumptions!T107 -> 146.22113
O52: =H52
A53: Total Packaging and Label Cost PKR Mn | B53: =B45 -> 2026 | C53: =C45 -> 2027 | D53: =D45 -> 2028 | E53: =E45 -> 2029 | F53: =F45 -> 2030 | H53: =A53 -> Total Packaging and Label Cost PKR Mn | I53: =B53 -> 2026 | J53: =C53 -> 2027 | K53: =D53 -> 2028 | L53: =E53 -> 2029 | M53: =F53 -> 2030 | O53: =H53 -> Total Packaging and Label Cost PKR Mn | P53: =I53 -> 2026 | Q53: =J53 -> 2027 | R53: =K53 -> 2028 | S53: =L53 -> 2029 | T53: =M53 -> 2030
A54: =A46 -> Royal Matt Emulsion paint | B54: =B46*Sales!C5/1000000 -> 10 | C54: =C46*Sales!D5/1000000 -> 20.71 | D54: =D46*Sales!E5/1000000 -> 40.26024 | E54: =E46*Sales!F5/1000000 -> 68.925531 | F54: =F46*Sales!G5/1000000 -> 102.76797 | H54: =A54 -> Royal Matt Emulsion paint | I54: =I46*Sales!J5/1000000 -> 10.5 | J54: =J46*Sales!K5/1000000 -> 21.7455 | K54: =K46*Sales!L5/1000000 -> 42.273252 | L54: =L46*Sales!M5/1000000 -> 72.371807 | M54: =M46*Sales!N5/1000000 -> 107.90636 | O54: =H54 -> Royal Matt Emulsion paint | P54: =P46*Sales!Q5/1000000 -> 1.32 | Q54: =Q46*Sales!R5/1000000 -> 2.73372 | R54: =R46*Sales!S5/1000000 -> 5.3143517 | S54: =S46*Sales!T5/1000000 -> 9.0981701 | T54: =T46*Sales!U5/1000000 -> 13.565372
A55: =A47 -> Anti-bacterial Interior paint | B55: =B47*Sales!C6/1000000 -> 7.56 | C55: =C47*Sales!D6/1000000 -> 15.65676 | D55: =D47*Sales!E6/1000000 -> 30.436741 | E55: =E47*Sales!F6/1000000 -> 52.107701 | F55: =F47*Sales!G6/1000000 -> 77.692583 | H55: =A55 -> Anti-bacterial Interior paint | I55: =I47*Sales!J6/1000000 -> 8.464 | J55: =J47*Sales!K6/1000000 -> 17.528944 | K55: =K47*Sales!L6/1000000 -> 34.076267 | L55: =L47*Sales!M6/1000000 -> 58.338569 | M55: =M47*Sales!N6/1000000 -> 86.982807 | O55: =H55 -> Anti-bacterial Interior paint | P55: =P47*Sales!Q6/1000000 -> 1.196 | Q55: =Q47*Sales!R6/1000000 -> 2.476916 | R55: =R47*Sales!S6/1000000 -> 4.8151247 | S55: =S47*Sales!T6/1000000 -> 8.2434935 | T55: =T47*Sales!U6/1000000 -> 12.291049
A56: =A48 -> Silk emulsion | B56: =B48*Sales!C7/1000000 -> 10.35 | C56: =C48*Sales!D7/1000000 -> 21.43485 | D56: =D48*Sales!E7/1000000 -> 41.669348 | E56: =E48*Sales!F7/1000000 -> 71.337924 | F56: =F48*Sales!G7/1000000 -> 106.36485 | H56: =A56 -> Silk emulsion | I56: =I48*Sales!J7/1000000 -> 10.638 | J56: =J48*Sales!K7/1000000 -> 22.031298 | K56: =K48*Sales!L7/1000000 -> 42.828843 | L56: =L48*Sales!M7/1000000 -> 73.32298 | M56: =M48*Sales!N7/1000000 -> 109.32456 | O56: =H56 -> Silk emulsion | P56: =P48*Sales!Q7/1000000 -> 1.666 | Q56: =Q48*Sales!R7/1000000 -> 3.450286 | R56: =R48*Sales!S7/1000000 -> 6.707356 | S56: =S48*Sales!T7/1000000 -> 11.482993 | T56: =T48*Sales!U7/1000000 -> 17.121143
A57: =A49 -> Weather resistent exterior paint | B57: =B49*Sales!C8/1000000 -> 14.4 | C57: =C49*Sales!D8/1000000 -> 29.8224 | D57: =D49*Sales!E8/1000000 -> 57.974746 | E57: =E49*Sales!F8/1000000 -> 99.252764 | F57: =F49*Sales!G8/1000000 -> 147.98587 | H57: =A57 -> Weather resistent exterior paint | I57: =I49*Sales!J8/1000000 -> 14.7 | J57: =J49*Sales!K8/1000000 -> 30.4437 | K57: =K49*Sales!L8/1000000 -> 59.182553 | L57: =L49*Sales!M8/1000000 -> 101.32053 | M57: =M49*Sales!N8/1000000 -> 151.06891 | O57: =H57 -> Weather resistent exterior paint | P57: =P49*Sales!Q8/1000000 -> 2.625 | Q57: =Q49*Sales!R8/1000000 -> 5.436375 | R57: =R49*Sales!S8/1000000 -> 10.568313 | S57: =S49*Sales!T8/1000000 -> 18.092952 | T57: =T49*Sales!U8/1000000 -> 26.976591
A58: =A50 -> Super primer | B58: =B50*Sales!C9/1000000 -> 13.3 | C58: =C50*Sales!D9/1000000 -> 27.5443 | D58: =D50*Sales!E9/1000000 -> 53.546119 | E58: =E50*Sales!F9/1000000 -> 91.670956 | F58: =F50*Sales!G9/1000000 -> 136.6814 | H58: =A58 -> Super primer | I58: =I50*Sales!J9/1000000 -> 13.32 | J58: =J50*Sales!K9/1000000 -> 27.58572 | K58: =K50*Sales!L9/1000000 -> 53.62664 | L58: =L50*Sales!M9/1000000 -> 91.808807 | M58: =M50*Sales!N9/1000000 -> 136.88693 | O58: =H58 -> Super primer | P58: =P50*Sales!Q9/1000000 -> 2.49 | Q58: =Q50*Sales!R9/1000000 -> 5.15679 | R58: =R50*Sales!S9/1000000 -> 10.0248 | S58: =S50*Sales!T9/1000000 -> 17.162457 | T58: =T50*Sales!U9/1000000 -> 25.589224
A59: =A51 -> Synthetic Enamel | B59: =B51*Sales!C10/1000000 -> 20 | C59: =C51*Sales!D10/1000000 -> 41.42 | D59: =D51*Sales!E10/1000000 -> 80.52048 | E59: =E51*Sales!F10/1000000 -> 137.85106 | F59: =F51*Sales!G10/1000000 -> 205.53593 | H59: =A59 -> Synthetic Enamel | I59: =I51*Sales!J10/1000000 -> 19.71 | J59: =J51*Sales!K10/1000000 -> 40.81941 | K59: =K51*Sales!L10/1000000 -> 79.352933 | L59: =L51*Sales!M10/1000000 -> 135.85222 | M59: =M51*Sales!N10/1000000 -> 202.55566 | O59: =H59 -> Synthetic Enamel | P59: =P51*Sales!Q10/1000000 -> 3.815 | Q59: =Q51*Sales!R10/1000000 -> 7.900865 | R59: =R51*Sales!S10/1000000 -> 15.359282 | S59: =S51*Sales!T10/1000000 -> 26.29509 | T59: =T51*Sales!U10/1000000 -> 39.205979
A60: Total Packaging and label cost | B60: =SUM(B54:B59) -> 75.61 | C60: =SUM(C54:C59) -> 156.58831 | D60: =SUM(D54:D59) -> 304.40767 | E60: =SUM(E54:E59) -> 521.14594 | F60: =SUM(F54:F59) -> 777.02859 | H60: =A60 -> Total Packaging and label cost | I60: =SUM(I54:I59) -> 77.332 | J60: =SUM(J54:J59) -> 160.15457 | K60: =SUM(K54:K59) -> 311.34049 | L60: =SUM(L54:L59) -> 533.01492 | M60: =SUM(M54:M59) -> 794.72524 | O60: =H60 -> Total Packaging and label cost | P60: =SUM(P54:P59) -> 13.112 | Q60: =SUM(Q54:Q59) -> 27.154952 | R60: =SUM(R54:R59) -> 52.789227 | S60: =SUM(S54:S59) -> 90.375156 | T60: =SUM(T54:T59) -> 134.74936
O61: =H61
A62: Total COS PKR Mn | B62: =B60+B43 -> 974.664 | C62: =C60+C43 -> 2016.1877 | D62: =D60+D43 -> 3936.8035 | E62: =E60+E43 -> 6812.7157 | F62: =F60+F43 -> 10304.62 | H62: =A62 -> Total COS PKR Mn | I62: =I60+I43 -> 339.14475 | J62: =J60+J43 -> 701.68962 | K62: =K60+K43 -> 1369.1066 | L62: =L60+L43 -> 2365.0364 | M62: =M60+M43 -> 3548.1913 | O62: =H62 -> Total COS PKR Mn | P62: =P60+P43 -> 58.0955 | Q62: =Q60+Q43 -> 120.19659 | R62: =R60+R43 -> 234.54042 | S62: =S60+S43 -> 405.229 | T62: =T60+T43 -> 607.62944
A64: Total Cost | B64: =B53 -> 2026 | C64: =C53 -> 2027 | D64: =D53 -> 2028 | E64: =E53 -> 2029 | F64: =F53 -> 2030
A65: =Sales!A77 -> Drummi | B65: =B62 -> 974.664 | C65: =C62 -> 2016.1877 | D65: =D62 -> 3936.8035 | E65: =E62 -> 6812.7157 | F65: =F62 -> 10304.62
A66: =Sales!A78 -> Gallon | B66: =I62 -> 339.14475 | C66: =J62 -> 701.68962 | D66: =K62 -> 1369.1066 | E66: =L62 -> 2365.0364 | F66: =M62 -> 3548.1913
A67: =Sales!A79 -> Litre | B67: =P62 -> 58.0955 | C67: =Q62 -> 120.19659 | D67: =R62 -> 234.54042 | E67: =S62 -> 405.229 | F67: =T62 -> 607.62944
A68: =Sales!A80 | B68: =SUM(B65:B67) -> 1371.9043 | C68: =SUM(C65:C67) -> 2838.0739 | D68: =SUM(D65:D67) -> 5540.4506 | E68: =SUM(E65:E67) -> 9582.981 | F68: =SUM(F65:F67) -> 14460.441
A70: Admin Costs | B70: (PKR Mn)
C71: =B64 -> 2026 | D71: =C64 -> 2027 | E71: =D64 -> 2028 | F71: =E64 -> 2029 | G71: =F64 -> 2030
A72: Utilities | C72: ='Income Statement'!B$7*Assumptions!C111 -> 68.595213 | D72: ='Income Statement'!C$7*Assumptions!D111 -> 113.52296 | E72: ='Income Statement'!D$7*Assumptions!E111 -> 166.21352 | F72: ='Income Statement'!E$7*Assumptions!F111 -> 191.65962 | G72: ='Income Statement'!F$7*Assumptions!G111 -> 289.20882
A73: Salaries (Indirect Labor) | C73: ='Income Statement'!B$7*Assumptions!C112 -> 192.0666 | D73: ='Income Statement'!C$7*Assumptions!D112 -> 340.56887 | E73: ='Income Statement'!D$7*Assumptions!E112 -> 554.04506 | F73: ='Income Statement'!E$7*Assumptions!F112 -> 766.63848 | G73: ='Income Statement'!F$7*Assumptions!G112 -> 1012.2309
A74: Misc. Admin Expenses | C74: ='Income Statement'!B$7*Assumptions!C113 -> 96.033298 | D74: ='Income Statement'!C$7*Assumptions!D113 -> 170.28444 | E74: ='Income Statement'!D$7*Assumptions!E113 -> 277.02253 | F74: ='Income Statement'!E$7*Assumptions!F113 -> 383.31924 | G74: ='Income Statement'!F$7*Assumptions!G113 -> 578.41763
A75: Total | C75: =SUM(C72:C74) -> 356.69511 | D75: =SUM(D72:D74) -> 624.37626 | E75: =SUM(E72:E74) -> 997.2811 | F75: =SUM(F72:F74) -> 1341.6173 | G75: =SUM(G72:G74) -> 1879.8573
A77: Selling Costs | B77: (PKR Mn)
C78: =C71 -> 2026 | D78: =D71 -> 2027 | E78: =E71 -> 2028 | F78: =F71 -> 2029 | G78: =G71 -> 2030
A79: Salaries Sales | C79: ='Income Statement'!B$6*Assumptions!C117 -> 88.162042 | D79: ='Income Statement'!C$6*Assumptions!D117 -> 183.12432 | E79: ='Income Statement'!D$6*Assumptions!E117 -> 356.7176 | F79: ='Income Statement'!E$6*Assumptions!F117 -> 613.47861 | G79: ='Income Statement'!F$6*Assumptions!G117 -> 915.10756
A80: Marketing | C80: ='Income Statement'!B$6*Assumptions!C118 -> 176.32408 | D80: ='Income Statement'!C$6*Assumptions!D118 -> 366.24863 | E80: ='Income Statement'!D$6*Assumptions!E118 -> 713.43519 | F80: ='Income Statement'!E$6*Assumptions!F118 -> 1226.9572 | G80: ='Income Statement'!F$6*Assumptions!G118 -> 1525.1793
A81: Promotions | C81: ='Income Statement'!B$6*Assumptions!C119 -> 58.774695 | D81: ='Income Statement'!C$6*Assumptions!D119 -> 122.08288 | E81: ='Income Statement'!D$6*Assumptions!E119 -> 237.81173 | F81: ='Income Statement'!E$6*Assumptions!F119 -> 408.98574 | G81: ='Income Statement'!F$6*Assumptions!G119 -> 610.07171
A82: Total | C82: =SUM(C79:C81) -> 323.26082 | D82: =SUM(D79:D81) -> 671.45583 | E82: =SUM(E79:E81) -> 1307.9645 | F82: =SUM(F79:F81) -> 2249.4216 | G82: =SUM(G79:G81) -> 3050.3585

Sheet Fixed Assets
A1: Fixed Assets Schedule | B1: (PKR Mn)
A3: 2026
B4: Begin Assets | C4: New Capex | D4: Updated Assets | E4: Depreciation | F4: Ending Assets
A5: Land | B5: 0 | C5: =Assumptions!C131 -> 22 | D5: =+B5+C5 -> 22 | E5: 0 | F5: =D5-E5 -> 22
A6: Building | B6: 0 | C6: =Assumptions!C132 -> 28 | D6: =+B6+C6 -> 28 | E6: 0 | F6: =D6-E6 -> 28
A7: Machinery | B7: 0 | C7: =Assumptions!C133 -> 60 | D7: =+B7+C7 -> 60 | E7: =D7*Assumptions!$C$139 -> 12 | F7: =D7-E7 -> 48
A8: Vehicles | B8: 0 | C8: =Assumptions!C134 -> 10 | D8: =+B8+C8 -> 10 | E8: =D8*Assumptions!$C$139 -> 2 | F8: =D8-E8 -> 8
A9: Retail outlets/Others | B9: 0 | C9: =Assumptions!C135 -> 18 | D9: =+B9+C9 -> 18 | E9: =D9*Assumptions!$C$139 -> 3.6 | F9: =D9-E9 -> 14.4
A10: Total | B10: =SUM(B5:B9) -> 0 | C10: =SUM(C5:C9) -> 138 | D10: =SUM(D5:D9) -> 138 | E10: =SUM(E5:E9) -> 17.6 | F10: =SUM(F5:F9) -> 120.4
A12: =+A3+1 -> 2027
B13: Begin Assets | C13: New Capex | D13: Updated Assets | E13: Depreciation | F13: Ending Assets
A14: =A5 -> Land | B14: =F5 -> 22 | C14: =Assumptions!D131 -> 0 | D14: =+B14+C14 -> 22 | E14: =+E5 -> 0 | F14: =D14-E14 -> 22
A15: =A6 -> Building | B15: =F6 -> 28 | C15: =Assumptions!D132 -> 0 | D15: =+B15+C15 -> 28 | E15: =E6 -> 0 | F15: =D15-E15 -> 28
A16: =A7 -> Machinery | B16: =F7 -> 48 | C16: =Assumptions!D133 -> 10 | D16: =+B16+C16 -> 58 | E16: =D16*Assumptions!$C$139 -> 11.6 | F16: =D16-E16 -> 46.4
A17: =A8 -> Vehicles | B17: =F8 -> 8 | C17: =Assumptions!D134 -> 2 | D17: =+B17+C17 -> 10 | E17: =D17*Assumptions!$C$139 -> 2 | F17: =D17-E17 -> 8
A18: =A9 -> Retail outlets/Others | B18: =F9 -> 14.4 | C18: =Assumptions!D135 -> 5 | D18: =+B18+C18 -> 19.4 | E18: =D18*Assumptions!$C$139 -> 3.88 | F18: =D18-E18 -> 15.52
A19: Total | B19: =SUM(B14:B18) -> 120.4 | C19: =SUM(C14:C18) -> 17 | D19: =SUM(D14:D18) -> 137.4 | E19: =SUM(E14:E18) -> 17.48 | F19: =SUM(F14:F18) -> 119.92
A21: =+A12+1 -> 2028
B22: Begin Assets | C22: New Capex | D22: Updated Assets | E22: Depreciation | F22: Ending Assets
A23: =A14 -> Land | B23: =F14 -> 22 | C23: =Assumptions!E131 -> 0 | D23: =+B23+C23 -> 22 | E23: =+E14 -> 0 | F23: =D23-E23 -> 22
A24: =A15 -> Building | B24: =F15 -> 28 | C24: =Assumptions!E132 -> 0 | D24: =+B24+C24 -> 28 | E24: =E6 -> 0 | F24: =D24-E24 -> 28
A25: =A16 -> Machinery | B25: =F16 -> 46.4 | C25: =Assumptions!E133 -> 6 | D25: =+B25+C25 -> 52.4 | E25: =D25*Assumptions!$C$139 -> 10.48 | F25: =D25-E25 -> 41.92
A26: =A17 -> Vehicles | B26: =F17 -> 8 | C26: =Assumptions!E134 -> 1 | D26: =+B26+C26 -> 9 | E26: =D26*Assumptions!$C$139 -> 1.8 | F26: =D26-E26 -> 7.2
A27: =A18 -> Retail outlets/Others | B27: =F18 -> 15.52 | C27: =Assumptions!E135 -> 4 | D27: =+B27+C27 -> 19.52 | E27: =D27*Assumptions!$C$139 -> 3.904 | F27: =D27-E27 -> 15.616
A28: Total | B28: =SUM(B23:B27) -> 119.92 | C28: =SUM(C23:C27) -> 11 | D28: =SUM(D23:D27) -> 130.92 | E28: =SUM(E23:E27) -> 16.184 | F28: =SUM(F23:F27) -> 114.736
A30: =+A21+1 -> 2029
B31: Begin Assets | C31: New Capex | D31: Updated Assets | E31: Depreciation | F31: Ending Assets
A32: =A23 -> Land | B32: =F23 -> 22 | C32: =Assumptions!F131 -> 0 | D32: =+B32+C32 -> 22 | E32: =+E23 -> 0 | F32: =D32-E32 -> 22
A33: =A24 -> Building | B33: =F24 -> 28 | C33: =Assumptions!F132 -> 0 | D33: =+B33+C33 -> 28 | E33: =E6 -> 0 | F33: =D33-E33 -> 28
A34: =A25 -> Machinery | B34: =F25 -> 41.92 | C34: =Assumptions!F133 -> 6 | D34: =+B34+C34 -> 47.92 | E34: =D34*Assumptions!$C$139 -> 9.584 | F34: =D34-E34 -> 38.336
A35: =A26 -> Vehicles | B35: =F26 -> 7.2 | C35: =Assumptions!F134 -> 1 | D35: =+B35+C35 -> 8.2 | E35: =D35*Assumptions!$C$139 -> 1.64 | F35: =D35-E35 -> 6.56
A36: =A27 -> Retail outlets/Others | B36: =F27 -> 15.616 | C36: =Assumptions!F135 -> 4 | D36: =+B36+C36 -> 19.616 | E36: =D36*Assumptions!$C$139 -> 3.9232 | F36: =D36-E36 -> 15.6928
A37: Total | B37: =SUM(B32:B36) -> 114.736 | C37: =SUM(C32:C36) -> 11 | D37: =SUM(D32:D36) -> 125.736 | E37: =SUM(E32:E36) -> 15.1472 | F37: =SUM(F32:F36) -> 110.5888
A39: =+A30+1 -> 2030
B40: Begin Assets | C40: New Capex | D40: Updated Assets | E40: Depreciation | F40: Ending Assets
A41: =A32 -> Land | B41: =F32 -> 22 | C41: =Assumptions!G131 -> 0 | D41: =+B41+C41 -> 22 | E41: =+E32 -> 0 | F41: =D41-E41 -> 22
A42: =A33 -> Building | B42: =F33 -> 28 | C42: =Assumptions!G132 -> 0 | D42: =+B42+C42 -> 28 | E42: =E6 -> 0 | F42: =D42-E42 -> 28
A43: =A34 -> Machinery | B43: =F34 -> 38.336 | C43: =Assumptions!G133 -> 5 | D43: =+B43+C43 -> 43.336 | E43: =D43*Assumptions!$C$139 -> 8.6672 | F43: =D43-E43 -> 34.6688
A44: =A35 -> Vehicles | B44: =F35 -> 6.56 | C44: =Assumptions!G134 -> 1 | D44: =+B44+C44 -> 7.56 | E44: =D44*Assumptions!$C$139 -> 1.512 | F44: =D44-E44 -> 6.048
A45: =A36 -> Retail outlets/Others | B45: =F36 -> 15.6928 | C45: =Assumptions!G135 -> 5 | D45: =+B45+C45 -> 20.6928 | E45: =D45*Assumptions!$C$139 -> 4.13856 | F45: =D45-E45 -> 16.55424
A46: Total | B46: =SUM(B41:B45) -> 110.5888 | C46: =SUM(C41:C45) -> 11 | D46: =SUM(D41:D45) -> 121.5888 | E46: =SUM(E41:E45) -> 14.31776 | F46: =SUM(F41:F45) -> 107.27104

Sheet Working Capital
A1: Working Capital
D3: =Assumptions!D2 -> 2026 | E3: =Assumptions!E2 -> 2027 | F3: =Assumptions!F2 -> 2028 | G3: =Assumptions!G2 -> 2029 | H3: =Assumptions!H2 -> 2030
A5: AR Turnover | B5: (times) | D5: =365/Assumptions!C123 -> 8.1111111 | E5: =365/Assumptions!D123 -> 8.1111111 | F5: =365/Assumptions!E123 -> 9.125 | G5: =365/Assumptions!F123 -> 9.125 | H5: =365/Assumptions!G123 -> 9.125
A6: AP Turnover | B6: (times) | D6: =365/Assumptions!C124 -> 4.5625 | E6: =365/Assumptions!D124 -> 4.8666667 | F6: =365/Assumptions!E124 -> 5.2142857 | G6: =365/Assumptions!F124 -> 5.6153846 | H6: =365/Assumptions!G124 -> 5.6153846
A7: Inv Turnover | B7: (times) | D7: =365/Assumptions!C125 -> 6.6363636 | E7: =365/Assumptions!D125 -> 7.3 | F7: =365/Assumptions!E125 -> 8.1111111 | G7: =365/Assumptions!F125 -> 9.125 | H7: =365/Assumptions!G125 -> 9.125
A9: Acc Rec | B9: PKR Mn | D9: ='Income Statement'!B$6/'Working Capital'!D5 -> 362.30976 | E9: ='Income Statement'!C$6/'Working Capital'!E5 -> 752.56569 | F9: ='Income Statement'!D$6/'Working Capital'!F5 -> 1303.078 | G9: ='Income Statement'!E$6/'Working Capital'!G5 -> 2241.0178 | H9: ='Income Statement'!F$6/'Working Capital'!H5 -> 3342.8587
A10: Acc Pay | B10: PKR Mn | D10: ='Income Statement'!B$7/'Working Capital'!D6 -> 300.69134 | E10: ='Income Statement'!C$7/'Working Capital'!E6 -> 583.16587 | F10: ='Income Statement'!D$7/'Working Capital'!F6 -> 1062.5522 | G10: ='Income Statement'!E$7/'Working Capital'!G6 -> 1706.5583 | H10: ='Income Statement'!F$7/'Working Capital'!H6 -> 2575.147
A11: Inv | B11: PKR Mn | D11: ='Income Statement'!B$7/'Working Capital'!D7 -> 206.7253 | E11: ='Income Statement'!C$7/'Working Capital'!E7 -> 388.77725 | F11: ='Income Statement'!D$7/'Working Capital'!F7 -> 683.06925 | G11: ='Income Statement'!E$7/'Working Capital'!G7 -> 1050.1897 | H11: ='Income Statement'!F$7/'Working Capital'!H7 -> 1584.7058

Sheet Equity
A1: Equity
C2: =Assumptions!D2 -> 2026 | D2: =Assumptions!E2 -> 2027 | E2: =Assumptions!F2 -> 2028 | F2: =Assumptions!G2 -> 2029 | G2: =Assumptions!H2 -> 2030
A3: Begin Capital | C3: 0 | D3: =C6 -> 100 | E3: =D6 -> 300 | F3: =E6 -> 400 | G3: =F6 -> 400
A4: Capital Injected | C4: =Assumptions!C143 -> 100 | D4: =Assumptions!D143 -> 200 | E4: =Assumptions!E143 -> 100 | F4: =Assumptions!F143 -> 0 | G4: =Assumptions!G143 -> 0
A5: Capital Withdrawn | C5: =Assumptions!C144 -> 0 | D5: =Assumptions!D144 -> 0 | E5: =Assumptions!E144 -> 0 | F5: =Assumptions!F144 -> 0 | G5: =Assumptions!G144 -> 0
A6: Ending Capital | C6: =C3+C4-C5 -> 100 | D6: =D3+D4-D5 -> 300 | E6: =E3+E4-E5 -> 400 | F6: =F3+F4-F5 -> 400 | G6: =G3+G4-G5 -> 400
A9: Begin Retained Earnings | C9: 0 | D9: =C12 -> 531.50342 | E9: =D12 -> 1671.7078 | F9: =E12 -> 3935.1625 | G9: =F12 -> 8044.5327
A10: Net Income | C10: ='Income Statement'!B18 -> 590.55935 | D10: ='Income Statement'!C18 -> 1341.4169 | E10: ='Income Statement'!D18 -> 2829.3184 | F10: ='Income Statement'!E18 -> 5136.7127 | G10: ='Income Statement'!F18 -> 7874.2444
A11: Dividend Paid | C11: =IF(C10>=0,C10*Assumptions!C$146,0) -> 59.055935 | D11: =IF(D10>=0,D10*Assumptions!D$146,0) -> 201.21253 | E11: =IF(E10>=0,E10*Assumptions!E$146,0) -> 565.86369 | F11: =IF(F10>=0,F10*Assumptions!F$146,0) -> 1027.3425 | G11: =IF(G10>=0,G10*Assumptions!G$146,0) -> 1574.8489
A12: Ending Retained Earnings | C12: =C9+C10-C11 -> 531.50342 | D12: =D9+D10-D11 -> 1671.7078 | E12: =E9+E10-E11 -> 3935.1625 | F12: =F9+F10-F11 -> 8044.5327 | G12: =G9+G10-G11 -> 14343.928

Sheet Short Term Loan
A1: Short Term Loan | C1: (PKR Mn)
C3: ='Income Statement'!C3 -> 2027 | D3: ='Income Statement'!D3 -> 2028 | E3: ='Income Statement'!E3 -> 2029 | F3: ='Income Statement'!F3 -> 2030 | G3: ='Income Statement'!G3
A5: Beginning Bal | C5: 0 | D5: =+C7 -> 0 | E5: =+D7 -> 0 | F5: =+E7 -> 0 | G5: =+F7 -> 0
A6: ST Loan Disbursed/ (Repaid) | C6: =-MIN(C5,('Cash Flow Statement'!C31+'Cash Flow Statement'!C11+'Cash Flow Statement'!C20+'Cash Flow Statement'!C23+'Cash Flow Statement'!C24+'Cash Flow Statement'!C26+'Cash Flow Statement'!C27)) -> 0 | D6: =-MIN(D5,('Cash Flow Statement'!D31+'Cash Flow Statement'!D11+'Cash Flow Statement'!D20+'Cash Flow Statement'!D23+'Cash Flow Statement'!D24+'Cash Flow Statement'!D26+'Cash Flow Statement'!D27)) -> 0 | E6: =-MIN(E5,('Cash Flow Statement'!E31+'Cash Flow Statement'!E11+'Cash Flow Statement'!E20+'Cash Flow Statement'!E23+'Cash Flow Statement'!E24+'Cash Flow Statement'!E26+'Cash Flow Statement'!E27)) -> 0 | F6: =-MIN(F5,('Cash Flow Statement'!F31+'Cash Flow Statement'!F11+'Cash Flow Statement'!F20+'Cash Flow Statement'!F23+'Cash Flow Statement'!F24+'Cash Flow Statement'!F26+'Cash Flow Statement'!F27)) -> 0 | G6: =-MIN(G5,('Cash Flow Statement'!G31+'Cash Flow Statement'!G11+'Cash Flow Statement'!G20+'Cash Flow Statement'!G23+'Cash Flow Statement'!G24+'Cash Flow Statement'!G26+'Cash Flow Statement'!G27)) -> 0
A7: Ending Bal | C7: =+C5+C6 -> 0 | D7: =+D5+D6 -> 0 | E7: =+E5+E6 -> 0 | F7: =+F5+F6 -> 0 | G7: =+G5+G6 -> 0
A9: Interest | C9: =AVERAGE(C5,C7)*(Assumptions!D$8+Assumptions!$C$152) -> 0 | D9: =AVERAGE(D5,D7)*(Assumptions!E$8+Assumptions!$C$152) -> 0 | E9: =AVERAGE(E5,E7)*(Assumptions!F$8+Assumptions!$C$152) -> 0 | F9: =AVERAGE(F5,F7)*(Assumptions!G$8+Assumptions!$C$152) -> 0 | G9: =AVERAGE(G5,G7)*(Assumptions!H$8+Assumptions!$C$152) -> 0

Sheet Long Term Loan
A1: Long Term Loan
C2: =Assumptions!D2 -> 2026 | D2: =Assumptions!E2 -> 2027 | E2: =Assumptions!F2 -> 2028 | F2: =Assumptions!G2 -> 2029 | G2: =Assumptions!H2 -> 2030
A4: Begin LTL | C4: 0 | D4: =+C7 -> 500 | E4: =+D7 -> 375 | F4: =+E7 -> 250 | G4: =+F7 -> 125
A5: Loan Disburse | C5: =Assumptions!C150 -> 500 | D5: =Assumptions!D150 -> 0 | E5: =Assumptions!E150 -> 0 | F5: =Assumptions!F150 -> 0 | G5: =Assumptions!G150 -> 0
A6: Principal Rpmt | C6: 0 | D6: =Assumptions!C$150/(Assumptions!$C$153-Assumptions!$C$154) -> 125 | E6: =+D6 -> 125 | F6: =+E6 -> 125 | G6: =+F6 -> 125 | H6: =+G6 -> 125 | I6: =+H6 -> 125
A7: Ending LTL | C7: =+C4+C5-C6 -> 500 | D7: =+D4+D5-D6 -> 375 | E7: =+E4+E5-E6 -> 250 | F7: =+F4+F5-F6 -> 125 | G7: =+G4+G5-G6 -> 0
A9: CPLTL | C9: =D6 -> 125 | D9: =E6 -> 125 | E9: =F6 -> 125 | F9: =G6 -> 125 | G9: =H6 -> 125
A10: LTL | C10: =+C7-C9 -> 375 | D10: =+D7-D9 -> 250 | E10: =+E7-E9 -> 125 | F10: =+F7-F9 -> 0 | G10: =+G7-G9 -> -125
A12: Interest | C12: =AVERAGE(C4,C7)*(Assumptions!D8+Assumptions!$C$152) -> 37.5 | D12: =AVERAGE(D4,D7)*(Assumptions!E8+Assumptions!$C$152) -> 63.4375 | E12: =AVERAGE(E4,E7)*(Assumptions!F8+Assumptions!$C$152) -> 43.75 | F12: =AVERAGE(F4,F7)*(Assumptions!G8+Assumptions!$C$152) -> 25.3125 | G12: =AVERAGE(G4,G7)*(Assumptions!H8+Assumptions!$C$152) -> 8.125

Sheet Income Statement
A1: Income Statement
B3: 2026 | C3: =B3+1 -> 2027 | D3: =C3+1 -> 2028 | E3: =D3+1 -> 2029 | F3: =E3+1 -> 2030
A4: Gross Sales | B4: =Sales!C80 -> 3467.707 | C4: =Sales!D80 -> 7202.8898 | D4: =Sales!E80 -> 14030.892 | E4: =Sales!F80 -> 24130.159 | F4: =Sales!G80 -> 35994.231
A5: Sales Tax | B5: =B4-B6 -> 528.97225 | C5: =C4-C6 -> 1098.7459 | D5: =D4-D6 -> 2140.3056 | E5: =E4-E6 -> 3680.8717 | F5: =F4-F6 -> 5490.6454
A6: Net Sales | B6: =B4/(1+Assumptions!$C$27) -> 2938.7347 | C6: =C4/(1+Assumptions!$C$27) -> 6104.1439 | D6: =D4/(1+Assumptions!$C$27) -> 11890.587 | E6: =E4/(1+Assumptions!$C$27) -> 20449.287 | F6: =F4/(1+Assumptions!$C$27) -> 30503.585
A7: COS | B7: =Cost!B68 -> 1371.9043 | C7: =Cost!C68 -> 2838.0739 | D7: =Cost!D68 -> 5540.4506 | E7: =Cost!E68 -> 9582.981 | F7: =Cost!F68 -> 14460.441
A8: Gross Profit | B8: =B6-B7 -> 1566.8305 | C8: =C6-C7 -> 3266.07 | D8: =D6-D7 -> 6350.136 | E8: =E6-E7 -> 10866.306 | F8: =F6-F7 -> 16043.145
A9: Selling Expenses | B9: =Cost!C82 -> 323.26082 | C9: =Cost!D82 -> 671.45583 | D9: =Cost!E82 -> 1307.9645 | E9: =Cost!F82 -> 2249.4216 | F9: =Cost!G82 -> 3050.3585
A10: Admin. Expenses | B10: =Cost!C75 -> 356.69511 | C10: =Cost!D75 -> 624.37626 | D10: =Cost!E75 -> 997.2811 | E10: =Cost!F75 -> 1341.6173 | F10: =Cost!G75 -> 1879.8573
A11: EBITDA | B11: =B8-(B9+B10) -> 886.87457 | C11: =C8-(C9+C10) -> 1970.2379 | D11: =D8-(D9+D10) -> 4044.8904 | E11: =E8-(E9+E10) -> 7275.2671 | F11: =F8-(F9+F10) -> 11112.929
A12: Depreciation | B12: ='Fixed Assets'!E10 -> 17.6 | C12: ='Fixed Assets'!E19 -> 17.48 | D12: ='Fixed Assets'!E28 -> 16.184 | E12: ='Fixed Assets'!E37 -> 15.1472 | F12: ='Fixed Assets'!E46 -> 14.31776
A13: Amortization | B13: =Assumptions!$B$173/Assumptions!$B$174 -> 0.00083333333 | C13: =Assumptions!$B$173/Assumptions!$B$174 -> 0.00083333333 | D13: =Assumptions!$B$173/Assumptions!$B$174 -> 0.00083333333 | E13: =Assumptions!$B$173/Assumptions!$B$174 -> 0.00083333333 | F13: =Assumptions!$B$173/Assumptions!$B$174 -> 0.00083333333
A14: EBIT | B14: =B11-(B12+B13) -> 869.27374 | C14: =C11-(C12+C13) -> 1952.7571 | D14: =D11-(D12+D13) -> 4028.7056 | E14: =E11-(E12+E13) -> 7260.1191 | F14: =F11-(F12+F13) -> 11098.61
A15: Interest | B15: ='Long Term Loan'!C12+'Short Term Loan'!C9 -> 37.5 | C15: ='Long Term Loan'!D12+'Short Term Loan'!D9 -> 63.4375 | D15: ='Long Term Loan'!E12+'Short Term Loan'!E9 -> 43.75 | E15: ='Long Term Loan'!F12+'Short Term Loan'!F9 -> 25.3125 | F15: ='Long Term Loan'!G12+'Short Term Loan'!G9 -> 8.125
A16: EBT | B16: =B14-B15 -> 831.77374 | C16: =C14-C15 -> 1889.3196 | D16: =D14-D15 -> 3984.9556 | E16: =E14-E15 -> 7234.8066 | F16: =F14-F15 -> 11090.485
A17: Tax | B17: =B16*Assumptions!$C$28 -> 241.21438 | C17: =C16*Assumptions!$C$28 -> 547.90267 | D17: =D16*Assumptions!$C$28 -> 1155.6371 | E17: =E16*Assumptions!$C$28 -> 2098.0939 | F17: =F16*Assumptions!$C$28 -> 3216.2407
A18: Net Income | B18: =B16-B17 -> 590.55935 | C18: =C16-C17 -> 1341.4169 | D18: =D16-D17 -> 2829.3184 | E18: =E16-E17 -> 5136.7127 | F18: =F16-F17 -> 7874.2444

Sheet Balance Sheet
A1: Balance Sheet | B1: (PKR Mn)
C3: =Assumptions!E2 -> 2027 | D3: =Assumptions!F2 -> 2028 | E3: =Assumptions!G2 -> 2029 | F3: =Assumptions!H2 -> 2030
A4: Assets
A5: Current Assets
A6: Cash | C6: ='Cash Flow Statement'!D32 -> 1668.6107 | D6: ='Cash Flow Statement'!E32 -> 3546.8315 | E6: ='Cash Flow Statement'!F32 -> 6874.2947 | F6: ='Cash Flow Statement'!G32 -> 12284.24
A7: Acc Receivables | C7: ='Working Capital'!E9 -> 752.56569 | D7: ='Working Capital'!F9 -> 1303.078 | E7: ='Working Capital'!G9 -> 2241.0178 | F7: ='Working Capital'!H9 -> 3342.8587
A8: Inventory | C8: ='Working Capital'!E11 -> 388.77725 | D8: ='Working Capital'!F11 -> 683.06925 | E8: ='Working Capital'!G11 -> 1050.1897 | F8: ='Working Capital'!H11 -> 1584.7058
A9: Other CA | C9: 0 | D9: 0 | E9: 0 | F9: 0
A10: Total Current Assets | C10: =SUM(C6:C9) -> 2809.9536 | D10: =SUM(D6:D9) -> 5532.9787 | E10: =SUM(E6:E9) -> 10165.502 | F10: =SUM(F6:F9) -> 17211.804
A12: Non-Current Assets
A13: ='Fixed Assets'!A5 -> Land | C13: ='Fixed Assets'!F14 -> 22 | D13: ='Fixed Assets'!F23 -> 22 | E13: ='Fixed Assets'!F32 -> 22 | F13: ='Fixed Assets'!F41 -> 22
A14: ='Fixed Assets'!A6 -> Building | C14: ='Fixed Assets'!F15 -> 28 | D14: ='Fixed Assets'!F24 -> 28 | E14: ='Fixed Assets'!F33 -> 28 | F14: ='Fixed Assets'!F42 -> 28
A15: ='Fixed Assets'!A7 -> Machinery | C15: ='Fixed Assets'!F16 -> 46.4 | D15: ='Fixed Assets'!F25 -> 41.92 | E15: ='Fixed Assets'!F34 -> 38.336 | F15: ='Fixed Assets'!F43 -> 34.6688
A16: ='Fixed Assets'!A8 -> Vehicles | C16: ='Fixed Assets'!F17 -> 8 | D16: ='Fixed Assets'!F26 -> 7.2 | E16: ='Fixed Assets'!F35 -> 6.56 | F16: ='Fixed Assets'!F44 -> 6.048
A17: ='Fixed Assets'!A9 -> Retail outlets/Others | C17: ='Fixed Assets'!F18 -> 15.52 | D17: ='Fixed Assets'!F27 -> 15.616 | E17: ='Fixed Assets'!F36 -> 15.6928 | F17: ='Fixed Assets'!F45 -> 16.55424
A18: Investments | C18: 0 | D18: 0 | E18: 0 | F18: 0
A19: Total Non-Current Assets | C19: =SUM(C13:C18) -> 119.92 | D19: =SUM(D13:D18) -> 114.736 | E19: =SUM(E13:E18) -> 110.5888 | F19: =SUM(F13:F18) -> 107.27104
A20: Total Assets | C20: =+C10+C19 -> 2929.8736 | D20: =+D10+D19 -> 5647.7147 | E20: =+E10+E19 -> 10276.091 | F20: =+F10+F19 -> 17319.075
A23: Liabilities
A24: Current Liab
A25: Acc Payable | C25: ='Working Capital'!E10 -> 583.16587 | D25: ='Working Capital'!F10 -> 1062.5522 | E25: ='Working Capital'!G10 -> 1706.5583 | F25: ='Working Capital'!H10 -> 2575.147
A26: Short Term Loans | C26: =+'Short Term Loan'!D7 -> 0 | D26: =+'Short Term Loan'!E7 -> 0 | E26: =+'Short Term Loan'!F7 -> 0 | F26: =+'Short Term Loan'!G7 -> 0
A27: CPLTL | C27: ='Long Term Loan'!D9 -> 125 | D27: ='Long Term Loan'!E9 -> 125 | E27: ='Long Term Loan'!F9 -> 125 | F27: ='Long Term Loan'!G9 -> 125
A28: Other CL | C28: 0 | D28: 0 | E28: 0 | F28: 0
A29: Total Current Liabilities | C29: =SUM(C25:C28) -> 708.16587 | D29: =SUM(D25:D28) -> 1187.5522 | E29: =SUM(E25:E28) -> 1831.5583 | F29: =SUM(F25:F28) -> 2700.147
A31: Non-Current Liab
A32: Long Term Loans | C32: ='Long Term Loan'!D10 -> 250 | D32: ='Long Term Loan'!E10 -> 125 | E32: ='Long Term Loan'!F10 -> 0 | F32: ='Long Term Loan'!G10 -> -125
A33: Other Non-Curr Liab | C33: 0 | D33: 0 | E33: 0 | F33: 0
A34: Total Long Term Liab | C34: =+C32+C33 -> 250 | D34: =+D32+D33 -> 125 | E34: =+E32+E33 -> 0 | F34: =+F32+F33 -> -125
A35: Total Liabilities | C35: =+C29+C34 -> 958.16587 | D35: =+D29+D34 -> 1312.5522 | E35: =+E29+E34 -> 1831.5583 | F35: =+F29+F34 -> 2575.147
A37: Equity
A38: Capital | C38: =Equity!D6 -> 300 | D38: =Equity!E6 -> 400 | E38: =Equity!F6 -> 400 | F38: =Equity!G6 -> 400
A39: Retained Earnings | C39: =Equity!D12 -> 1671.7078 | D39: =Equity!E12 -> 3935.1625 | E39: =Equity!F12 -> 8044.5327 | F39: =Equity!G12 -> 14343.928
A40: Total Equity | C40: =+C38+C39 -> 1971.7078 | D40: =+D38+D39 -> 4335.1625 | E40: =+E38+E39 -> 8444.5327 | F40: =+F38+F39 -> 14743.928
A42: Total Liab & Equity | C42: =+C35+C40 -> 2929.8736 | D42: =+D35+D40 -> 5647.7147 | E42: =+E35+E40 -> 10276.091 | F42: =+F35+F40 -> 17319.075
A44: Diff. | C44: =+C20-C42 -> 0 | D44: =+D20-D42 -> 0 | E44: =+E20-E42 -> 0 | F44: =+F20-F42 -> 0

Sheet Cash Flow Statement
A1: Cash Flow Statement
C3: =Assumptions!D2 -> 2026 | D3: =Assumptions!E2 -> 2027 | E3: =Assumptions!F2 -> 2028 | F3: =Assumptions!G2 -> 2029 | G3: =Assumptions!H2 -> 2030
A4: CF - Operating
A5: Net Income | C5: ='Income Statement'!B18 -> 590.55935 | D5: ='Income Statement'!C18 -> 1341.4169 | E5: ='Income Statement'!D18 -> 2829.3184 | F5: ='Income Statement'!E18 -> 5136.7127 | G5: ='Income Statement'!F18 -> 7874.2444
A6: Dep/ Amort | C6: ='Income Statement'!B12 -> 17.6 | D6: ='Income Statement'!C12 -> 17.48 | E6: ='Income Statement'!D12 -> 16.184 | F6: ='Income Statement'!E12 -> 15.1472 | G6: ='Income Statement'!F12 -> 14.31776
A7: Change in AR | C7: ='Working Capital'!C9-'Working Capital'!D9 -> -362.30976 | D7: ='Working Capital'!D9-'Working Capital'!E9 -> -390.25592 | E7: ='Working Capital'!E9-'Working Capital'!F9 -> -550.51229 | F7: ='Working Capital'!F9-'Working Capital'!G9 -> -937.93979 | G7: ='Working Capital'!G9-'Working Capital'!H9 -> -1101.8409
A8: Change Inv | C8: ='Working Capital'!C11-'Working Capital'!D11 -> -206.7253 | D8: ='Working Capital'!D11-'Working Capital'!E11 -> -182.05195 | E8: ='Working Capital'!E11-'Working Capital'!F11 -> -294.292 | F8: ='Working Capital'!F11-'Working Capital'!G11 -> -367.12046 | G8: ='Working Capital'!G11-'Working Capital'!H11 -> -534.51614
A9: Change in AP | C9: ='Working Capital'!D10-'Working Capital'!C10 -> 300.69134 | D9: ='Working Capital'!E10-'Working Capital'!D10 -> 282.47453 | E9: ='Working Capital'!F10-'Working Capital'!E10 -> 479.38629 | F9: ='Working Capital'!G10-'Working Capital'!F10 -> 644.00611 | G9: ='Working Capital'!H10-'Working Capital'!G10 -> 868.58872
A10: Change in Other CA/CL | C10: 0 | D10: 0 | E10: 0 | F10: 0 | G10: 0
A11: CFO | C11: =SUM(C5:C10) -> 339.81563 | D11: =SUM(D5:D10) -> 1069.0635 | E11: =SUM(E5:E10) -> 2480.0844 | F11: =SUM(F5:F10) -> 4490.8058 | G11: =SUM(G5:G10) -> 7120.7939
A13: CF - Investing
A14: ='Fixed Assets'!A41 -> Land | C14: =-Assumptions!C131 -> -22 | D14: =-Assumptions!D131 -> 0 | E14: =-Assumptions!E131 -> 0 | F14: =-Assumptions!F131 -> 0 | G14: =-Assumptions!G131 -> 0
A15: ='Fixed Assets'!A42 -> Building | C15: =-Assumptions!C132 -> -28 | D15: =-Assumptions!D132 -> 0 | E15: =-Assumptions!E132 -> 0 | F15: =-Assumptions!F132 -> 0 | G15: =-Assumptions!G132 -> 0
A16: ='Fixed Assets'!A43 -> Machinery | C16: =-Assumptions!C133 -> -60 | D16: =-Assumptions!D133 -> -10 | E16: =-Assumptions!E133 -> -6 | F16: =-Assumptions!F133 -> -6 | G16: =-Assumptions!G133 -> -5
A17: ='Fixed Assets'!A44 -> Vehicles | C17: =-Assumptions!C134 -> -10 | D17: =-Assumptions!D134 -> -2 | E17: =-Assumptions!E134 -> -1 | F17: =-Assumptions!F134 -> -1 | G17: =-Assumptions!G134 -> -1
A18: ='Fixed Assets'!A45 -> Retail outlets/Others | C18: =-Assumptions!C135 -> -18 | D18: =-Assumptions!D135 -> -5 | E18: =-Assumptions!E135 -> -4 | F18: =-Assumptions!F135 -> -4 | G18: =-Assumptions!G135 -> -5
A19: Inv in Other FA | C19: 0 | D19: 0 | E19: 0 | F19: 0 | G19: 0
A20: CFI | C20: =SUM(C14:C19) -> -138 | D20: =SUM(D14:D19) -> -17 | E20: =SUM(E14:E19) -> -11 | F20: =SUM(F14:F19) -> -11 | G20: =SUM(G14:G19) -> -11
A22: CF - Financing
A23: Net Capital Injection | C23: =Assumptions!C143-Assumptions!C144 -> 100 | D23: =Assumptions!D143-Assumptions!D144 -> 200 | E23: =Assumptions!E143-Assumptions!E144 -> 100 | F23: =Assumptions!F143-Assumptions!F144 -> 0 | G23: =Assumptions!G143-Assumptions!G144 -> 0
A24: Net LTL | C24: ='Long Term Loan'!C5-'Long Term Loan'!C6 -> 500 | D24: ='Long Term Loan'!D5-'Long Term Loan'!D6 -> -125 | E24: ='Long Term Loan'!E5-'Long Term Loan'!E6 -> -125 | F24: ='Long Term Loan'!F5-'Long Term Loan'!F6 -> -125 | G24: ='Long Term Loan'!G5-'Long Term Loan'!G6 -> -125
A25: STL | C25: ='Short Term Loan'!C6 -> 0 | D25: ='Short Term Loan'!D6 -> 0 | E25: ='Short Term Loan'!E6 -> 0 | F25: ='Short Term Loan'!F6 -> 0 | G25: ='Short Term Loan'!G6 -> 0
A26: Dividend Paid | C26: =-Equity!C11 -> -59.055935 | D26: =-Equity!D11 -> -201.21253 | E26: =-Equity!E11 -> -565.86369 | F26: =-Equity!F11 -> -1027.3425 | G26: =-Equity!G11 -> -1574.8489
A27: Others | C27: 0 | D27: 0 | E27: 0 | F27: 0 | G27: 0
A28: CFF | C28: =+SUM(C23:C27) -> 540.94406 | D28: =+SUM(D23:D27) -> -126.21253 | E28: =+SUM(E23:E27) -> -590.86369 | F28: =+SUM(F23:F27) -> -1152.3425 | G28: =+SUM(G23:G27) -> -1699.8489
A30: Net Change in Cash | C30: =+C11+C20+C28 -> 742.7597 | D30: =+D11+D20+D28 -> 925.85101 | E30: =+E11+E20+E28 -> 1878.2207 | F30: =+F11+F20+F28 -> 3327.4632 | G30: =+G11+G20+G28 -> 5409.945
A31: Beginning Cash | C31: 0 | D31: =+C32 -> 742.7597 | E31: =+D32 -> 1668.6107 | F31: =+E32 -> 3546.8315 | G31: =+F32 -> 6874.2947
A32: Ending Cash | C32: =+C30+C31 -> 742.7597 | D32: =+D30+D31 -> 1668.6107 | E32: =+E30+E31 -> 3546.8315 | F32: =+F30+F31 -> 6874.2947 | G32: =+G30+G31 -> 12284.24

Sheet Valuation
A1: DCF Valuation
C2: ='Cash Flow Statement'!C3 -> 2026 | D2: ='Cash Flow Statement'!D3 -> 2027 | E2: ='Cash Flow Statement'!E3 -> 2028 | F2: ='Cash Flow Statement'!F3 -> 2029 | G2: ='Cash Flow Statement'!G3 -> 2030
A4: Net Income | C4: ='Income Statement'!B18 -> 590.55935 | D4: ='Income Statement'!C18 -> 1341.4169 | E4: ='Income Statement'!D18 -> 2829.3184 | F4: ='Income Statement'!E18 -> 5136.7127 | G4: ='Income Statement'!F18 -> 7874.2444
A5: Interest | C5: =+'Income Statement'!B15 -> 37.5 | D5: =+'Income Statement'!C15 -> 63.4375 | E5: =+'Income Statement'!D15 -> 43.75 | F5: =+'Income Statement'!E15 -> 25.3125 | G5: =+'Income Statement'!F15 -> 8.125
A6: Dep/Amort | C6: ='Income Statement'!B12 -> 17.6 | D6: ='Income Statement'!C12 -> 17.48 | E6: ='Income Statement'!D12 -> 16.184 | F6: ='Income Statement'!E12 -> 15.1472 | G6: ='Income Statement'!F12 -> 14.31776
A7: Change in WC | C7: =+'Cash Flow Statement'!C7+'Cash Flow Statement'!C8+'Cash Flow Statement'!C9 -> -268.34372 | D7: =+'Cash Flow Statement'!D7+'Cash Flow Statement'!D8+'Cash Flow Statement'!D9 -> -289.83334 | E7: =+'Cash Flow Statement'!E7+'Cash Flow Statement'!E8+'Cash Flow Statement'!E9 -> -365.418 | F7: =+'Cash Flow Statement'!F7+'Cash Flow Statement'!F8+'Cash Flow Statement'!F9 -> -661.05414 | G7: =+'Cash Flow Statement'!G7+'Cash Flow Statement'!G8+'Cash Flow Statement'!G9 -> -767.76831
A8: Capex | C8: ='Cash Flow Statement'!C20 -> -138 | D8: ='Cash Flow Statement'!D20 -> -17 | E8: ='Cash Flow Statement'!E20 -> -11 | F8: ='Cash Flow Statement'!F20 -> -11 | G8: ='Cash Flow Statement'!G20 -> -11
A9: Free Cash Flow to Firm | C9: =SUM(C4:C8) -> 239.31563 | D9: =SUM(D4:D8) -> 1115.501 | E9: =SUM(E4:E8) -> 2512.8344 | F9: =SUM(F4:F8) -> 4505.1183 | G9: =SUM(G4:G8) -> 7117.9189
A10: Terminal Value | G10: =G9*(1+Assumptions!B158)/(Assumptions!B157-Assumptions!B158) -> #REF!
A11: FCFF with TV | C11: =+C9+C10 -> 239.31563 | D11: =+D9+D10 -> 1115.501 | E11: =+E9+E10 -> 2512.8344 | F11: =+F9+F10 -> 4505.1183 | G11: =+G9+G10 -> #REF!
A13: NPV | B13: {=NPV(Assumptions!B158,Valuation!C11:G11)} -> #REF!
A14: NPV (USD) | B14: =+B13/Assumptions!D7 -> #REF!
B15: 5
B16: =+B15/B14 -> #REF!

Sheet Ratios
D2: ='Cash Flow Statement'!C3 -> 2026 | E2: ='Cash Flow Statement'!D3 -> 2027 | F2: ='Cash Flow Statement'!E3 -> 2028 | G2: ='Cash Flow Statement'!F3 -> 2029 | H2: ='Cash Flow Statement'!G3 -> 2030
A3: Vertical Analysis
A4: Gross Profit Margin | D4: ='Income Statement'!B8/'Income Statement'!B6 -> 0.53316499 | E4: ='Income Statement'!C8/'Income Statement'!C6 -> 0.53505783 | F4: ='Income Statement'!D8/'Income Statement'!D6 -> 0.53404733 | G4: ='Income Statement'!E8/'Income Statement'!E6 -> 0.53137823 | H4: ='Income Statement'!F8/'Income Statement'!F6 -> 0.52594291
A5: Operating Profit Margin | D5: ='Income Statement'!B14/'Income Statement'!B6 -> 0.29579864 | E5: ='Income Statement'!C14/'Income Statement'!C6 -> 0.31990679 | F5: ='Income Statement'!D14/'Income Statement'!D6 -> 0.3388147 | G5: ='Income Statement'!E14/'Income Statement'!E6 -> 0.35503043 | H5: ='Income Statement'!F14/'Income Statement'!F6 -> 0.36384609
A6: Net Profit Margin | D6: ='Income Statement'!B18/'Income Statement'!B6 -> 0.20095701 | E6: ='Income Statement'!C18/'Income Statement'!C6 -> 0.21975512 | F6: ='Income Statement'!D18/'Income Statement'!D6 -> 0.23794608 | G6: ='Income Statement'!E18/'Income Statement'!E6 -> 0.25119275 | H6: ='Income Statement'!F18/'Income Statement'!F6 -> 0.2581416
A7: Current Assets/TotalAssets | D7: =#REF!/#REF! -> #REF! | E7: ='Balance Sheet'!C10/'Balance Sheet'!C20 -> 0.95906991 | F7: ='Balance Sheet'!D10/'Balance Sheet'!D20 -> 0.97968453 | G7: ='Balance Sheet'!E10/'Balance Sheet'!E20 -> 0.98923824 | H7: ='Balance Sheet'!F10/'Balance Sheet'!F20 -> 0.99380619
A8: Cash/TotalAssets | D8: =#REF!/#REF! -> #REF! | E8: ='Balance Sheet'!C$6/'Balance Sheet'!C$20 -> 0.56951627 | F8: ='Balance Sheet'!D$6/'Balance Sheet'!D$20 -> 0.6280118 | G8: ='Balance Sheet'!E$6/'Balance Sheet'!E$20 -> 0.66896009 | H8: ='Balance Sheet'!F$6/'Balance Sheet'!F$20 -> 0.70928958
A9: Short term loan/TotalAssets | D9: =#REF!/#REF! -> #REF! | E9: ='Balance Sheet'!C26/'Balance Sheet'!C20 -> 0 | F9: ='Balance Sheet'!D26/'Balance Sheet'!D20 -> 0 | G9: ='Balance Sheet'!E26/'Balance Sheet'!E20 -> 0 | H9: ='Balance Sheet'!F26/'Balance Sheet'!F20 -> 0
A10: Long term loan/TotalAssets | D10: =#REF!/#REF! -> #REF! | E10: ='Balance Sheet'!C32/'Balance Sheet'!C20 -> 0.085327912 | F10: ='Balance Sheet'!D32/'Balance Sheet'!D20 -> 0.022132846 | G10: ='Balance Sheet'!E32/'Balance Sheet'!E20 -> 0 | H10: ='Balance Sheet'!F32/'Balance Sheet'!F20 -> -0.0072174754
A11: Equity/TotalAssets | D11: =#REF!/#REF! -> #REF! | E11: ='Balance Sheet'!C40/'Balance Sheet'!C20 -> 0.67296683 | F11: ='Balance Sheet'!D40/'Balance Sheet'!D20 -> 0.76759588 | G11: ='Balance Sheet'!E40/'Balance Sheet'!E20 -> 0.82176508 | H11: ='Balance Sheet'!F40/'Balance Sheet'!F20 -> 0.85131152
A14: Horizantal Analysis
A15: Gross Revenue | E15: =(('Income Statement'!C4)-'Income Statement'!B4)/'Income Statement'!B4 -> 1.0771333 | F15: =(('Income Statement'!D4)-'Income Statement'!C4)/'Income Statement'!C4 -> 0.94795319 | G15: =(('Income Statement'!E4)-'Income Statement'!D4)/'Income Statement'!D4 -> 0.71978792 | H15: =(('Income Statement'!F4)-'Income Statement'!E4)/'Income Statement'!E4 -> 0.49166986
A16: Net Income | E16: =(('Income Statement'!C18)-'Income Statement'!B18)/'Income Statement'!B18 -> 1.2714345 | F16: =(('Income Statement'!D18)-'Income Statement'!C18)/'Income Statement'!C18 -> 1.1092015 | G16: =(('Income Statement'!E18)-'Income Statement'!D18)/'Income Statement'!D18 -> 0.81553006 | H16: =(('Income Statement'!F18)-'Income Statement'!E18)/'Income Statement'!E18 -> 0.53293456
A17: Current Assessts | E17: =(('Balance Sheet'!C10)-#REF!)/#REF! -> #REF! | F17: =(('Balance Sheet'!D10)-'Balance Sheet'!C10)/'Balance Sheet'!C10 -> 0.96906404 | G17: =(('Balance Sheet'!E10)-'Balance Sheet'!D10)/'Balance Sheet'!D10 -> 0.8372567 | H17: =(('Balance Sheet'!F10)-'Balance Sheet'!E10)/'Balance Sheet'!E10 -> 0.69315828
A18: Inventory | E18: =(('Balance Sheet'!C8)-#REF!)/#REF! -> #REF! | F18: =(('Balance Sheet'!D8)-'Balance Sheet'!C8)/'Balance Sheet'!C8 -> 0.75696816 | G18: =(('Balance Sheet'!E8)-'Balance Sheet'!D8)/'Balance Sheet'!D8 -> 0.53745716 | H18: =(('Balance Sheet'!F8)-'Balance Sheet'!E8)/'Balance Sheet'!E8 -> 0.50897103
A19: Account receivable | E19: =(('Balance Sheet'!C7)-#REF!)/#REF! -> #REF! | F19: =(('Balance Sheet'!D7)-'Balance Sheet'!C7)/'Balance Sheet'!C7 -> 0.73151395 | G19: =(('Balance Sheet'!E7)-'Balance Sheet'!D7)/'Balance Sheet'!D7 -> 0.71978792 | H19: =(('Balance Sheet'!F7)-'Balance Sheet'!E7)/'Balance Sheet'!E7 -> 0.49166986
A20: Account payable | E20: =(('Balance Sheet'!C25)-#REF!)/#REF! -> #REF! | F20: =(('Balance Sheet'!D25)-'Balance Sheet'!C25)/'Balance Sheet'!C25 -> 0.82204105 | G20: =(('Balance Sheet'!E25)-'Balance Sheet'!D25)/'Balance Sheet'!D25 -> 0.60609364 | H20: =(('Balance Sheet'!F25)-'Balance Sheet'!E25)/'Balance Sheet'!E25 -> 0.50897103
A21: Short term loan
A22: Long term loan | E22: =IFERROR(('Balance Sheet'!C32-#REF!)/#REF!,0) -> 0 | F22: =IFERROR(('Balance Sheet'!D32-'Balance Sheet'!C32)/'Balance Sheet'!C32,0) -> -0.5 | G22: =IFERROR(('Balance Sheet'!E32-'Balance Sheet'!D32)/'Balance Sheet'!D32,0) -> -1 | H22: =IFERROR(('Balance Sheet'!F32-'Balance Sheet'!E32)/'Balance Sheet'!E32,0) -> 0
A23: Equity | E23: =(('Balance Sheet'!C40)-#REF!)/#REF! -> #REF! | F23: =(('Balance Sheet'!D40)-'Balance Sheet'!C40)/'Balance Sheet'!C40 -> 1.1986841 | G23: =(('Balance Sheet'!E40)-'Balance Sheet'!D40)/'Balance Sheet'!D40 -> 0.94791605 | H23: =(('Balance Sheet'!F40)-'Balance Sheet'!E40)/'Balance Sheet'!E40 -> 0.74597326
A27: Ratios
A28: Current Ratio | D28: =#REF!/#REF! -> #REF! | E28: ='Balance Sheet'!C10/'Balance Sheet'!C29 -> 3.9679315 | F28: ='Balance Sheet'!D10/'Balance Sheet'!D29 -> 4.6591458 | G28: ='Balance Sheet'!E10/'Balance Sheet'!E29 -> 5.5501931 | H28: ='Balance Sheet'!F10/'Balance Sheet'!F29 -> 6.3743953
A29: Quick Ratio | D29: =((#REF!)-#REF!)/#REF! -> #REF! | E29: =(('Balance Sheet'!C10)-'Balance Sheet'!C8)/'Balance Sheet'!C29 -> 3.4189397 | F29: =(('Balance Sheet'!D10)-'Balance Sheet'!D8)/'Balance Sheet'!D29 -> 4.0839549 | G29: =(('Balance Sheet'!E10)-'Balance Sheet'!E8)/'Balance Sheet'!E29 -> 4.9768072 | H29: =(('Balance Sheet'!F10)-'Balance Sheet'!F8)/'Balance Sheet'!F29 -> 5.7874991
A30: Return on equity | D30: ='Income Statement'!B18/#REF! -> #REF! | E30: ='Income Statement'!C18/'Balance Sheet'!C40 -> 0.6803325 | F30: ='Income Statement'!D18/'Balance Sheet'!D40 -> 0.65264415 | G30: ='Income Statement'!E18/'Balance Sheet'!E40 -> 0.60828857 | H30: ='Income Statement'!F18/'Balance Sheet'!F40 -> 0.53406693
A31: Return on Assests | D31: ='Income Statement'!B18/#REF! -> #REF! | E31: ='Income Statement'!C18/'Balance Sheet'!C20 -> 0.45784121 | F31: ='Income Statement'!D18/'Balance Sheet'!D20 -> 0.50096696 | G31: ='Income Statement'!E18/'Balance Sheet'!E20 -> 0.4998703 | H31: ='Income Statement'!F18/'Balance Sheet'!F20 -> 0.45465733
A32: Int. Coverage | D32: =IFERROR('Income Statement'!B14/'Income Statement'!B15,0) -> 23.180633 | E32: =IFERROR('Income Statement'!C14/'Income Statement'!C15,0) -> 30.782377 | F32: =IFERROR('Income Statement'!D14/'Income Statement'!D15,0) -> 92.084698 | G32: =IFERROR('Income Statement'!E14/'Income Statement'!E15,0) -> 286.81952 | H32: =IFERROR('Income Statement'!F14/'Income Statement'!F15,0) -> 1365.9828
A33: Total Loans/TA | D33: =(#REF!+#REF!+#REF!)/#REF! -> #REF! | E33: =('Balance Sheet'!C26+'Balance Sheet'!C27+'Balance Sheet'!C32)/'Balance Sheet'!C20 -> 0.12799187 | F33: =('Balance Sheet'!D26+'Balance Sheet'!D27+'Balance Sheet'!D32)/'Balance Sheet'!D20 -> 0.044265692 | G33: =('Balance Sheet'!E26+'Balance Sheet'!E27+'Balance Sheet'!E32)/'Balance Sheet'!E20 -> 0.012164159 | H33: =('Balance Sheet'!F26+'Balance Sheet'!F27+'Balance Sheet'!F32)/'Balance Sheet'!F20 -> 0
A34: Total Loans/Equity | D34: =(#REF!+#REF!+#REF!)/#REF! -> #REF! | E34: =('Balance Sheet'!C26+'Balance Sheet'!C27+'Balance Sheet'!C32)/'Balance Sheet'!C40 -> 0.19019046 | F34: =('Balance Sheet'!D26+'Balance Sheet'!D27+'Balance Sheet'!D32)/'Balance Sheet'!D40 -> 0.057667965 | G34: =('Balance Sheet'!E26+'Balance Sheet'!E27+'Balance Sheet'!E32)/'Balance Sheet'!E40 -> 0.014802477 | H34: =('Balance Sheet'!F26+'Balance Sheet'!F27+'Balance Sheet'!F32)/'Balance Sheet'!F40 -> 0

Sheet Dupont Analysis
B3: Roe = Net profit margin x Asset Turnover x Equity Multiplier
B5: Roe = (Net Income/net sales) x (Net Sales / Total Assets) x (Total Assets/Equity) | C5: 2026 | D5: 2027 | E5: 2028 | F5: =E5+1 -> 2029 | G5: =F5+1 -> 2030
C6: =(Ratios!D6)*(('Income Statement'!B6/#REF!))*((#REF!/#REF!)) -> #REF! | D6: =(Ratios!E6)*(('Income Statement'!C6/'Balance Sheet'!C20))*(('Balance Sheet'!C20/'Balance Sheet'!C40)) -> 0.6803325 | E6: =(Ratios!F6)*(('Income Statement'!D6/'Balance Sheet'!D20))*(('Balance Sheet'!D20/'Balance Sheet'!D40)) -> 0.65264415 | F6: =(Ratios!G6)*(('Income Statement'!E6/'Balance Sheet'!E20))*(('Balance Sheet'!E20/'Balance Sheet'!E40)) -> 0.60828857 | G6: =(Ratios!H6)*(('Income Statement'!F6/'Balance Sheet'!F20))*(('Balance Sheet'!F20/'Balance Sheet'!F40)) -> 0.53406693
B8: ROE declines due to equity growth and deleveraging, while profitability and shareholder value continue to improve.

Sheet Break-even analysis
A1: Break-even analysis
A3: Year | B3: Net Sales | C3: Variable Costs (COS) | D3: Fixed Costs | E3: Contribution Margin | F3: CM Ratio | G3: Break-Even Revenue | J3: Year | K3: Total Revenue (TR) | L3: Total Costs (TC) | M3: Fixed Costs (FC) | N3: Break-Even Revenue (BEP)
A4: =Assumptions!D$2 -> 2026 | B4: ='Income Statement'!B6 -> 2938.7347 | C4: ='Income Statement'!B7 -> 1371.9043 | D4: ='Income Statement'!B9+'Income Statement'!B10+'Income Statement'!B12+'Income Statement'!B13+'Income Statement'!B15 -> 735.05676 | E4: =B4-C4 -> 1566.8305 | F4: =E4/B4 -> 0.53316499 | G4: =D4/F4 -> 1378.6666 | J4: 2026 | K4: =B4 -> 2938.7347 | L4: =C4+D4 -> 2106.961 | M4: =D4 -> 735.05676 | N4: =G4 -> 1378.6666
A5: =A4+1 -> 2027 | B5: ='Income Statement'!C6 -> 6104.1439 | C5: ='Income Statement'!C7 -> 2838.0739 | D5: ='Income Statement'!C9+'Income Statement'!C10+'Income Statement'!C12+'Income Statement'!C13+'Income Statement'!C15 -> 1376.7504 | E5: =B5-C5 -> 3266.07 | F5: =E5/B5 -> 0.53505783 | G5: =D5/F5 -> 2573.0872 | J5: 2027 | K5: =B5 -> 6104.1439 | L5: =C5+D5 -> 4214.8243 | M5: =D5 -> 1376.7504 | N5: =G5 -> 2573.0872
A6: =A5+1 -> 2028 | B6: ='Income Statement'!D6 -> 11890.587 | C6: ='Income Statement'!D7 -> 5540.4506 | D6: ='Income Statement'!D9+'Income Statement'!D10+'Income Statement'!D12+'Income Statement'!D13+'Income Statement'!D15 -> 2365.1805 | E6: =B6-C6 -> 6350.136 | F6: =E6/B6 -> 0.53404733 | G6: =D6/F6 -> 4428.7843 | J6: 2028 | K6: =B6 -> 11890.587 | L6: =C6+D6 -> 7905.631 | M6: =D6 -> 2365.1805 | N6: =G6 -> 4428.7843
A7: =A6+1 -> 2029 | B7: ='Income Statement'!E6 -> 20449.287 | C7: ='Income Statement'!E7 -> 9582.981 | D7: ='Income Statement'!E9+'Income Statement'!E10+'Income Statement'!E12+'Income Statement'!E13+'Income Statement'!E15 -> 3631.4995 | E7: =B7-C7 -> 10866.306 | F7: =E7/B7 -> 0.53137823 | G7: =D7/F7 -> 6834.1141 | J7: 2029 | K7: =B7 -> 20449.287 | L7: =C7+D7 -> 13214.481 | M7: =D7 -> 3631.4995 | N7: =G7 -> 6834.1141
A8: =A7+1 -> 2030 | B8: ='Income Statement'!F6 -> 30503.585 | C8: ='Income Statement'!F7 -> 14460.441 | D8: ='Income Statement'!F9+'Income Statement'!F10+'Income Statement'!F12+'Income Statement'!F13+'Income Statement'!F15 -> 4952.6594 | E8: =B8-C8 -> 16043.145 | F8: =E8/B8 -> 0.52594291 | G8: =D8/F8 -> 9416.7243 | J8: 2030 | K8: =B8 -> 30503.585 | L8: =C8+D8 -> 19413.1 | M8: =D8 -> 4952.6594 | N8: =G8 -> 9416.7243
